Workbook
Name CLASS: #REF!
Name CLASS: #REF!
Name CLASS: #REF!
Name CLASS: #REF!
Name CLASS: #REF!
Name CLASS: #REF!
Name CODE: #REF!
Name CODE: #REF!
Name CODE: #REF!
Name CODE: #REF!
Name CODE: #REF!
Name CODE: #REF!
Name CODE: #REF!
Name COURSE_NAME: #REF!
Name COURSE_NAME: #REF!
Name COURSE_NAME: #REF!
Name COURSE_NAME: #REF!
Name COURSE_NAME: #REF!
Name COURSE_NAME: #REF!
Name COURSE_NAME: #REF!
Name EXAMINER: #REF!
Name EXAMINER: #REF!
Name EXAMINER: #REF!
Name EXAMINER: #REF!
Name EXAMINER: #REF!
Name EXAMINER: #REF!
Name EXAMINER: #REF!
Name hy: #REF!
Name po: #REF!
Name room_no: #REF!
Name ROOM_NO.: #REF!
Name ROOM_NO.: #REF!
Name ROOM_NO.: #REF!
Name ROOM_NO.: #REF!
Name ROOM_NO.: #REF!
Name ROOM_NO.: #REF!
Name STDS: #REF!
Name STDS: #REF!
Name STDS: #REF!
Name STDS: #REF!
Name STDS: #REF!
Name STDS: #REF!
Name STDS: #REF!
Name TO_PRT: #REF!
Name TO_PRT: #REF!
Name TO_PRT: #REF!
Name TO_PRT: #REF!
Name TO_PRT: #REF!
Name TO_PRT: #REF!
Name TO_PRT: #REF!
Name Total_F1: [1]TT!$D$666:$D$681
Name Total_F1: '[2]TT (Working)'!$D$668:$D$683
Name Total_F1: '[2]TT (Working)'!$D$668:$D$683
Name Total_F1_1: [3]TT!$D$226:$D$238
Name Total_F1_1: '[4]TT (MAIN)'!$D$183:$D$215
Name Total_F1_1: [5]TT!$D$206:$D$219
Name Total_F1_2: [3]TT!$D$252:$D$267
Name Total_F1_2: [5]TT!$D$225:$D$227
Name Total_F1_3: [3]TT!$D$277:$D$290
Name Total_F1_3: [5]TT!$D$245:$D$261

Sheet TT 
A1: Monday, 23 February 2026 | I1: =CONCATENATE(A1,",",B1,",",E1) -> Monday, 23 February 2026,,
A2: Session, 1 (8:15AM - 9:15 AM) | I2: =CONCATENATE(A2,",",B2,",",E2) -> Session, 1 (8:15AM - 9:15 AM),, | L2: COMPARE
A3: CODE | B3: COURSE NAME | C3: EXAMINER | D3: CLASS | E3: # STDS | F3: ROOM NO. | G3: TO PRT | I3: =CONCATENATE(A3,",",B3,",",E3) -> CODE ,COURSE NAME ,# STDS
A4: MATH 351 | B4: {=IFERROR(VLOOKUP(I4:I31,Lecturers!A2:G597,7,FALSE),0)} -> NUMERICAL ANALYSIS | C4: {=IFERROR(VLOOKUP(I4:I31,Lecturers!A2:G597,2,FALSE),0)} -> Azure Isaac | D4: ED3-ME | E4: {=IFERROR(VLOOKUP(I4:I31,Lecturers!A2:G597,3,FALSE),0)} -> 230 | F4: Computer Based | G4: =1.1*E4 -> 253 | I4: =CONCATENATE(A4,",",D4) -> MATH 351,ED3-ME
A5: MATH 351 | B5: NUMERICAL ANALYSIS | C5: Azure Isaac | D5: ED3-AUTO | E5: 47 | F5: Computer Based | G5: =1.1*E5 -> 51.7 | I5: =CONCATENATE(A5,",",D5) -> MATH 351,ED3-AUTO
A6: MATH 351 | B6: NUMERICAL METHODS | C6: Azure Isaac | D6: ED3-BME | E6: 94 | F6: Computer Based | G6: =1.1*E6 -> 103.4 | I6: =CONCATENATE(A6,",",D6) -> MATH 351,ED3-BME
A7: MATH 351 | B7: NUMERICAL ANALYSIS | C7: Borkor Reindorf Nartey | D7: ED3-AERO | E7: 76 | F7: Computer Based | G7: =1.1*E7 -> 83.6 | I7: =CONCATENATE(A7,",",D7) -> MATH 351,ED3-AERO
A8: MATH 351 | B8: NUMERICAL ANALYSIS | C8: Borkor Reindorf Nartey | D8: ED3-AE | E8: 105 | F8: Computer Based | G8: =1.1*E8 -> 115.5 | I8: =CONCATENATE(A8,",",D8) -> MATH 351,ED3-AE
A9: MATH 351 | B9: NUMERICAL ANALYSIS | C9: Borkor Reindorf Nartey | D9: ED3-GEOL | E9: 154 | F9: Computer Based | G9: =1.1*E9 -> 169.4 | I9: =CONCATENATE(A9,",",D9) -> MATH 351,ED3-GEOL
A10: MATH 351 | B10: NUMERICAL ANALYSIS | C10: Borkor Reindorf Nartey | D10: ED3-COE | E10: 276 | F10: Computer Based | G10: =1.1*E10 -> 303.6 | I10: =CONCATENATE(A10,",",D10) -> MATH 351,ED3-COE
A11: MATH 351 | B11: NUMERICAL ANALYSIS | C11: Awashie Gaston Edem | D11: ED3-TEL | E11: 147 | F11: Computer Based | G11: =1.1*E11 -> 161.7 | I11: =CONCATENATE(A11,",",D11) -> MATH 351,ED3-TEL
A12: MATH 351 | B12: NUMERICAL ANALYSIS | C12: Awashie Gaston Edem | D12: ED3-EE | E12: 254 | F12: Computer Based | G12: =1.1*E12 -> 279.4 | I12: =CONCATENATE(A12,",",D12) -> MATH 351,ED3-EE
A13: MATH 351 | B13: NUMERICAL ANALYSIS | C13: Awashie Gaston Edem | D13: ED3-IND | E13: 72 | F13: Computer Based | G13: =1.1*E13 -> 79.2 | I13: =CONCATENATE(A13,",",D13) -> MATH 351,ED3-IND
A14: MATH 351 | B14: NUMERICAL ANALYSIS | C14: Awashie Gaston Edem | D14: ED3-MARI | E14: 40 | F14: Computer Based | G14: =1.1*E14 -> 44 | I14: =CONCATENATE(A14,",",D14) -> MATH 351,ED3-MARI
A15: MATH 351 | B15: NUMERICAL ANALYSIS | C15: Borkor Reindorf Nartey | D15: ED3-CE | E15: 223 | F15: Computer Based | G15: =1.1*E15 -> 245.3 | I15: =CONCATENATE(A15,",",D15) -> MATH 351,ED3-CE
A16: PE 351 | B16: PETROLEUM ROCK MECHANICS | C16: Erzuah Samuel | D16: ED3-PE | E16: 82 | F16: EA/A110/VCR | G16: =1.1*E16 -> 90.2 | H16: 27/30/25 | I16: =CONCATENATE(A16,",",D16) -> PE 351,ED3-PE
A17: ACF 255 | B17: FINANCIAL ACCOUNTING I | C17: Yeboah Edward | D17: ED2-BME | E17: 16 | F17: N1 | G17: =1.1*E17 -> 17.6 | H17: 16 | I17: =CONCATENATE(A17,",",D17) -> ACF 255,ED2-BME
A18: ACF 255 | B18: FINANCIAL ACCOUNTING I | C18: Yeboah Edward | D18: ED2-COE | E18: 61 | F18: 303/304/206 | G18: =1.1*E18 -> 67.1 | H18: 25/20/16 | I18: =CONCATENATE(A18,",",D18) -> ACF 255,ED2-COE
A19: ACF 255 | B19: FINANCIAL ACCOUNTING I | C19: Yeboah Edward | D19: ED2-TEL | E19: 35 | F19: LT/RMB | G19: =1.1*E19 -> 38.5 | H19: 20/15 | I19: =CONCATENATE(A19,",",D19) -> ACF 255,ED2-TEL
A20: ACF 255 | B20: FINANCIAL ACCOUNTING I | C20: Yeboah Edward | D20: ED2-MSE | E20: 13 | F20: N1 | G20: =1.1*E20 -> 14.3 | H20: 13 | I20: =CONCATENATE(A20,",",D20) -> ACF 255,ED2-MSE
A21: ACF 255 | B21: FINANCIAL ACCOUNTING I | C21: Yeboah Edward | D21: ED3-GEOM | E21: 34 | F21: 206/RMB | G21: =1.1*E21 -> 37.4 | H21: 20/14 | I21: =CONCATENATE(A21,",",D21) -> ACF 255,ED3-GEOM
A22: ACF 255 | B22: FINANCIAL ACCOUNTING I | C22: Yeboah Edward | D22: ED1-GEOL | E22: 3 | F22: RMA | G22: =1.1*E22 -> 3.3 | H22: 3 | I22: =CONCATENATE(A22,",",D22) -> ACF 255,ED1-GEOL
A23: MSE 151 | B23: INTRODUCTION TO THERMODYNAMICS OF MATERIALS | C23: Gikunoo Emmanuel | D23: ED1-MSE | E23: 98 | F23: PB001/PB208/PB008 | G23: =1.1*E23 -> 107.8 | H23: 45/30/23 | I23: =CONCATENATE(A23,",",D23) -> MSE 151,ED1-MSE
A24: BME 161 | B24: CELL BIOLOGY | C24: Adjei Prince Ebenezer | D24: ED1-BME | E24: 136 | F24: PB201/PB214/PB020/PB212 | G24: =1.1*E24 -> 149.6 | H24: 40/40/40/16 | I24: =CONCATENATE(A24,",",D24) -> BME 161,ED1-BME
A25: GE 261 | B25: FIELD AND GEODETIC ASTRONOMY | C25: Ayer John Wise Divine | D25: ED2-GEOM | E25: 134 | F25: PB201/PB214/PB014/PB208 | G25: =1.1*E25 -> 147.4 | H25: 40/40/35/20 | I25: =CONCATENATE(A25,",",D25) -> GE 261,ED2-GEOM
A26: GE 151 | B26: CARTOGRAPHY I | C26: Quaye-Ballard Jonathan Arthur | D26: ED1-GEOM | E26: 100 | F26: 303/LT/VSLA | G26: =1.1*E26 -> 110 | H26: 30/30/40 | I26: =CONCATENATE(A26,",",D26) -> GE 151,ED1-GEOM
A27: EE 161 | B27: TRANSFORMERS | C27: Opoku Daniel | D27: ED1-EE | E27: 287 | F27: NEB-SF/NEB-TF/NEB-FF1/NEB-FF2/NAF1 | G27: =1.1*E27 -> 315.7 | H27: 85/80/55/30/37 | I27: =CONCATENATE(A27,",",D27) -> EE 161,ED1-EE
A28: GED 475 | B28: PRINCIPLES OF HYDROGEOLOGY | C28: Appiah-Adjei Emmanuel Kwame | D28: ED4-GEOL | E28: 102 | F28: NAF1/EA/A110 | G28: =1.1*E28 -> 112.2 | H28: 45/30/27 | I28: =CONCATENATE(A28,",",D28) -> GED 475,ED4-GEOL
A29: PE 459 | B29: NATURAL GAS ENGINEERING I | C29: Sarkodie Kwame | D29: ED4-PE | E29: 103 | F29: RMA/VSLA/304/N2 | G29: =1.1*E29 -> 113.3 | H29: 20/40/20/23 | I29: =CONCATENATE(A29,",",D29) -> PE 459,ED4-PE
... A31: GED 253 | B31: PHYSICAL GEOLOGY | C31: Mensah Emmanuel | D31: ED2-GEOL | E31: 154 | F31: PB014/PB001/PB020/PB008 | G31: =1.1*E31 -> 169.4 | H31: 42/42/42/28 | I31: =CONCATENATE(A31,",",D31) -> GED 253,ED2-GEOL
D32: Total M1 | E32: =SUM(E16:E31) -> 1618 | I32: =CONCATENATE(A32,",",D32) -> ,Total M1
I33: =CONCATENATE(A33,",",D33) -> ,
I34: =CONCATENATE(A34,",",D34) -> ,
A35: Monday, 23 February 2026 | I35: =CONCATENATE(A35,",",D35) -> Monday, 23 February 2026,
A36: Session, 2 (10:00AM - 11:00 AM) | I36: =CONCATENATE(A36,",",D36) -> Session, 2 (10:00AM - 11:00 AM),
A37: CODE | B37: COURSE NAME | C37: EXAMINER | D37: CLASS | E37: # STDS | F37: ROOM NO. | G37: TO PRT | I37: =CONCATENATE(A37,",",D37) -> CODE ,CLASS
A38: EE 467 | B38: {=IFERROR(VLOOKUP(I38:I49,Lecturers!A2:G597,7,FALSE),0)} -> POWER SYSTEMS OPERATION AND CONTROL | C38: {=IFERROR(VLOOKUP(I38:I49,Lecturers!A2:G597,2,FALSE),0)} -> Antoh Emmanuel Kwaku | D38: ED4-EE | E38: {=IFERROR(VLOOKUP(I38:I49,Lecturers!A2:G597,3,FALSE),0)} -> 224 | F38: VSLA/LT/303/304/206/RMA/RMB/N1/N2 | G38: =1.1*E38 -> 246.4 | H38: 45/30/30/20/20/20/20/20/20 | I38: =CONCATENATE(A38,",",D38) -> EE 467,ED4-EE
A39: COE 457 | B39: ARTIFICIAL INTELLIGENCE | C39: Nunoo-Mensah Henry | D39: ED4-COE | E39: 170 | F39: NEB-SF/NEB-FF1/NEB-FF2 | G39: =1.1*E39 -> 187 | H39: 85/55/30 | I39: =CONCATENATE(A39,",",D39) -> COE 457,ED4-COE
A40: CHE 255 | B40: FLUID TRANSPORT | C40: Momade Zsuzsanna Gál | D40: ED2-CHE | E40: 154 | F40: NEB-SF/NEB-FF1/NEB-FF2 | G40: =1.1*E40 -> 169.4 | H40: 80/46/28 | I40: =CONCATENATE(A40,",",D40) -> CHE 255,ED2-CHE
A41: CHE 255 | B41: FLUID TRANSPORT | C41: Dogbe Eunice Sefakor Aku | D41: ED2-PCE | E41: 59 | F41: 303/304/206 | G41: =1.1*E41 -> 64.9 | H41: 22/20/17 | I41: =CONCATENATE(A41,",",D41) -> CHE 255,ED2-PCE
A42: CE 457 | B42: DRAINAGE SYSTEMS | C42: Adjei Kwaku Amaning | D42: ED4-CE | E42: 245 | F42: PB001/PB020/PB014/PB201/PB214/PB212 | G42: =1.1*E42 -> 269.5 | H42: 45/45/45/45/45/20 | I42: =CONCATENATE(A42,",",D42) -> CE 457,ED4-CE
A43: BME 471 | B43: BIOINSTRUMENTATION II | C43: Acquah Isaac | D43: ED4-BME | E43: 84 | F43: PB008/PB208/PB212 | G43: =1.1*E43 -> 92.4 | H43: 30/30/24 | I43: =CONCATENATE(A43,",",D43) -> BME 471,ED4-BME
A44: MSE 353 | B44: PYROMETALLURGY | C44: Agyemang Frank Ofori | D44: ED3-METE | E44: 83 | F44: VSLA/RMA/RMB | G44: =1.1*E44 -> 91.3 | H44: 40/22/21 | I44: =CONCATENATE(A44,",",D44) -> MSE 353,ED3-METE
A45: MSE 353 | B45: PYROMETALLURGY | C45: Agyemang Frank Ofori | D45: ED3-MSE | E45: 89 | F45: NAF1/A110/VCR | G45: =1.1*E45 -> 97.9 | H45: 40/30/19 | I45: =CONCATENATE(A45,",",D45) -> MSE 353,ED3-MSE
A46: PCE 351 | B46: SEPARATION PROCESSES I | C46: Dogbe Eunice Sefakor Aku | D46: ED3-PCE | E46: 51 | F46: EA/ECR | G46: =1.1*E46 -> 56.1 | H46: 30/21 | I46: =CONCATENATE(A46,",",D46) -> PCE 351,ED3-PCE
A47: EE 265 | B47: ELECTRICAL SERVICES DESIGN | C47: Kwegyir Daniel | D47: ED2-EE | E47: 340 | F47: PB001/PB020/PB014/PB201/PB214/PB008/PB208/NEB-GF | G47: =1.1*E47 -> 374 | H47: 45/45/45/45/45/30/30/55 | I47: =CONCATENATE(A47,",",D47) -> EE 265,ED2-EE
A48: TE 451 | B48: FUNDAMENTALS OF NETWORK SECURITY | C48: Agyemang Justice Owusu | D48: ED4-TEL | E48: 142 | F48: NEB-TF | G48: =1.1*E48 -> 156.2 | H48: 142 | I48: =CONCATENATE(A48,",",D48) -> TE 451,ED4-TEL
A49: AE 453 | B49: ENVIRONMENTAL CONTROL AND LIVESTOCK HOUSING | C49: Lavie Jerome Dela | D49: ED4-AE | E49: 103 | F49: NAF1/EA/A110/VCR | G49: =1.1*E49 -> 113.3 | H49: 40/25/25/13 | I49: =CONCATENATE(A49,",",D49) -> AE 453,ED4-AE
D50: Total M2 | E50: =SUM(E38:E49) -> 1744 | I50: =CONCATENATE(A50,",",D50) -> ,Total M2
I51: =CONCATENATE(A51,",",D51) -> ,
I52: =CONCATENATE(A52,",",D52) -> ,
A53: Monday, 23 February 2026 | I53: =CONCATENATE(A53,",",D53) -> Monday, 23 February 2026,
A54: Session, 3 (11:45AM - 12:45 PM) | I54: =CONCATENATE(A54,",",D54) -> Session, 3 (11:45AM - 12:45 PM),
A55: CODE | B55: COURSE NAME | C55: EXAMINER | D55: CLASS | E55: # STDS | F55: ROOM NO. | G55: TO PRT | I55: =CONCATENATE(A55,",",D55) -> CODE ,CLASS
A56: ENGL 157 | B56: {=IFERROR(VLOOKUP(I56:I78,Lecturers!A2:G597,7,FALSE),0)} -> COMMUNICATION SKILLS I | C56: {=IFERROR(VLOOKUP(I56:I78,Lecturers!A2:G597,2,FALSE),0)} -> Yeboah Philomena Ama Okyeso | D56: ED1-MARI | E56: {=IFERROR(VLOOKUP(I56:I78,Lecturers!A2:G597,3,FALSE),0)} -> 46 | F56: Computer Based | G56: =1.1*E56 -> 50.6 | I56: =CONCATENATE(A56,",",D56) -> ENGL 157,ED1-MARI
A57: ENGL 157 | B57: COMMUNICATION SKILLS I | C57: Yeboah Philomena Ama Okyeso | D57: ED1-ME | E57: 223 | F57: Computer Based | G57: =1.1*E57 -> 245.3 | I57: =CONCATENATE(A57,",",D57) -> ENGL 157,ED1-ME
A58: ENGL 157 | B58: COMMUNICATION SKILLS I | C58: Yeboah Philomena Ama Okyeso | D58: ED1-GEOL | E58: 119 | F58: Computer Based | G58: =1.1*E58 -> 130.9 | I58: =CONCATENATE(A58,",",D58) -> ENGL 157,ED1-GEOL
A59: ENGL 157 | B59: COMMUNICATION SKILLS I | C59: Alhassan Yakubu | D59: ED1-TEL | E59: 129 | F59: Computer Based | G59: =1.1*E59 -> 141.9 | I59: =CONCATENATE(A59,",",D59) -> ENGL 157,ED1-TEL
A60: ENGL 157 | B60: COMMUNICATION SKILLS I | C60: Yeboah Philomena Ama Okyeso | D60: ED1-IND | E60: 81 | F60: Computer Based | G60: =1.1*E60 -> 89.1 | I60: =CONCATENATE(A60,",",D60) -> ENGL 157,ED1-IND
A61: ENGL 157 | B61: COMMUNICATION SKILLS I | C61: Sarfo-Adu Kwasi | D61: ED1-AUTO | E61: 88 | F61: Computer Based | G61: =1.1*E61 -> 96.8 | I61: =CONCATENATE(A61,",",D61) -> ENGL 157,ED1-AUTO
A62: ENGL 157 | B62: COMMUNICATION SKILLS I | C62: Alhassan Yakubu | D62: ED1-CE | E62: 242 | F62: Computer Based | G62: =1.1*E62 -> 266.2 | I62: =CONCATENATE(A62,",",D62) -> ENGL 157,ED1-CE
A63: AME 467 | B63: AUTOMOTIVE COMPRESSION-IGNITION ENGINES | C63: Abu Frimpong Solomon | D63: ED4-AUTO | E63: 32 | F63: VSLA | G63: =1.1*E63 -> 35.2 | H63: 32 | I63: =CONCATENATE(A63,",",D63) -> AME 467,ED4-AUTO
A64: PE 251 | B64: RESERVOIR ENGINEERING I | C64: Adenutsi Caspar Daniel | D64: ED2-PE | E64: 97 | F64: LT/303/304/RMA | G64: =1.1*E64 -> 106.7 | H64: 25/25/24/24 | I64: =CONCATENATE(A64,",",D64) -> PE 251,ED2-PE
A65: GE 461 | B65: CADASTRAL SURVEYING | C65: Akrofi Emmanuel Offei | D65: ED4-GEOM | E65: 93 | F65: PB201/PB214/PB208 | G65: =1.1*E65 -> 102.3 | H65: 40/40/13 | I65: =CONCATENATE(A65,",",D65) -> GE 461,ED4-GEOM
A66: IE 461 | B66: INDUSTRIAL SAFETY AND MANUFACTURING RELATIONS | C66: Asiedu Charlotte | D66: ED4-IND | E66: 67 | F66: NAF1/A110 | G66: =1.1*E66 -> 73.7 | H66: 40/27 | I66: =CONCATENATE(A66,",",D66) -> IE 461,ED4-IND
A67: CHE 461 | B67: COMPUTER OPTIMIZATION METHOD | C67: Bonsu Jude Kwaku | D67: ED4-CHE | E67: 114 | F67: NAF1/A110/EA/VCR | G67: =1.1*E67 -> 125.4 | H67: 45/25/25/20 | I67: =CONCATENATE(A67,",",D67) -> CHE 461,ED4-CHE
A68: CHE 461 | B68: COMPUTER OPTIMIZATION METHOD | C68: Bonsu Jude Kwaku | D68: ED4-PCE | E68: 8 | F68: 206 | G68: =1.1*E68 -> 8.8 | H68: 8 | I68: =CONCATENATE(A68,",",D68) -> CHE 461,ED4-PCE
A69: MSE 251 | B69: MOMENTUM TRANSPORT | C69: Adjaottor Albert Amatey | D69: ED2-MSE | E69: 80 | F69: LT/303/304 | G69: =1.1*E69 -> 88 | H69: 30/30/20 | I69: =CONCATENATE(A69,",",D69) -> MSE 251,ED2-MSE
A70: MSE 251 | B70: MOMENTUM TRANSPORT | C70: Adjaottor Albert Amatey | D70: ED2-METE | E70: 59 | F70: PB001/PB208 | G70: =1.1*E70 -> 64.9 | H70: 35/24 | I70: =CONCATENATE(A70,",",D70) -> MSE 251,ED2-METE
A71: ME 473 | B71: COMPUTER AIDED DESIGN AND MANUFACTURING | C71: Afriyie Nyarko Frank Kwabena | D71: ED4-AERO | E71: 61 | F71: N1/N2/206 | G71: =1.1*E71 -> 67.1 | H71: 20/20/21 | I71: =CONCATENATE(A71,",",D71) -> ME 473,ED4-AERO
A72: ME 473 | B72: COMPUTER AIDED DESIGN AND MANUFACTURING | C72: Afriyie Nyarko Frank Kwabena | D72: ED4-ME | E72: 144 | F72: NEB-SF/NEB-FF1/NEB-FF2 | G72: =1.1*E72 -> 158.4 | H72: 80/50/14 | I72: =CONCATENATE(A72,",",D72) -> ME 473,ED4-ME
A73: ME 159 | B73: TECHNICAL DRAWING | C73: Oppong Tawiah Peter | D73: ED1-PE | E73: 129 | F73: NEB-SF/NEB-FF1/NEB-FF2 | G73: =1.1*E73 -> 141.9 | H73: 70/35/24 | I73: =CONCATENATE(A73,",",D73) -> ME 159,ED1-PE
A74: ME 159 | B74: TECHNICAL DRAWING | C74: Oppong Tawiah Peter | D74: ED1-METE | E74: 72 | F74: PB201/PB214 | G74: =1.1*E74 -> 79.2 | H74: 36/36 | I74: =CONCATENATE(A74,",",D74) -> ME 159,ED1-METE
A75: ME 159 | B75: TECHNICAL DRAWING | C75: Oppong Tawiah Peter | D75: ED1-AERO | E75: 70 | F75: PB020/PB014/PB008 | G75: =1.1*E75 -> 77 | H75: 30/30/10 | I75: =CONCATENATE(A75,",",D75) -> ME 159,ED1-AERO
A76: ME 265 | B76: THERMODYNAMICS I | C76: Forson Francis Kofi | D76: ED2-AE | E76: 155 | F76: PB001/PB020/PB014/PB008 | G76: =1.1*E76 -> 170.5 | H76: 42/42/42/29 | I76: =CONCATENATE(A76,",",D76) -> ME 265,ED2-AE
A77: METE 457 | B77: CORROSION OF ENGINEERING MATERIALS | C77: Andrews Anthony | D77: ED4-METE | E77: 49 | F77: VSLA | G77: =1.1*E77 -> 53.9 | H77: 49 | I77: =CONCATENATE(A77,",",D77) -> METE 457,ED4-METE
A78: MSE 453 | B78: CORROSION OF ENGINEERING MATERIALS | C78: Andrews Anthony | D78: ED4-MSE | E78: 64 | F78: NEB-TF | G78: =1.1*E78 -> 70.4 | H78: 64 | I78: =CONCATENATE(A78,",",D78) -> MSE 453,ED4-MSE
D79: Total M3 | E79: =SUM(E63:E78) -> 1294 | I79: =CONCATENATE(A79,",",D79) -> ,Total M3
I80: =CONCATENATE(A80,",",D80) -> ,
I81: =CONCATENATE(A81,",",D81) -> ,
A82: Monday, 23 February 2026 | I82: =CONCATENATE(A82,",",D82) -> Monday, 23 February 2026,
A83: Session, 4 (1:30PM - 2:30 PM) | I83: =CONCATENATE(A83,",",D83) -> Session, 4 (1:30PM - 2:30 PM),
A84: CODE | B84: COURSE NAME | C84: EXAMINER | D84: CLASS | E84: # STDS | F84: ROOM NO. | G84: TO PRT | I84: =CONCATENATE(A84,",",D84) -> CODE ,CLASS
A85: ENGL 157 | B85: {=IFERROR(VLOOKUP(I85:I105,Lecturers!A2:G597,7,FALSE),0)} -> COMMUNICATION SKILLS I | C85: {=IFERROR(VLOOKUP(I85:I105,Lecturers!A2:G597,2,FALSE),0)} -> Sarfo-Adu Kwasi | D85: ED1-CHE | E85: {=IFERROR(VLOOKUP(I85:I105,Lecturers!A2:G597,3,FALSE),0)} -> 120 | F85: Computer Based | G85: =1.1*E85 -> 132 | I85: =CONCATENATE(A85,",",D85) -> ENGL 157,ED1-CHE
A86: ENGL 157 | B86: COMMUNICATION SKILLS I | C86: Yeboah Philomena Ama Okyeso | D86: ED1-PCE | E86: 56 | F86: Computer Based | G86: =1.1*E86 -> 61.6 | I86: =CONCATENATE(A86,",",D86) -> ENGL 157,ED1-PCE
A87: ENGL 157 | B87: COMMUNICATION SKILLS I | C87: Alhassan Yakubu | D87: ED1-BME | E87: 136 | F87: Computer Based | G87: =1.1*E87 -> 149.6 | I87: =CONCATENATE(A87,",",D87) -> ENGL 157,ED1-BME
A88: ENGL 157 | B88: COMMUNICATION SKILLS I | C88: Alhassan Yakubu | D88: ED1-COE | E88: 261 | F88: Computer Based | G88: =1.1*E88 -> 287.1 | I88: =CONCATENATE(A88,",",D88) -> ENGL 157,ED1-COE
A89: ENGL 157 | B89: COMMUNICATION SKILLS I | C89: Yeboah Philomena Ama Okyeso | D89: ED1-GEOM | E89: 100 | F89: Computer Based | G89: =1.1*E89 -> 110 | I89: =CONCATENATE(A89,",",D89) -> ENGL 157,ED1-GEOM
A90: ENGL 157 | B90: COMMUNICATION SKILLS I | C90: Yeboah Philomena Ama Okyeso | D90: ED1-AE | E90: 126 | F90: Computer Based | G90: =1.1*E90 -> 138.6 | I90: =CONCATENATE(A90,",",D90) -> ENGL 157,ED1-AE
A91: ENGL 157 | B91: COMMUNICATION SKILLS I | C91: Sarfo-Adu Kwasi | D91: ED1-EE | E91: 287 | F91: Computer Based | G91: =1.1*E91 -> 315.7 | I91: =CONCATENATE(A91,",",D91) -> ENGL 157,ED1-EE
A92: MME 291 | B92: ECONOMICS AND COMMERCIAL GEOGRAPHY | C92: Bonuedi Isaac | D92: ED2-MARI | E92: 37 | F92: PB008/PB208 | G92: =1.1*E92 -> 40.7 | H92: 30/7 | I92: =CONCATENATE(A92,",",D92) -> MME 291,ED2-MARI
A93: ME 363 | B93: AUTOMATIC CONTROL I | C93: F. W. Adam | D93: ED3-AERO | E93: 76 | F93: VSLA/LT | G93: =1.1*E93 -> 83.6 | H93: 46/30 | I93: =CONCATENATE(A93,",",D93) -> ME 363,ED3-AERO
A94: ME 363 | B94: AUTOMATIC CONTROL | C94: Adam Faisal Wahib | D94: ED3-ME | E94: 230 | F94: NEB-SF/NEB-TF/NEB-FF1/NEB-FF2 | G94: =1.1*E94 -> 253 | H94: 80/80/50/20 | I94: =CONCATENATE(A94,",",D94) -> ME 363,ED3-ME
A95: ME 363 | B95: AUTOMATIC CONTROL I | C95: Adam Faisal Wahib | D95: ED3-MARI | E95: 40 | F95: PB208/PB008 | G95: =1.1*E95 -> 44 | H95: 30/10 | I95: =CONCATENATE(A95,",",D95) -> ME 363,ED3-MARI
A96: BME 285 | B96: ANATOMY AND PHYSIOLOGY FOR ENGINEERS I | C96: Agyapong Dorothy Araba Yakoba | D96: ED2-BME | E96: 87 | F96: RMB/304/N1/N2 | G96: =1.1*E96 -> 95.7 | H96: 22/20/25/20 | I96: =CONCATENATE(A96,",",D96) -> BME 285,ED2-BME
A97: CE 257 | B97: COMPUTER PROGRAMMING | C97: Osei Jack Banahene | D97: ED2-CE | E97: 260 | F97: PB001/PB020/PB014/PB201/PB214/PB208/PB212 | G97: =1.1*E97 -> 286 | H97: 45/45/45/45/45/20/15 | I97: =CONCATENATE(A97,",",D97) -> CE 257,ED2-CE
A98: EE 367 | B98: POWER GENERATION AND SUPPLY | C98: Asigri Peter | D98: ED3-EE | E98: 254 | F98: PB001/PB020/PB014/PB201/PB214/PB212 | G98: =1.1*E98 -> 279.4 | H98: 45/45/45/45/45/29 | I98: =CONCATENATE(A98,",",D98) -> EE 367,ED3-EE
A99: GED 451 | B99: REGIONAL GEOLOGY | C99: Foli Gordon | D99: ED4-GEOL | E99: 102 | F99: NAF1/A110/EA | G99: =1.1*E99 -> 112.2 | H99: 45/30/27 | I99: =CONCATENATE(A99,",",D99) -> GED 451,ED4-GEOL
A100: CHE 359 | B100: MECHANICAL SEPARATION PROCESSES | C100: Darkwah Lawrence | D100: ED3-CHE | E100: 100 | F100: NEB-TF/NEB-FF2 | G100: =1.1*E100 -> 110 | H100: 80/20 | I100: =CONCATENATE(A100,",",D100) -> CHE 359,ED3-CHE
A101: PE 473 | B101: SAFETY AND RELIABILITY ENGINEERING | C101: Quaye Jonathan Atuquaye | D101: ED4-PE | E101: 93 | F101: VSLA/LT/RMA | G101: =1.1*E101 -> 102.3 | H101: 40/30/23 | I101: =CONCATENATE(A101,",",D101) -> PE 473,ED4-PE
...

Sheet Sheet1
A1: Monday, 23 February 2026
A2: Session, 1 (8:15AM - 9:15 AM)
A3: CODE | B3: COURSE NAME | C3: EXAMINER | D3: CLASS | E3: # STDS | F3: ROOM NO. | G3: TO PRT
A4: MATH 351 | B4: NUMERICAL ANALYSIS | C4: Azure Isaac | D4: ED3-ME | E4: 230 | F4: Computer Based | G4: 253
A5: MATH 351 | B5: NUMERICAL ANALYSIS | C5: Azure Isaac | D5: ED3-AUTO | E5: 47 | F5: Computer Based | G5: 51.7
A6: MATH 351 | B6: NUMERICAL METHODS | C6: Azure Isaac | D6: ED3-BME | E6: 94 | F6: Computer Based | G6: 103.4
A7: MATH 351 | B7: NUMERICAL ANALYSIS | C7: Borkor Reindorf Nartey | D7: ED3-AERO | E7: 76 | F7: Computer Based | G7: 83.6
A8: MATH 351 | B8: NUMERICAL ANALYSIS | C8: Borkor Reindorf Nartey | D8: ED3-AE | E8: 105 | F8: Computer Based | G8: 115.5
A9: MATH 351 | B9: NUMERICAL ANALYSIS | C9: Borkor Reindorf Nartey | D9: ED3-GEOL | E9: 154 | F9: Computer Based | G9: 169.4
A10: MATH 351 | B10: NUMERICAL ANALYSIS | C10: Borkor Reindorf Nartey | D10: ED3-COE | E10: 276 | F10: Computer Based | G10: 303.6
A11: MATH 351 | B11: NUMERICAL ANALYSIS | C11: Awashie Gaston Edem | D11: ED3-TEL | E11: 147 | F11: Computer Based | G11: 161.7
A12: MATH 351 | B12: NUMERICAL ANALYSIS | C12: Awashie Gaston Edem | D12: ED3-EE | E12: 254 | F12: Computer Based | G12: 279.4
A13: MATH 351 | B13: NUMERICAL ANALYSIS | C13: Awashie Gaston Edem | D13: ED3-IND | E13: 72 | F13: Computer Based | G13: 79.2
A14: MATH 351 | B14: NUMERICAL ANALYSIS | C14: Awashie Gaston Edem | D14: ED3-MARI | E14: 40 | F14: Computer Based | G14: 44
A15: MATH 351 | B15: NUMERICAL ANALYSIS | C15: Borkor Reindorf Nartey | D15: ED3-CE | E15: 223 | F15: Computer Based | G15: 245.3
A16: PE 351 | B16: PETROLEUM ROCK MECHANICS | C16: Erzuah Samuel | D16: ED3-PE | E16: 82 | F16: EA/A110/VCR | G16: 90.2 | H16: 27/30/25
A17: ACF 255 | B17: FINANCIAL ACCOUNTING I | C17: Yeboah Edward | D17: ED2-BME | E17: 16 | F17: N1 | G17: 17.6 | H17: 16
A18: ACF 255 | B18: FINANCIAL ACCOUNTING I | C18: Yeboah Edward | D18: ED2-COE | E18: 61 | F18: 303/304/206 | G18: 67.1 | H18: 25/20/16
A19: ACF 255 | B19: FINANCIAL ACCOUNTING I | C19: Yeboah Edward | D19: ED2-TEL | E19: 35 | F19: LT/RMB | G19: 38.5 | H19: 20/15
A20: ACF 255 | B20: FINANCIAL ACCOUNTING I | C20: Yeboah Edward | D20: ED2-MSE | E20: 13 | F20: N1 | G20: 14.3 | H20: 13
A21: ACF 255 | B21: FINANCIAL ACCOUNTING I | C21: Yeboah Edward | D21: ED3-GEOM | E21: 34 | F21: 206/RMB | G21: 37.4 | H21: 20/14
A22: ACF 255 | B22: FINANCIAL ACCOUNTING I | C22: Yeboah Edward | D22: ED1-GEOL | E22: 3 | F22: RMA | G22: 3.3 | H22: 3
A23: MSE 151 | B23: INTRODUCTION TO THERMODYNAMICS OF MATERIALS | C23: Gikunoo Emmanuel | D23: ED1-MSE | E23: 98 | F23: PB001/PB208/PB008 | G23: 107.8 | H23: 45/30/23
A24: BME 161 | B24: CELL BIOLOGY | C24: Adjei Prince Ebenezer | D24: ED1-BME | E24: 136 | F24: PB201/PB214/PB020/PB212 | G24: 149.6 | H24: 40/40/40/16
A25: GE 261 | B25: FIELD AND GEODETIC ASTRONOMY | C25: Ayer John Wise Divine | D25: ED2-GEOM | E25: 134 | F25: PB201/PB214/PB014/PB208 | G25: 147.4 | H25: 40/40/35/20
A26: GE 151 | B26: CARTOGRAPHY I | C26: Quaye-Ballard Jonathan Arthur | D26: ED1-GEOM | E26: 100 | F26: 303/LT/VSLA | G26: 110 | H26: 30/30/40
A27: EE 161 | B27: TRANSFORMERS | C27: Opoku Daniel | D27: ED1-EE | E27: 287 | F27: NEB-SF/NEB-TF/NEB-FF1/NEB-FF2/NAF1 | G27: 315.7 | H27: 85/80/55/30/37
A28: GED 475 | B28: PRINCIPLES OF HYDROGEOLOGY | C28: Appiah-Adjei Emmanuel Kwame | D28: ED4-GEOL | E28: 102 | F28: NAF1/EA/A110 | G28: 112.2 | H28: 45/30/27
A29: PE 459 | B29: NATURAL GAS ENGINEERING I | C29: Sarkodie Kwame | D29: ED4-PE | E29: 103 | F29: RMA/VSLA/304/N2 | G29: 113.3 | H29: 20/40/20/23
... A31: GED 253 | B31: PHYSICAL GEOLOGY | C31: Mensah Emmanuel | D31: ED2-GEOL | E31: 154 | F31: PB014/PB001/PB020/PB008 | G31: 169.4 | H31: 42/42/42/28
D32: Total M1 | E32: 1618
A35: Monday, 23 February 2026
A36: Session, 2 (10:00AM - 11:00 AM)
A37: CODE | B37: COURSE NAME | C37: EXAMINER | D37: CLASS | E37: # STDS | F37: ROOM NO. | G37: TO PRT
A38: EE 467 | B38: POWER SYSTEMS OPERATION AND CONTROL | C38: Antoh Emmanuel Kwaku | D38: ED4-EE | E38: 224 | F38: VSLA/LT/303/304/206/RMA/RMB/N1/N2 | G38: 246.4 | H38: 45/30/30/20/20/20/20/20/20
A39: COE 457 | B39: ARTIFICIAL INTELLIGENCE | C39: Nunoo-Mensah Henry | D39: ED4-COE | E39: 170 | F39: NEB-SF/NEB-FF1/NEB-FF2 | G39: 187 | H39: 85/55/30
A40: CHE 255 | B40: FLUID TRANSPORT | C40: Momade Zsuzsanna Gál | D40: ED2-CHE | E40: 154 | F40: NEB-SF/NEB-FF1/NEB-FF2 | G40: 169.4 | H40: 80/46/28
A41: CHE 255 | B41: FLUID TRANSPORT | C41: Dogbe Eunice Sefakor Aku | D41: ED2-PCE | E41: 59 | F41: 303/304/206 | G41: 64.9 | H41: 22/20/17
A42: CE 457 | B42: DRAINAGE SYSTEMS | C42: Adjei Kwaku Amaning | D42: ED4-CE | E42: 245 | F42: PB001/PB020/PB014/PB201/PB214/PB212 | G42: 269.5 | H42: 45/45/45/45/45/20
A43: BME 471 | B43: BIOINSTRUMENTATION II | C43: Acquah Isaac | D43: ED4-BME | E43: 84 | F43: PB008/PB208/PB212 | G43: 92.4 | H43: 30/30/24
A44: MSE 353 | B44: PYROMETALLURGY | C44: Agyemang Frank Ofori | D44: ED3-METE | E44: 83 | F44: VSLA/RMA/RMB | G44: 91.3 | H44: 40/22/21
A45: MSE 353 | B45: PYROMETALLURGY | C45: Agyemang Frank Ofori | D45: ED3-MSE | E45: 89 | F45: NAF1/A110/VCR | G45: 97.9 | H45: 40/30/19
A46: PCE 351 | B46: SEPARATION PROCESSES I | C46: Dogbe Eunice Sefakor Aku | D46: ED3-PCE | E46: 51 | F46: EA/ECR | G46: 56.1 | H46: 30/21
A47: EE 265 | B47: ELECTRICAL SERVICES DESIGN | C47: Kwegyir Daniel | D47: ED2-EE | E47: 340 | F47: PB001/PB020/PB014/PB201/PB214/PB008/PB208/NEB-GF | G47: 374 | H47: 45/45/45/45/45/30/30/55
A48: TE 451 | B48: FUNDAMENTALS OF NETWORK SECURITY | C48: Agyemang Justice Owusu | D48: ED4-TEL | E48: 142 | F48: NEB-TF | G48: 156.2 | H48: 142
A49: AE 453 | B49: ENVIRONMENTAL CONTROL AND LIVESTOCK HOUSING | C49: Lavie Jerome Dela | D49: ED4-AE | E49: 103 | F49: NAF1/EA/A110/VCR | G49: 113.3 | H49: 40/25/25/13
D50: Total M2 | E50: 1744
A53: Monday, 23 February 2026
A54: Session, 3 (11:45AM - 12:45 PM)
A55: CODE | B55: COURSE NAME | C55: EXAMINER | D55: CLASS | E55: # STDS | F55: ROOM NO. | G55: TO PRT
A56: ENGL 157 | B56: COMMUNICATION SKILLS I | C56: Yeboah Philomena Ama Okyeso | D56: ED1-MARI | E56: 46 | F56: Computer Based | G56: 50.6
A57: ENGL 157 | B57: COMMUNICATION SKILLS I | C57: Yeboah Philomena Ama Okyeso | D57: ED1-ME | E57: 223 | F57: Computer Based | G57: 245.3
A58: ENGL 157 | B58: COMMUNICATION SKILLS I | C58: Yeboah Philomena Ama Okyeso | D58: ED1-GEOL | E58: 119 | F58: Computer Based | G58: 130.9
A59: ENGL 157 | B59: COMMUNICATION SKILLS I | C59: Alhassan Yakubu | D59: ED1-TEL | E59: 129 | F59: Computer Based | G59: 141.9
A60: ENGL 157 | B60: COMMUNICATION SKILLS I | C60: Yeboah Philomena Ama Okyeso | D60: ED1-IND | E60: 81 | F60: Computer Based | G60: 89.1
A61: ENGL 157 | B61: COMMUNICATION SKILLS I | C61: Sarfo-Adu Kwasi | D61: ED1-AUTO | E61: 88 | F61: Computer Based | G61: 96.8
A62: ENGL 157 | B62: COMMUNICATION SKILLS I | C62: Alhassan Yakubu | D62: ED1-CE | E62: 242 | F62: Computer Based | G62: 266.2
A63: AME 467 | B63: AUTOMOTIVE COMPRESSION-IGNITION ENGINES | C63: Abu Frimpong Solomon | D63: ED4-AUTO | E63: 32 | F63: VSLA | G63: 35.2 | H63: 32
A64: PE 251 | B64: RESERVOIR ENGINEERING I | C64: Adenutsi Caspar Daniel | D64: ED2-PE | E64: 97 | F64: LT/303/304/RMA | G64: 106.7 | H64: 25/25/24/24
A65: GE 461 | B65: CADASTRAL SURVEYING | C65: Akrofi Emmanuel Offei | D65: ED4-GEOM | E65: 93 | F65: PB201/PB214/PB208 | G65: 102.3 | H65: 40/40/13
A66: IE 461 | B66: INDUSTRIAL SAFETY AND MANUFACTURING RELATIONS | C66: Asiedu Charlotte | D66: ED4-IND | E66: 67 | F66: NAF1/A110 | G66: 73.7 | H66: 40/27
A67: CHE 461 | B67: COMPUTER OPTIMIZATION METHOD | C67: Bonsu Jude Kwaku | D67: ED4-CHE | E67: 114 | F67: NAF1/A110/EA/VCR | G67: 125.4 | H67: 45/25/25/20
A68: CHE 461 | B68: COMPUTER OPTIMIZATION METHOD | C68: Bonsu Jude Kwaku | D68: ED4-PCE | E68: 8 | F68: 206 | G68: 8.8 | H68: 8
A69: MSE 251 | B69: MOMENTUM TRANSPORT | C69: Adjaottor Albert Amatey | D69: ED2-MSE | E69: 80 | F69: LT/303/304 | G69: 88 | H69: 30/30/20
A70: MSE 251 | B70: MOMENTUM TRANSPORT | C70: Adjaottor Albert Amatey | D70: ED2-METE | E70: 59 | F70: PB001/PB208 | G70: 64.9 | H70: 35/24
A71: ME 473 | B71: COMPUTER AIDED DESIGN AND MANUFACTURING | C71: Afriyie Nyarko Frank Kwabena | D71: ED4-AERO | E71: 61 | F71: N1/N2/206 | G71: 67.1 | H71: 20/20/21
A72: ME 473 | B72: COMPUTER AIDED DESIGN AND MANUFACTURING | C72: Afriyie Nyarko Frank Kwabena | D72: ED4-ME | E72: 144 | F72: NEB-SF/NEB-FF1/NEB-FF2 | G72: 158.4 | H72: 80/50/14
A73: ME 159 | B73: TECHNICAL DRAWING | C73: Oppong Tawiah Peter | D73: ED1-PE | E73: 129 | F73: NEB-SF/NEB-FF1/NEB-FF2 | G73: 141.9 | H73: 70/35/24
A74: ME 159 | B74: TECHNICAL DRAWING | C74: Oppong Tawiah Peter | D74: ED1-METE | E74: 72 | F74: PB201/PB214 | G74: 79.2 | H74: 36/36
A75: ME 159 | B75: TECHNICAL DRAWING | C75: Oppong Tawiah Peter | D75: ED1-AERO | E75: 70 | F75: PB020/PB014/PB008 | G75: 77 | H75: 30/30/10
A76: ME 265 | B76: THERMODYNAMICS I | C76: Forson Francis Kofi | D76: ED2-AE | E76: 155 | F76: PB001/PB020/PB014/PB008 | G76: 170.5 | H76: 42/42/42/29
A77: METE 457 | B77: CORROSION OF ENGINEERING MATERIALS | C77: Andrews Anthony | D77: ED4-METE | E77: 49 | F77: VSLA | G77: 53.9 | H77: 49
A78: MSE 453 | B78: CORROSION OF ENGINEERING MATERIALS | C78: Andrews Anthony | D78: ED4-MSE | E78: 64 | F78: NEB-TF | G78: 70.4 | H78: 64
D79: Total M3 | E79: 1294
A82: Monday, 23 February 2026
A83: Session, 4 (1:30PM - 2:30 PM)
A84: CODE | B84: COURSE NAME | C84: EXAMINER | D84: CLASS | E84: # STDS | F84: ROOM NO. | G84: TO PRT
A85: ENGL 157 | B85: COMMUNICATION SKILLS I | C85: Sarfo-Adu Kwasi | D85: ED1-CHE | E85: 120 | F85: Computer Based | G85: 132
A86: ENGL 157 | B86: COMMUNICATION SKILLS I | C86: Yeboah Philomena Ama Okyeso | D86: ED1-PCE | E86: 56 | F86: Computer Based | G86: 61.6
A87: ENGL 157 | B87: COMMUNICATION SKILLS I | C87: Alhassan Yakubu | D87: ED1-BME | E87: 136 | F87: Computer Based | G87: 149.6
A88: ENGL 157 | B88: COMMUNICATION SKILLS I | C88: Alhassan Yakubu | D88: ED1-COE | E88: 261 | F88: Computer Based | G88: 287.1
A89: ENGL 157 | B89: COMMUNICATION SKILLS I | C89: Yeboah Philomena Ama Okyeso | D89: ED1-GEOM | E89: 100 | F89: Computer Based | G89: 110
A90: ENGL 157 | B90: COMMUNICATION SKILLS I | C90: Yeboah Philomena Ama Okyeso | D90: ED1-AE | E90: 126 | F90: Computer Based | G90: 138.6
A91: ENGL 157 | B91: COMMUNICATION SKILLS I | C91: Sarfo-Adu Kwasi | D91: ED1-EE | E91: 287 | F91: Computer Based | G91: 315.7
A92: MME 291 | B92: ECONOMICS AND COMMERCIAL GEOGRAPHY | C92: Bonuedi Isaac | D92: ED2-MARI | E92: 37 | F92: PB008/PB208 | G92: 40.7 | H92: 30/7
A93: ME 363 | B93: AUTOMATIC CONTROL I | C93: F. W. Adam | D93: ED3-AERO | E93: 76 | F93: VSLA/LT | G93: 83.6 | H93: 46/30
A94: ME 363 | B94: AUTOMATIC CONTROL | C94: Adam Faisal Wahib | D94: ED3-ME | E94: 230 | F94: NEB-SF/NEB-TF/NEB-FF1/NEB-FF2 | G94: 253 | H94: 80/80/50/20
A95: ME 363 | B95: AUTOMATIC CONTROL I | C95: Adam Faisal Wahib | D95: ED3-MARI | E95: 40 | F95: PB208/PB008 | G95: 44 | H95: 30/10
A96: BME 285 | B96: ANATOMY AND PHYSIOLOGY FOR ENGINEERS I | C96: Agyapong Dorothy Araba Yakoba | D96: ED2-BME | E96: 87 | F96: RMB/304/N1/N2 | G96: 95.7 | H96: 22/20/25/20
A97: CE 257 | B97: COMPUTER PROGRAMMING | C97: Osei Jack Banahene | D97: ED2-CE | E97: 260 | F97: PB001/PB020/PB014/PB201/PB214/PB208/PB212 | G97: 286 | H97: 45/45/45/45/45/20/15
A98: EE 367 | B98: POWER GENERATION AND SUPPLY | C98: Asigri Peter | D98: ED3-EE | E98: 254 | F98: PB001/PB020/PB014/PB201/PB214/PB212 | G98: 279.4 | H98: 45/45/45/45/45/29
A99: GED 451 | B99: REGIONAL GEOLOGY | C99: Foli Gordon | D99: ED4-GEOL | E99: 102 | F99: NAF1/A110/EA | G99: 112.2 | H99: 45/30/27
A100: CHE 359 | B100: MECHANICAL SEPARATION PROCESSES | C100: Darkwah Lawrence | D100: ED3-CHE | E100: 100 | F100: NEB-TF/NEB-FF2 | G100: 110 | H100: 80/20
A101: PE 473 | B101: SAFETY AND RELIABILITY ENGINEERING | C101: Quaye Jonathan Atuquaye | D101: ED4-PE | E101: 93 | F101: VSLA/LT/RMA | G101: 102.3 | H101: 40/30/23
A102: AME 365 | B102: HEAT TRANSFER AND COMBUSTION | C102: Forson Francis Kofi | D102: ED3-AUTO | E102: 47 | F102: NEB-FF1/NEB-FF2 | G102: 51.7 | H102: 37/10
A103: GE 353 | B103: GEOMETRICAL GEODESY | C103: Dadzie Isaac | D103: ED3-GEOM | E103: 115 | F103: NEB-SF/NEB-FF1 | G103: 126.5 | H103: 80/35
... A105: BME 397 | B105: RESEARCH METHODS | C105: Acquah Isaac | D105: ED3-BME | E105: 94 | F105: NAF1/A110/EA | G105: 103.4 | H105: 40/30/24
D106: Total M4 | E106: 1617
A109: Monday, 23 February 2026
A110: Session, 5 (3:15PM - 4:15 PM)
...

Sheet TALLY
B1: M | I1: T | P1: W | W1: H | AD1: F | AL1: M | AM1: T | AN1: W | AO1: H | AP1: F
B2: M1 | C2: M2 | D2: M3 | E2: M4 | F2: M5 | G2: M6 | H2: M7 | I2: T1 | J2: T2 | K2: T3 | L2: T4 | M2: T5 | N2: T6 | O2: T7 | P2: W1 | Q2: W2 | R2: W3 | S2: W4 | T2: W5 | U2: W6 | V2: W7 | W2: H1 | X2: H2 | Y2: H3 | Z2: H4 | AA2: H5 | AB2: H6 | AC2: H7 | AD2: F1 | AE2: F2 | AF2: F3 | AG2: F4 | AH2: F5 | AI2: F6 | AL2: M | AM2: T | AN2: W | AO2: H | AP2: F | AT2: {=count} -> #NAME?
A3: ED1-AE | B3: =COUNTIF('TT '!$D$4:$D$31,TALLY!A3) -> 0 | C3: =COUNTIF('TT '!$D$38:$D$49,TALLY!A3) -> 0 | D3: =COUNTIF('TT '!$D$56:$D$78,TALLY!A3) -> 0 | E3: =COUNTIF('TT '!$D$85:$D$105,TALLY!A3) -> 1 | F3: =COUNTIF('TT '!$D$112:$D$126,TALLY!A3) -> 0 | G3: =COUNTIF('TT '!$D$133:$D$147,TALLY!A3) -> 0 | H3: =COUNTIF('TT '!$D$4:$D$31,TALLY!G3) -> 0 | I3: =COUNTIF('TT '!$D$154:$D$173,TALLY!A3) -> 0 | J3: =COUNTIF('TT '!$D$180:$D$197,TALLY!A3) -> 1 | K3: =COUNTIF('TT '!$D$204:$D$216,TALLY!A3) -> 0 | L3: =COUNTIF('TT '!$D$223:$D$235,TALLY!A3) -> 0 | M3: =COUNTIF('TT '!$D$242:$D$257,TALLY!A3) -> 1 | N3: =COUNTIF('TT '!$D$264:$D$276,TALLY!A3) -> 0 | O3: =COUNTIF([8]TT!$D$36:$D$41,$A3) -> #VALUE! | P3: =COUNTIF('TT '!$D$283:$D$294,TALLY!A3) -> 1 | Q3: =COUNTIF('TT '!$D$301:$D$317,TALLY!A3) -> 0 | R3: =COUNTIF('TT '!$D$324:$D$339,TALLY!A3) -> 0 | S3: =COUNTIF('TT '!$D$346:$D$362,TALLY!A3) -> 0 | T3: =COUNTIF('TT '!$D$369:$D$383,TALLY!A3) -> 0 | U3: =COUNTIF('TT '!$D$390:$D$409,TALLY!A3) -> 0 | V3: =COUNTIF([8]TT!$D$36:$D$41,$A3) -> #VALUE! | W3: =COUNTIF('TT '!$D$416:$D$429,TALLY!A3) -> 0 | X3: =COUNTIF('TT '!$D$436:$D$449,TALLY!A3) -> 0 | Y3: =COUNTIF('TT '!$D$456:$D$474,TALLY!A3) -> 0 | Z3: =COUNTIF('TT '!$D$481:$D$495,TALLY!A3) -> 1 | AA3: =COUNTIF('TT '!$D$502:$D$519,TALLY!A3) -> 0 | AB3: =COUNTIF('TT '!$D$526:$D$540,TALLY!A3) -> 0 | AC3: =COUNTIF([8]TT!$D$36:$D$41,$A3) -> #VALUE! | AD3: =COUNTIF('TT '!$D$547:$D$556,TALLY!A3) -> 0 | AE3: =COUNTIF('TT '!$D$563:$D$577,TALLY!A3) -> 0 | AF3: =COUNTIF('TT '!$D$584:$D$598,TALLY!A3) -> 0 | AG3: =COUNTIF('TT '!$D$605:$D$617,TALLY!A3) -> 0 | AH3: =COUNTIF('TT '!$D$624:$D$636,TALLY!A3) -> 1 | AI3: =COUNTIF('TT '!$D$643:$D$654,TALLY!A3) -> 0 | AJ3: =COUNTIF([8]TT!$D$36:$D$41,$A3) -> #VALUE! | AK3: =CONCATENATE(B3,C3,D3,E3,F3,G3,I3,J3,K3,L3,M3,N3,P3,Q3,R3,S3,T3,U3,W3,X3,Y3,Z3,AA3,AB3,AD3,AE3,AF3,AG3,AH3,AI3) -> 000100010010100000000100000010 | AL3: =SUM(B3:G3) -> 1 | AM3: =SUM(I3:N3) -> 2 | AN3: =SUM(P3:U3) -> 1 | AO3: =SUM(W3:AB3) -> 1 | AP3: =SUM(AD3:AI3) -> 1
A4: ED1-AERO | B4: =COUNTIF('TT '!$D$4:$D$31,TALLY!A4) -> 0 | C4: =COUNTIF('TT '!$D$38:$D$49,TALLY!A4) -> 0 | D4: =COUNTIF('TT '!$D$56:$D$78,TALLY!A4) -> 1 | E4: =COUNTIF('TT '!$D$85:$D$105,TALLY!A4) -> 0 | F4: =COUNTIF('TT '!$D$112:$D$126,TALLY!A4) -> 1 | G4: =COUNTIF('TT '!$D$133:$D$147,TALLY!A4) -> 0 | H4: =COUNTIF('TT '!$D$4:$D$31,TALLY!G4) -> 0 | I4: =COUNTIF('TT '!$D$154:$D$173,TALLY!A4) -> 0 | J4: =COUNTIF('TT '!$D$180:$D$197,TALLY!A4) -> 1 | K4: =COUNTIF('TT '!$D$204:$D$216,TALLY!A4) -> 0 | L4: =COUNTIF('TT '!$D$223:$D$235,TALLY!A4) -> 0 | M4: =COUNTIF('TT '!$D$242:$D$257,TALLY!A4) -> 1 | N4: =COUNTIF('TT '!$D$264:$D$276,TALLY!A4) -> 0 | O4: =COUNTIF([8]TT!$D$36:$D$41,$A4) -> #VALUE! | P4: =COUNTIF('TT '!$D$283:$D$294,TALLY!A4) -> 0 | Q4: =COUNTIF('TT '!$D$301:$D$317,TALLY!A4) -> 1 | R4: =COUNTIF('TT '!$D$324:$D$339,TALLY!A4) -> 0 | S4: =COUNTIF('TT '!$D$346:$D$362,TALLY!A4) -> 0 | T4: =COUNTIF('TT '!$D$369:$D$383,TALLY!A4) -> 0 | U4: =COUNTIF('TT '!$D$390:$D$409,TALLY!A4) -> 0 | V4: =COUNTIF([8]TT!$D$36:$D$41,$A4) -> #VALUE! | W4: =COUNTIF('TT '!$D$416:$D$429,TALLY!A4) -> 0 | X4: =COUNTIF('TT '!$D$436:$D$449,TALLY!A4) -> 0 | Y4: =COUNTIF('TT '!$D$456:$D$474,TALLY!A4) -> 0 | Z4: =COUNTIF('TT '!$D$481:$D$495,TALLY!A4) -> 1 | AA4: =COUNTIF('TT '!$D$502:$D$519,TALLY!A4) -> 0 | AB4: =COUNTIF('TT '!$D$526:$D$540,TALLY!A4) -> 0 | AC4: =COUNTIF([8]TT!$D$36:$D$41,$A4) -> #VALUE! | AD4: =COUNTIF('TT '!$D$547:$D$556,TALLY!A4) -> 1 | AE4: =COUNTIF('TT '!$D$563:$D$577,TALLY!A4) -> 0 | AF4: =COUNTIF('TT '!$D$584:$D$598,TALLY!A4) -> 0 | AG4: =COUNTIF('TT '!$D$605:$D$617,TALLY!A4) -> 0 | AH4: =COUNTIF('TT '!$D$624:$D$636,TALLY!A4) -> 0 | AI4: =COUNTIF('TT '!$D$643:$D$654,TALLY!A4) -> 0 | AJ4: =COUNTIF([8]TT!$D$36:$D$41,$A4) -> #VALUE! | AK4: =CONCATENATE(B4,C4,D4,E4,F4,G4,I4,J4,K4,L4,M4,N4,P4,Q4,R4,S4,T4,U4,W4,X4,Y4,Z4,AA4,AB4,AD4,AE4,AF4,AG4,AH4,AI4) -> 001010010010010000000100100000 | AL4: =SUM(B4:G4) -> 2 | AM4: =SUM(I4:N4) -> 2 | AN4: =SUM(P4:U4) -> 1 | AO4: =SUM(W4:AB4) -> 1 | AP4: =SUM(AD4:AI4) -> 1
A5: ED1-AUTO | B5: =COUNTIF('TT '!$D$4:$D$31,TALLY!A5) -> 0 | C5: =COUNTIF('TT '!$D$38:$D$49,TALLY!A5) -> 0 | D5: =COUNTIF('TT '!$D$56:$D$78,TALLY!A5) -> 1 | E5: =COUNTIF('TT '!$D$85:$D$105,TALLY!A5) -> 0 | F5: =COUNTIF('TT '!$D$112:$D$126,TALLY!A5) -> 0 | G5: =COUNTIF('TT '!$D$133:$D$147,TALLY!A5) -> 0 | H5: =COUNTIF('TT '!$D$4:$D$31,TALLY!G5) -> 0 | I5: =COUNTIF('TT '!$D$154:$D$173,TALLY!A5) -> 0 | J5: =COUNTIF('TT '!$D$180:$D$197,TALLY!A5) -> 1 | K5: =COUNTIF('TT '!$D$204:$D$216,TALLY!A5) -> 0 | L5: =COUNTIF('TT '!$D$223:$D$235,TALLY!A5) -> 0 | M5: =COUNTIF('TT '!$D$242:$D$257,TALLY!A5) -> 0 | N5: =COUNTIF('TT '!$D$264:$D$276,TALLY!A5) -> 0 | O5: =COUNTIF([8]TT!$D$36:$D$41,$A5) -> #VALUE! | P5: =COUNTIF('TT '!$D$283:$D$294,TALLY!A5) -> 0 | Q5: =COUNTIF('TT '!$D$301:$D$317,TALLY!A5) -> 0 | R5: =COUNTIF('TT '!$D$324:$D$339,TALLY!A5) -> 1 | S5: =COUNTIF('TT '!$D$346:$D$362,TALLY!A5) -> 0 | T5: =COUNTIF('TT '!$D$369:$D$383,TALLY!A5) -> 0 | U5: =COUNTIF('TT '!$D$390:$D$409,TALLY!A5) -> 1 | V5: =COUNTIF([8]TT!$D$36:$D$41,$A5) -> #VALUE! | W5: =COUNTIF('TT '!$D$416:$D$429,TALLY!A5) -> 0 | X5: =COUNTIF('TT '!$D$436:$D$449,TALLY!A5) -> 0 | Y5: =COUNTIF('TT '!$D$456:$D$474,TALLY!A5) -> 0 | Z5: =COUNTIF('TT '!$D$481:$D$495,TALLY!A5) -> 1 | AA5: =COUNTIF('TT '!$D$502:$D$519,TALLY!A5) -> 0 | AB5: =COUNTIF('TT '!$D$526:$D$540,TALLY!A5) -> 0 | AC5: =COUNTIF([8]TT!$D$36:$D$41,$A5) -> #VALUE! | AD5: =COUNTIF('TT '!$D$547:$D$556,TALLY!A5) -> 0 | AE5: =COUNTIF('TT '!$D$563:$D$577,TALLY!A5) -> 0 | AF5: =COUNTIF('TT '!$D$584:$D$598,TALLY!A5) -> 0 | AG5: =COUNTIF('TT '!$D$605:$D$617,TALLY!A5) -> 0 | AH5: =COUNTIF('TT '!$D$624:$D$636,TALLY!A5) -> 0 | AI5: =COUNTIF('TT '!$D$643:$D$654,TALLY!A5) -> 0 | AJ5: =COUNTIF([8]TT!$D$36:$D$41,$A5) -> #VALUE! | AK5: =CONCATENATE(B5,C5,D5,E5,F5,G5,I5,J5,K5,L5,M5,N5,P5,Q5,R5,S5,T5,U5,W5,X5,Y5,Z5,AA5,AB5,AD5,AE5,AF5,AG5,AH5,AI5) -> 001000010000001001000100000000 | AL5: =SUM(B5:G5) -> 1 | AM5: =SUM(I5:N5) -> 1 | AN5: =SUM(P5:U5) -> 2 | AO5: =SUM(W5:AB5) -> 1 | AP5: =SUM(AD5:AI5) -> 0
A6: ED1-BME | B6: =COUNTIF('TT '!$D$4:$D$31,TALLY!A6) -> 1 | C6: =COUNTIF('TT '!$D$38:$D$49,TALLY!A6) -> 0 | D6: =COUNTIF('TT '!$D$56:$D$78,TALLY!A6) -> 0 | E6: =COUNTIF('TT '!$D$85:$D$105,TALLY!A6) -> 1 | F6: =COUNTIF('TT '!$D$112:$D$126,TALLY!A6) -> 0 | G6: =COUNTIF('TT '!$D$133:$D$147,TALLY!A6) -> 0 | H6: =COUNTIF('TT '!$D$4:$D$31,TALLY!G6) -> 0 | I6: =COUNTIF('TT '!$D$154:$D$173,TALLY!A6) -> 0 | J6: =COUNTIF('TT '!$D$180:$D$197,TALLY!A6) -> 1 | K6: =COUNTIF('TT '!$D$204:$D$216,TALLY!A6) -> 0 | L6: =COUNTIF('TT '!$D$223:$D$235,TALLY!A6) -> 0 | M6: =COUNTIF('TT '!$D$242:$D$257,TALLY!A6) -> 0 | N6: =COUNTIF('TT '!$D$264:$D$276,TALLY!A6) -> 0 | O6: =COUNTIF([8]TT!$D$36:$D$41,$A6) -> #VALUE! | P6: =COUNTIF('TT '!$D$283:$D$294,TALLY!A6) -> 0 | Q6: =COUNTIF('TT '!$D$301:$D$317,TALLY!A6) -> 1 | R6: =COUNTIF('TT '!$D$324:$D$339,TALLY!A6) -> 0 | S6: =COUNTIF('TT '!$D$346:$D$362,TALLY!A6) -> 0 | T6: =COUNTIF('TT '!$D$369:$D$383,TALLY!A6) -> 0 | U6: =COUNTIF('TT '!$D$390:$D$409,TALLY!A6) -> 0 | V6: =COUNTIF([8]TT!$D$36:$D$41,$A6) -> #VALUE! | W6: =COUNTIF('TT '!$D$416:$D$429,TALLY!A6) -> 0 | X6: =COUNTIF('TT '!$D$436:$D$449,TALLY!A6) -> 0 | Y6: =COUNTIF('TT '!$D$456:$D$474,TALLY!A6) -> 0 | Z6: =COUNTIF('TT '!$D$481:$D$495,TALLY!A6) -> 1 | AA6: =COUNTIF('TT '!$D$502:$D$519,TALLY!A6) -> 0 | AB6: =COUNTIF('TT '!$D$526:$D$540,TALLY!A6) -> 0 | AC6: =COUNTIF([8]TT!$D$36:$D$41,$A6) -> #VALUE! | AD6: =COUNTIF('TT '!$D$547:$D$556,TALLY!A6) -> 0 | AE6: =COUNTIF('TT '!$D$563:$D$577,TALLY!A6) -> 0 | AF6: =COUNTIF('TT '!$D$584:$D$598,TALLY!A6) -> 1 | AG6: =COUNTIF('TT '!$D$605:$D$617,TALLY!A6) -> 0 | AH6: =COUNTIF('TT '!$D$624:$D$636,TALLY!A6) -> 0 | AI6: =COUNTIF('TT '!$D$643:$D$654,TALLY!A6) -> 0 | AJ6: =COUNTIF([8]TT!$D$36:$D$41,$A6) -> #VALUE! | AK6: =CONCATENATE(B6,C6,D6,E6,F6,G6,I6,J6,K6,L6,M6,N6,P6,Q6,R6,S6,T6,U6,W6,X6,Y6,Z6,AA6,AB6,AD6,AE6,AF6,AG6,AH6,AI6) -> 100100010000010000000100001000 | AL6: =SUM(B6:G6) -> 2 | AM6: =SUM(I6:N6) -> 1 | AN6: =SUM(P6:U6) -> 1 | AO6: =SUM(W6:AB6) -> 1 | AP6: =SUM(AD6:AI6) -> 1
A7: ED1-CE | B7: =COUNTIF('TT '!$D$4:$D$31,TALLY!A7) -> 0 | C7: =COUNTIF('TT '!$D$38:$D$49,TALLY!A7) -> 0 | D7: =COUNTIF('TT '!$D$56:$D$78,TALLY!A7) -> 1 | E7: =COUNTIF('TT '!$D$85:$D$105,TALLY!A7) -> 0 | F7: =COUNTIF('TT '!$D$112:$D$126,TALLY!A7) -> 0 | G7: =COUNTIF('TT '!$D$133:$D$147,TALLY!A7) -> 0 | H7: =COUNTIF('TT '!$D$4:$D$31,TALLY!G7) -> 0 | I7: =COUNTIF('TT '!$D$154:$D$173,TALLY!A7) -> 0 | J7: =COUNTIF('TT '!$D$180:$D$197,TALLY!A7) -> 1 | K7: =COUNTIF('TT '!$D$204:$D$216,TALLY!A7) -> 0 | L7: =COUNTIF('TT '!$D$223:$D$235,TALLY!A7) -> 0 | M7: =COUNTIF('TT '!$D$242:$D$257,TALLY!A7) -> 0 | N7: =COUNTIF('TT '!$D$264:$D$276,TALLY!A7) -> 1 | O7: =COUNTIF([8]TT!$D$36:$D$41,$A7) -> #VALUE! | P7: =COUNTIF('TT '!$D$283:$D$294,TALLY!A7) -> 0 | Q7: =COUNTIF('TT '!$D$301:$D$317,TALLY!A7) -> 1 | R7: =COUNTIF('TT '!$D$324:$D$339,TALLY!A7) -> 0 | S7: =COUNTIF('TT '!$D$346:$D$362,TALLY!A7) -> 0 | T7: =COUNTIF('TT '!$D$369:$D$383,TALLY!A7) -> 0 | U7: =COUNTIF('TT '!$D$390:$D$409,TALLY!A7) -> 1 | V7: =COUNTIF([8]TT!$D$36:$D$41,$A7) -> #VALUE! | W7: =COUNTIF('TT '!$D$416:$D$429,TALLY!A7) -> 0 | X7: =COUNTIF('TT '!$D$436:$D$449,TALLY!A7) -> 1 | Y7: =COUNTIF('TT '!$D$456:$D$474,TALLY!A7) -> 0 | Z7: =COUNTIF('TT '!$D$481:$D$495,TALLY!A7) -> 0 | AA7: =COUNTIF('TT '!$D$502:$D$519,TALLY!A7) -> 0 | AB7: =COUNTIF('TT '!$D$526:$D$540,TALLY!A7) -> 1 | AC7: =COUNTIF([8]TT!$D$36:$D$41,$A7) -> #VALUE! | AD7: =COUNTIF('TT '!$D$547:$D$556,TALLY!A7) -> 0 | AE7: =COUNTIF('TT '!$D$563:$D$577,TALLY!A7) -> 1 | AF7: =COUNTIF('TT '!$D$584:$D$598,TALLY!A7) -> 0 | AG7: =COUNTIF('TT '!$D$605:$D$617,TALLY!A7) -> 0 | AH7: =COUNTIF('TT '!$D$624:$D$636,TALLY!A7) -> 1 | AI7: =COUNTIF('TT '!$D$643:$D$654,TALLY!A7) -> 0 | AJ7: =COUNTIF([8]TT!$D$36:$D$41,$A7) -> #VALUE! | AK7: =CONCATENATE(B7,C7,D7,E7,F7,G7,I7,J7,K7,L7,M7,N7,P7,Q7,R7,S7,T7,U7,W7,X7,Y7,Z7,AA7,AB7,AD7,AE7,AF7,AG7,AH7,AI7) -> 001000010001010001010001010010 | AL7: =SUM(B7:G7) -> 1 | AM7: =SUM(I7:N7) -> 2 | AN7: =SUM(P7:U7) -> 2 | AO7: =SUM(W7:AB7) -> 2 | AP7: =SUM(AD7:AI7) -> 2
A8: ED1-CHE | B8: =COUNTIF('TT '!$D$4:$D$31,TALLY!A8) -> 0 | C8: =COUNTIF('TT '!$D$38:$D$49,TALLY!A8) -> 0 | D8: =COUNTIF('TT '!$D$56:$D$78,TALLY!A8) -> 0 | E8: =COUNTIF('TT '!$D$85:$D$105,TALLY!A8) -> 1 | F8: =COUNTIF('TT '!$D$112:$D$126,TALLY!A8) -> 0 | G8: =COUNTIF('TT '!$D$133:$D$147,TALLY!A8) -> 0 | H8: =COUNTIF('TT '!$D$4:$D$31,TALLY!G8) -> 0 | I8: =COUNTIF('TT '!$D$154:$D$173,TALLY!A8) -> 0 | J8: =COUNTIF('TT '!$D$180:$D$197,TALLY!A8) -> 1 | K8: =COUNTIF('TT '!$D$204:$D$216,TALLY!A8) -> 0 | L8: =COUNTIF('TT '!$D$223:$D$235,TALLY!A8) -> 0 | M8: =COUNTIF('TT '!$D$242:$D$257,TALLY!A8) -> 1 | N8: =COUNTIF('TT '!$D$264:$D$276,TALLY!A8) -> 0 | O8: =COUNTIF([8]TT!$D$36:$D$41,$A8) -> #VALUE! | P8: =COUNTIF('TT '!$D$283:$D$294,TALLY!A8) -> 0 | Q8: =COUNTIF('TT '!$D$301:$D$317,TALLY!A8) -> 0 | R8: =COUNTIF('TT '!$D$324:$D$339,TALLY!A8) -> 0 | S8: =COUNTIF('TT '!$D$346:$D$362,TALLY!A8) -> 0 | T8: =COUNTIF('TT '!$D$369:$D$383,TALLY!A8) -> 1 | U8: =COUNTIF('TT '!$D$390:$D$409,TALLY!A8) -> 0 | V8: =COUNTIF([8]TT!$D$36:$D$41,$A8) -> #VALUE! | W8: =COUNTIF('TT '!$D$416:$D$429,TALLY!A8) -> 0 | X8: =COUNTIF('TT '!$D$436:$D$449,TALLY!A8) -> 0 | Y8: =COUNTIF('TT '!$D$456:$D$474,TALLY!A8) -> 0 | Z8: =COUNTIF('TT '!$D$481:$D$495,TALLY!A8) -> 1 | AA8: =COUNTIF('TT '!$D$502:$D$519,TALLY!A8) -> 0 | AB8: =COUNTIF('TT '!$D$526:$D$540,TALLY!A8) -> 0 | AC8: =COUNTIF([8]TT!$D$36:$D$41,$A8) -> #VALUE! | AD8: =COUNTIF('TT '!$D$547:$D$556,TALLY!A8) -> 0 | AE8: =COUNTIF('TT '!$D$563:$D$577,TALLY!A8) -> 0 | AF8: =COUNTIF('TT '!$D$584:$D$598,TALLY!A8) -> 0 | AG8: =COUNTIF('TT '!$D$605:$D$617,TALLY!A8) -> 0 | AH8: =COUNTIF('TT '!$D$624:$D$636,TALLY!A8) -> 1 | AI8: =COUNTIF('TT '!$D$643:$D$654,TALLY!A8) -> 0 | AJ8: =COUNTIF([8]TT!$D$36:$D$41,$A8) -> #VALUE! | AK8: =CONCATENATE(B8,C8,D8,E8,F8,G8,I8,J8,K8,L8,M8,N8,P8,Q8,R8,S8,T8,U8,W8,X8,Y8,Z8,AA8,AB8,AD8,AE8,AF8,AG8,AH8,AI8) -> 000100010010000010000100000010 | AL8: =SUM(B8:G8) -> 1 | AM8: =SUM(I8:N8) -> 2 | AN8: =SUM(P8:U8) -> 1 | AO8: =SUM(W8:AB8) -> 1 | AP8: =SUM(AD8:AI8) -> 1
A9: ED1-COE | B9: =COUNTIF('TT '!$D$4:$D$31,TALLY!A9) -> 0 | C9: =COUNTIF('TT '!$D$38:$D$49,TALLY!A9) -> 0 | D9: =COUNTIF('TT '!$D$56:$D$78,TALLY!A9) -> 0 | E9: =COUNTIF('TT '!$D$85:$D$105,TALLY!A9) -> 1 | F9: =COUNTIF('TT '!$D$112:$D$126,TALLY!A9) -> 0 | G9: =COUNTIF('TT '!$D$133:$D$147,TALLY!A9) -> 0 | H9: =COUNTIF('TT '!$D$4:$D$31,TALLY!G9) -> 0 | I9: =COUNTIF('TT '!$D$154:$D$173,TALLY!A9) -> 0 | J9: =COUNTIF('TT '!$D$180:$D$197,TALLY!A9) -> 1 | K9: =COUNTIF('TT '!$D$204:$D$216,TALLY!A9) -> 0 | L9: =COUNTIF('TT '!$D$223:$D$235,TALLY!A9) -> 0 | M9: =COUNTIF('TT '!$D$242:$D$257,TALLY!A9) -> 1 | N9: =COUNTIF('TT '!$D$264:$D$276,TALLY!A9) -> 0 | O9: =COUNTIF([8]TT!$D$36:$D$41,$A9) -> #VALUE! | P9: =COUNTIF('TT '!$D$283:$D$294,TALLY!A9) -> 0 | Q9: =COUNTIF('TT '!$D$301:$D$317,TALLY!A9) -> 0 | R9: =COUNTIF('TT '!$D$324:$D$339,TALLY!A9) -> 1 | S9: =COUNTIF('TT '!$D$346:$D$362,TALLY!A9) -> 0 | T9: =COUNTIF('TT '!$D$369:$D$383,TALLY!A9) -> 0 | U9: =COUNTIF('TT '!$D$390:$D$409,TALLY!A9) -> 0 | V9: =COUNTIF([8]TT!$D$36:$D$41,$A9) -> #VALUE! | W9: =COUNTIF('TT '!$D$416:$D$429,TALLY!A9) -> 0 | X9: =COUNTIF('TT '!$D$436:$D$449,TALLY!A9) -> 0 | Y9: =COUNTIF('TT '!$D$456:$D$474,TALLY!A9) -> 0 | Z9: =COUNTIF('TT '!$D$481:$D$495,TALLY!A9) -> 1 | AA9: =COUNTIF('TT '!$D$502:$D$519,TALLY!A9) -> 0 | AB9: =COUNTIF('TT '!$D$526:$D$540,TALLY!A9) -> 0 | AC9: =COUNTIF([8]TT!$D$36:$D$41,$A9) -> #VALUE! | AD9: =COUNTIF('TT '!$D$547:$D$556,TALLY!A9) -> 0 | AE9: =COUNTIF('TT '!$D$563:$D$577,TALLY!A9) -> 0 | AF9: =COUNTIF('TT '!$D$584:$D$598,TALLY!A9) -> 0 | AG9: =COUNTIF('TT '!$D$605:$D$617,TALLY!A9) -> 0 | AH9: =COUNTIF('TT '!$D$624:$D$636,TALLY!A9) -> 0 | AI9: =COUNTIF('TT '!$D$643:$D$654,TALLY!A9) -> 1 | AJ9: =COUNTIF([8]TT!$D$36:$D$41,$A9) -> #VALUE! | AK9: =CONCATENATE(B9,C9,D9,E9,F9,G9,I9,J9,K9,L9,M9,N9,P9,Q9,R9,S9,T9,U9,W9,X9,Y9,Z9,AA9,AB9,AD9,AE9,AF9,AG9,AH9,AI9) -> 000100010010001000000100000001 | AL9: =SUM(B9:G9) -> 1 | AM9: =SUM(I9:N9) -> 2 | AN9: =SUM(P9:U9) -> 1 | AO9: =SUM(W9:AB9) -> 1 | AP9: =SUM(AD9:AI9) -> 1
A10: ED1-EE | B10: =COUNTIF('TT '!$D$4:$D$31,TALLY!A10) -> 1 | C10: =COUNTIF('TT '!$D$38:$D$49,TALLY!A10) -> 0 | D10: =COUNTIF('TT '!$D$56:$D$78,TALLY!A10) -> 0 | E10: =COUNTIF('TT '!$D$85:$D$105,TALLY!A10) -> 1 | F10: =COUNTIF('TT '!$D$112:$D$126,TALLY!A10) -> 0 | G10: =COUNTIF('TT '!$D$133:$D$147,TALLY!A10) -> 0 | H10: =COUNTIF('TT '!$D$4:$D$31,TALLY!G10) -> 0 | I10: =COUNTIF('TT '!$D$154:$D$173,TALLY!A10) -> 0 | J10: =COUNTIF('TT '!$D$180:$D$197,TALLY!A10) -> 1 | K10: =COUNTIF('TT '!$D$204:$D$216,TALLY!A10) -> 0 | L10: =COUNTIF('TT '!$D$223:$D$235,TALLY!A10) -> 0 | M10: =COUNTIF('TT '!$D$242:$D$257,TALLY!A10) -> 0 | N10: =COUNTIF('TT '!$D$264:$D$276,TALLY!A10) -> 0 | O10: =COUNTIF([8]TT!$D$36:$D$41,$A10) -> #VALUE! | P10: =COUNTIF('TT '!$D$283:$D$294,TALLY!A10) -> 1 | Q10: =COUNTIF('TT '!$D$301:$D$317,TALLY!A10) -> 0 | R10: =COUNTIF('TT '!$D$324:$D$339,TALLY!A10) -> 0 | S10: =COUNTIF('TT '!$D$346:$D$362,TALLY!A10) -> 0 | T10: =COUNTIF('TT '!$D$369:$D$383,TALLY!A10) -> 1 | U10: =COUNTIF('TT '!$D$390:$D$409,TALLY!A10) -> 0 | V10: =COUNTIF([8]TT!$D$36:$D$41,$A10) -> #VALUE! | W10: =COUNTIF('TT '!$D$416:$D$429,TALLY!A10) -> 0 | X10: =COUNTIF('TT '!$D$436:$D$449,TALLY!A10) -> 0 | Y10: =COUNTIF('TT '!$D$456:$D$474,TALLY!A10) -> 0 | Z10: =COUNTIF('TT '!$D$481:$D$495,TALLY!A10) -> 1 | AA10: =COUNTIF('TT '!$D$502:$D$519,TALLY!A10) -> 0 | AB10: =COUNTIF('TT '!$D$526:$D$540,TALLY!A10) -> 0 | AC10: =COUNTIF([8]TT!$D$36:$D$41,$A10) -> #VALUE! | AD10: =COUNTIF('TT '!$D$547:$D$556,TALLY!A10) -> 1 | AE10: =COUNTIF('TT '!$D$563:$D$577,TALLY!A10) -> 0 | AF10: =COUNTIF('TT '!$D$584:$D$598,TALLY!A10) -> 0 | AG10: =COUNTIF('TT '!$D$605:$D$617,TALLY!A10) -> 0 | AH10: =COUNTIF('TT '!$D$624:$D$636,TALLY!A10) -> 0 | AI10: =COUNTIF('TT '!$D$643:$D$654,TALLY!A10) -> 0 | AJ10: =COUNTIF([8]TT!$D$36:$D$41,$A10) -> #VALUE! | AK10: =CONCATENATE(B10,C10,D10,E10,F10,G10,I10,J10,K10,L10,M10,N10,P10,Q10,R10,S10,T10,U10,W10,X10,Y10,Z10,AA10,AB10,AD10,AE10,AF10,AG10,AH10,AI10) -> 100100010000100010000100100000 | AL10: =SUM(B10:G10) -> 2 | AM10: =SUM(I10:N10) -> 1 | AN10: =SUM(P10:U10) -> 2 | AO10: =SUM(W10:AB10) -> 1 | AP10: =SUM(AD10:AI10) -> 1
A11: ED1-GEOL | B11: =COUNTIF('TT '!$D$4:$D$31,TALLY!A11) -> 1 | C11: =COUNTIF('TT '!$D$38:$D$49,TALLY!A11) -> 0 | D11: =COUNTIF('TT '!$D$56:$D$78,TALLY!A11) -> 1 | E11: =COUNTIF('TT '!$D$85:$D$105,TALLY!A11) -> 0 | F11: =COUNTIF('TT '!$D$112:$D$126,TALLY!A11) -> 0 | G11: =COUNTIF('TT '!$D$133:$D$147,TALLY!A11) -> 0 | H11: =COUNTIF('TT '!$D$4:$D$31,TALLY!G11) -> 0 | I11: =COUNTIF('TT '!$D$154:$D$173,TALLY!A11) -> 0 | J11: =COUNTIF('TT '!$D$180:$D$197,TALLY!A11) -> 1 | K11: =COUNTIF('TT '!$D$204:$D$216,TALLY!A11) -> 0 | L11: =COUNTIF('TT '!$D$223:$D$235,TALLY!A11) -> 0 | M11: =COUNTIF('TT '!$D$242:$D$257,TALLY!A11) -> 0 | N11: =COUNTIF('TT '!$D$264:$D$276,TALLY!A11) -> 1 | O11: =COUNTIF([8]TT!$D$36:$D$41,$A11) -> #VALUE! | P11: =COUNTIF('TT '!$D$283:$D$294,TALLY!A11) -> 0 | Q11: =COUNTIF('TT '!$D$301:$D$317,TALLY!A11) -> 1 | R11: =COUNTIF('TT '!$D$324:$D$339,TALLY!A11) -> 0 | S11: =COUNTIF('TT '!$D$346:$D$362,TALLY!A11) -> 0 | T11: =COUNTIF('TT '!$D$369:$D$383,TALLY!A11) -> 0 | U11: =COUNTIF('TT '!$D$390:$D$409,TALLY!A11) -> 1 | V11: =COUNTIF([8]TT!$D$36:$D$41,$A11) -> #VALUE! | W11: =COUNTIF('TT '!$D$416:$D$429,TALLY!A11) -> 1 | X11: =COUNTIF('TT '!$D$436:$D$449,TALLY!A11) -> 0 | Y11: =COUNTIF('TT '!$D$456:$D$474,TALLY!A11) -> 0 | Z11: =COUNTIF('TT '!$D$481:$D$495,TALLY!A11) -> 0 | AA11: =COUNTIF('TT '!$D$502:$D$519,TALLY!A11) -> 0 | AB11: =COUNTIF('TT '!$D$526:$D$540,TALLY!A11) -> 0 | AC11: =COUNTIF([8]TT!$D$36:$D$41,$A11) -> #VALUE! | AD11: =COUNTIF('TT '!$D$547:$D$556,TALLY!A11) -> 0 | AE11: =COUNTIF('TT '!$D$563:$D$577,TALLY!A11) -> 1 | AF11: =COUNTIF('TT '!$D$584:$D$598,TALLY!A11) -> 0 | AG11: =COUNTIF('TT '!$D$605:$D$617,TALLY!A11) -> 0 | AH11: =COUNTIF('TT '!$D$624:$D$636,TALLY!A11) -> 1 | AI11: =COUNTIF('TT '!$D$643:$D$654,TALLY!A11) -> 0 | AJ11: =COUNTIF([8]TT!$D$36:$D$41,$A11) -> #VALUE! | AK11: =CONCATENATE(B11,C11,D11,E11,F11,G11,I11,J11,K11,L11,M11,N11,P11,Q11,R11,S11,T11,U11,W11,X11,Y11,Z11,AA11,AB11,AD11,AE11,AF11,AG11,AH11,AI11) -> 101000010001010001100000010010 | AL11: =SUM(B11:G11) -> 2 | AM11: =SUM(I11:N11) -> 2 | AN11: =SUM(P11:U11) -> 2 | AO11: =SUM(W11:AB11) -> 1 | AP11: =SUM(AD11:AI11) -> 2
A12: ED1-GEOM | B12: =COUNTIF('TT '!$D$4:$D$31,TALLY!A12) -> 1 | C12: =COUNTIF('TT '!$D$38:$D$49,TALLY!A12) -> 0 | D12: =COUNTIF('TT '!$D$56:$D$78,TALLY!A12) -> 0 | E12: =COUNTIF('TT '!$D$85:$D$105,TALLY!A12) -> 1 | F12: =COUNTIF('TT '!$D$112:$D$126,TALLY!A12) -> 0 | G12: =COUNTIF('TT '!$D$133:$D$147,TALLY!A12) -> 0 | H12: =COUNTIF('TT '!$D$4:$D$31,TALLY!G12) -> 0 | I12: =COUNTIF('TT '!$D$154:$D$173,TALLY!A12) -> 0 | J12: =COUNTIF('TT '!$D$180:$D$197,TALLY!A12) -> 1 | K12: =COUNTIF('TT '!$D$204:$D$216,TALLY!A12) -> 0 | L12: =COUNTIF('TT '!$D$223:$D$235,TALLY!A12) -> 0 | M12: =COUNTIF('TT '!$D$242:$D$257,TALLY!A12) -> 0 | N12: =COUNTIF('TT '!$D$264:$D$276,TALLY!A12) -> 0 | O12: =COUNTIF([8]TT!$D$36:$D$41,$A12) -> #VALUE! | P12: =COUNTIF('TT '!$D$283:$D$294,TALLY!A12) -> 1 | Q12: =COUNTIF('TT '!$D$301:$D$317,TALLY!A12) -> 0 | R12: =COUNTIF('TT '!$D$324:$D$339,TALLY!A12) -> 0 | S12: =COUNTIF('TT '!$D$346:$D$362,TALLY!A12) -> 0 | T12: =COUNTIF('TT '!$D$369:$D$383,TALLY!A12) -> 0 | U12: =COUNTIF('TT '!$D$390:$D$409,TALLY!A12) -> 0 | V12: =COUNTIF([8]TT!$D$36:$D$41,$A12) -> #VALUE! | W12: =COUNTIF('TT '!$D$416:$D$429,TALLY!A12) -> 1 | X12: =COUNTIF('TT '!$D$436:$D$449,TALLY!A12) -> 0 | Y12: =COUNTIF('TT '!$D$456:$D$474,TALLY!A12) -> 0 | Z12: =COUNTIF('TT '!$D$481:$D$495,TALLY!A12) -> 0 | AA12: =COUNTIF('TT '!$D$502:$D$519,TALLY!A12) -> 0 | AB12: =COUNTIF('TT '!$D$526:$D$540,TALLY!A12) -> 1 | AC12: =COUNTIF([8]TT!$D$36:$D$41,$A12) -> #VALUE! | AD12: =COUNTIF('TT '!$D$547:$D$556,TALLY!A12) -> 0 | AE12: =COUNTIF('TT '!$D$563:$D$577,TALLY!A12) -> 0 | AF12: =COUNTIF('TT '!$D$584:$D$598,TALLY!A12) -> 0 | AG12: =COUNTIF('TT '!$D$605:$D$617,TALLY!A12) -> 0 | AH12: =COUNTIF('TT '!$D$624:$D$636,TALLY!A12) -> 0 | AI12: =COUNTIF('TT '!$D$643:$D$654,TALLY!A12) -> 0 | AJ12: =COUNTIF([8]TT!$D$36:$D$41,$A12) -> #VALUE! | AK12: =CONCATENATE(B12,C12,D12,E12,F12,G12,I12,J12,K12,L12,M12,N12,P12,Q12,R12,S12,T12,U12,W12,X12,Y12,Z12,AA12,AB12,AD12,AE12,AF12,AG12,AH12,AI12) -> 100100010000100000100001000000 | AL12: =SUM(B12:G12) -> 2 | AM12: =SUM(I12:N12) -> 1 | AN12: =SUM(P12:U12) -> 1 | AO12: =SUM(W12:AB12) -> 2 | AP12: =SUM(AD12:AI12) -> 0
A13: ED1-IND | B13: =COUNTIF('TT '!$D$4:$D$31,TALLY!A13) -> 0 | C13: =COUNTIF('TT '!$D$38:$D$49,TALLY!A13) -> 0 | D13: =COUNTIF('TT '!$D$56:$D$78,TALLY!A13) -> 1 | E13: =COUNTIF('TT '!$D$85:$D$105,TALLY!A13) -> 0 | F13: =COUNTIF('TT '!$D$112:$D$126,TALLY!A13) -> 0 | G13: =COUNTIF('TT '!$D$133:$D$147,TALLY!A13) -> 0 | H13: =COUNTIF('TT '!$D$4:$D$31,TALLY!G13) -> 0 | I13: =COUNTIF('TT '!$D$154:$D$173,TALLY!A13) -> 0 | J13: =COUNTIF('TT '!$D$180:$D$197,TALLY!A13) -> 1 | K13: =COUNTIF('TT '!$D$204:$D$216,TALLY!A13) -> 0 | L13: =COUNTIF('TT '!$D$223:$D$235,TALLY!A13) -> 0 | M13: =COUNTIF('TT '!$D$242:$D$257,TALLY!A13) -> 1 | N13: =COUNTIF('TT '!$D$264:$D$276,TALLY!A13) -> 0 | O13: =COUNTIF([8]TT!$D$36:$D$41,$A13) -> #VALUE! | P13: =COUNTIF('TT '!$D$283:$D$294,TALLY!A13) -> 0 | Q13: =COUNTIF('TT '!$D$301:$D$317,TALLY!A13) -> 0 | R13: =COUNTIF('TT '!$D$324:$D$339,TALLY!A13) -> 1 | S13: =COUNTIF('TT '!$D$346:$D$362,TALLY!A13) -> 0 | T13: =COUNTIF('TT '!$D$369:$D$383,TALLY!A13) -> 0 | U13: =COUNTIF('TT '!$D$390:$D$409,TALLY!A13) -> 0 | V13: =COUNTIF([8]TT!$D$36:$D$41,$A13) -> #VALUE! | W13: =COUNTIF('TT '!$D$416:$D$429,TALLY!A13) -> 0 | X13: =COUNTIF('TT '!$D$436:$D$449,TALLY!A13) -> 0 | Y13: =COUNTIF('TT '!$D$456:$D$474,TALLY!A13) -> 0 | Z13: =COUNTIF('TT '!$D$481:$D$495,TALLY!A13) -> 1 | AA13: =COUNTIF('TT '!$D$502:$D$519,TALLY!A13) -> 0 | AB13: =COUNTIF('TT '!$D$526:$D$540,TALLY!A13) -> 0 | AC13: =COUNTIF([8]TT!$D$36:$D$41,$A13) -> #VALUE! | AD13: =COUNTIF('TT '!$D$547:$D$556,TALLY!A13) -> 1 | AE13: =COUNTIF('TT '!$D$563:$D$577,TALLY!A13) -> 0 | AF13: =COUNTIF('TT '!$D$584:$D$598,TALLY!A13) -> 0 | AG13: =COUNTIF('TT '!$D$605:$D$617,TALLY!A13) -> 0 | AH13: =COUNTIF('TT '!$D$624:$D$636,TALLY!A13) -> 0 | AI13: =COUNTIF('TT '!$D$643:$D$654,TALLY!A13) -> 0 | AJ13: =COUNTIF([8]TT!$D$36:$D$41,$A13) -> #VALUE! | AK13: =CONCATENATE(B13,C13,D13,E13,F13,G13,I13,J13,K13,L13,M13,N13,P13,Q13,R13,S13,T13,U13,W13,X13,Y13,Z13,AA13,AB13,AD13,AE13,AF13,AG13,AH13,AI13) -> 001000010010001000000100100000 | AL13: =SUM(B13:G13) -> 1 | AM13: =SUM(I13:N13) -> 2 | AN13: =SUM(P13:U13) -> 1 | AO13: =SUM(W13:AB13) -> 1 | AP13: =SUM(AD13:AI13) -> 1
A14: ED1-MARI | B14: =COUNTIF('TT '!$D$4:$D$31,TALLY!A14) -> 0 | C14: =COUNTIF('TT '!$D$38:$D$49,TALLY!A14) -> 0 | D14: =COUNTIF('TT '!$D$56:$D$78,TALLY!A14) -> 1 | E14: =COUNTIF('TT '!$D$85:$D$105,TALLY!A14) -> 0 | F14: =COUNTIF('TT '!$D$112:$D$126,TALLY!A14) -> 0 | G14: =COUNTIF('TT '!$D$133:$D$147,TALLY!A14) -> 1 | H14: =COUNTIF('TT '!$D$4:$D$31,TALLY!G14) -> 0 | I14: =COUNTIF('TT '!$D$154:$D$173,TALLY!A14) -> 0 | J14: =COUNTIF('TT '!$D$180:$D$197,TALLY!A14) -> 1 | K14: =COUNTIF('TT '!$D$204:$D$216,TALLY!A14) -> 0 | L14: =COUNTIF('TT '!$D$223:$D$235,TALLY!A14) -> 0 | M14: =COUNTIF('TT '!$D$242:$D$257,TALLY!A14) -> 0 | N14: =COUNTIF('TT '!$D$264:$D$276,TALLY!A14) -> 0 | O14: =COUNTIF([8]TT!$D$36:$D$41,$A14) -> #VALUE! | P14: =COUNTIF('TT '!$D$283:$D$294,TALLY!A14) -> 0 | Q14: =COUNTIF('TT '!$D$301:$D$317,TALLY!A14) -> 1 | R14: =COUNTIF('TT '!$D$324:$D$339,TALLY!A14) -> 0 | S14: =COUNTIF('TT '!$D$346:$D$362,TALLY!A14) -> 0 | T14: =COUNTIF('TT '!$D$369:$D$383,TALLY!A14) -> 0 | U14: =COUNTIF('TT '!$D$390:$D$409,TALLY!A14) -> 0 | V14: =COUNTIF([8]TT!$D$36:$D$41,$A14) -> #VALUE! | W14: =COUNTIF('TT '!$D$416:$D$429,TALLY!A14) -> 0 | X14: =COUNTIF('TT '!$D$436:$D$449,TALLY!A14) -> 0 | Y14: =COUNTIF('TT '!$D$456:$D$474,TALLY!A14) -> 0 | Z14: =COUNTIF('TT '!$D$481:$D$495,TALLY!A14) -> 1 | AA14: =COUNTIF('TT '!$D$502:$D$519,TALLY!A14) -> 0 | AB14: =COUNTIF('TT '!$D$526:$D$540,TALLY!A14) -> 0 | AC14: =COUNTIF([8]TT!$D$36:$D$41,$A14) -> #VALUE! | AD14: =COUNTIF('TT '!$D$547:$D$556,TALLY!A14) -> 1 | AE14: =COUNTIF('TT '!$D$563:$D$577,TALLY!A14) -> 0 | AF14: =COUNTIF('TT '!$D$584:$D$598,TALLY!A14) -> 0 | AG14: =COUNTIF('TT '!$D$605:$D$617,TALLY!A14) -> 1 | AH14: =COUNTIF('TT '!$D$624:$D$636,TALLY!A14) -> 0 | AI14: =COUNTIF('TT '!$D$643:$D$654,TALLY!A14) -> 0 | AJ14: =COUNTIF([8]TT!$D$36:$D$41,$A14) -> #VALUE! | AK14: =CONCATENATE(B14,C14,D14,E14,F14,G14,I14,J14,K14,L14,M14,N14,P14,Q14,R14,S14,T14,U14,W14,X14,Y14,Z14,AA14,AB14,AD14,AE14,AF14,AG14,AH14,AI14) -> 001001010000010000000100100100 | AL14: =SUM(B14:G14) -> 2 | AM14: =SUM(I14:N14) -> 1 | AN14: =SUM(P14:U14) -> 1 | AO14: =SUM(W14:AB14) -> 1 | AP14: =SUM(AD14:AI14) -> 2
... A74: ED4-TEL | B74: =COUNTIF('TT '!$D$4:$D$31,TALLY!A74) -> 0 | C74: =COUNTIF('TT '!$D$38:$D$49,TALLY!A74) -> 1 | D74: =COUNTIF('TT '!$D$56:$D$78,TALLY!A74) -> 0 | E74: =COUNTIF('TT '!$D$85:$D$105,TALLY!A74) -> 0 | F74: =COUNTIF('TT '!$D$112:$D$126,TALLY!A74) -> 0 | G74: =COUNTIF('TT '!$D$133:$D$147,TALLY!A74) -> 0 | H74: =COUNTIF('TT '!$D$4:$D$31,TALLY!G74) -> 0 | I74: =COUNTIF('TT '!$D$154:$D$173,TALLY!A74) -> 1 | J74: =COUNTIF('TT '!$D$180:$D$197,TALLY!A74) -> 0 | K74: =COUNTIF('TT '!$D$204:$D$216,TALLY!A74) -> 0 | L74: =COUNTIF('TT '!$D$223:$D$235,TALLY!A74) -> 0 | M74: =COUNTIF('TT '!$D$242:$D$257,TALLY!A74) -> 0 | N74: =COUNTIF('TT '!$D$264:$D$276,TALLY!A74) -> 1 | O74: =COUNTIF([8]TT!$D$36:$D$41,$A74) -> #VALUE! | P74: =COUNTIF('TT '!$D$283:$D$294,TALLY!A74) -> 0 | Q74: =COUNTIF('TT '!$D$301:$D$317,TALLY!A74) -> 0 | R74: =COUNTIF('TT '!$D$324:$D$339,TALLY!A74) -> 0 | S74: =COUNTIF('TT '!$D$346:$D$362,TALLY!A74) -> 0 | T74: =COUNTIF('TT '!$D$369:$D$383,TALLY!A74) -> 0 | U74: =COUNTIF('TT '!$D$390:$D$409,TALLY!A74) -> 1 | V74: =COUNTIF([8]TT!$D$36:$D$41,$A74) -> #VALUE! | W74: =COUNTIF('TT '!$D$416:$D$429,TALLY!A74) -> 0 | X74: =COUNTIF('TT '!$D$436:$D$449,TALLY!A74) -> 0 | Y74: =COUNTIF('TT '!$D$456:$D$474,TALLY!A74) -> 0 | Z74: =COUNTIF('TT '!$D$481:$D$495,TALLY!A74) -> 0 | AA74: =COUNTIF('TT '!$D$502:$D$519,TALLY!A74) -> 1 | AB74: =COUNTIF('TT '!$D$526:$D$540,TALLY!A74) -> 0 | AC74: =COUNTIF([8]TT!$D$36:$D$41,$A74) -> #VALUE! | AD74: =COUNTIF('TT '!$D$547:$D$556,TALLY!A74) -> 0 | AE74: =COUNTIF('TT '!$D$563:$D$577,TALLY!A74) -> 0 | AF74: =COUNTIF('TT '!$D$584:$D$598,TALLY!A74) -> 1 | AG74: =COUNTIF('TT '!$D$605:$D$617,TALLY!A74) -> 0 | AH74: =COUNTIF('TT '!$D$624:$D$636,TALLY!A74) -> 0 | AI74: =COUNTIF('TT '!$D$643:$D$654,TALLY!A74) -> 0 | AJ74: =COUNTIF([8]TT!$D$36:$D$41,$A74) -> #VALUE! | AK74: =CONCATENATE(B74,C74,D74,E74,F74,G74,I74,J74,K74,L74,M74,N74,P74,Q74,R74,S74,T74,U74,W74,X74,Y74,Z74,AA74,AB74,AD74,AE74,AF74,AG74,AH74,AI74) -> 010000100001000001000010001000 | AL74: =SUM(B74:G74) -> 1 | AM74: =SUM(I74:N74) -> 2 | AN74: =SUM(P74:U74) -> 1 | AO74: =SUM(W74:AB74) -> 1 | AP74: =SUM(AD74:AI74) -> 1

Sheet Lecturers
A1: Unnamed: 0 | B1: Unnamed: 6 | C1: No of students | E1: BSC. AEROSPACE ENG., Year 1 | F1: Unnamed: 2 | G1: Unnamed: 4
A2: =_xlfn.CONCAT(E2,",",D2) -> AERO 157,ED1-AERO | B2: Oppong David Kofi | C2: 70 | D2: ED1-AERO | E2: AERO 157 | G2: INTRODUCTION TO AVIATION TECHNOLOGY
A3: =_xlfn.CONCAT(E3,",",D3) -> CE 155,ED1-AERO | B3: =[9]Sheet1!$G$13 -> Appiah-Brempong Miriam | C3: 70 | D3: =D2 -> ED1-AERO | E3: CE 155 | G3: ENVIRONMENTAL STUDIES
A4: =_xlfn.CONCAT(E4,",",D4) -> EE 151,ED1-AERO | B4: Oteng Gyasi Kwame | C4: 70 | D4: =D3 -> ED1-AERO | E4: EE 151 | G4: APPLIED ELECTRICITY
A5: =_xlfn.CONCAT(E5,",",D5) -> ENGL 157,ED1-AERO | B5: =[9]Sheet1!$G$15 -> Appiah Franklin Benjamin | C5: 70 | D5: =D4 -> ED1-AERO | E5: ENGL 157 | G5: COMMUNICATION SKILLS I
A6: =_xlfn.CONCAT(E6,",",D6) -> MATH 151,ED1-AERO | B6: Fosu Gabriel Obed | C6: 70 | D6: =D5 -> ED1-AERO | E6: MATH 151 | G6: ALGEBRA
A7: =_xlfn.CONCAT(E7,",",D7) -> ME 157,ED1-AERO | B7: Sackey Michael Nii | C7: 70 | D7: =D6 -> ED1-AERO | E7: ME 157 | G7: INTRODUCTION TO INFORMATION TECHNOLOGY
A8: =_xlfn.CONCAT(E8,",",D8) -> ME 159,ED1-AERO | B8: =$B$470 -> Oppong Tawiah Peter | C8: 70 | D8: =D7 -> ED1-AERO | E8: ME 159 | G8: TECHNICAL DRAWING
A9: =_xlfn.CONCAT(E9,",",D9) -> ME 281,ED2-AERO | B9: Amoabeng Kofi Owura | C9: 74 | D9: ED2-AERO | E9: ME 281 | G9: ENGINEERING MATERIALS I
A10: =_xlfn.CONCAT(E10,",",D10) -> CENG 291,ED2-AERO | B10: Oppong David Kofi | C10: 74 | D10: =D9 -> ED2-AERO | E10: CENG 291 | G10: ENGINEERING IN SOCIETY
A11: =_xlfn.CONCAT(E11,",",D11) -> AERO 293,ED2-AERO | B11: Oppong David Kofi | C11: 74 | D11: =D10 -> ED2-AERO | E11: AERO 293 | G11: AEROSPACE ENGINEERING VACATION TRAINING I
A12: =_xlfn.CONCAT(E12,",",D12) -> ME 255,ED2-AERO | B12: Agyei Agyemang Anthony | C12: 74 | D12: =D11 -> ED2-AERO | E12: ME 255 | G12: STRENGTH OF MATERIALS I
A13: =_xlfn.CONCAT(E13,",",D13) -> ENGL 263,ED2-AERO | B13: =[9]Sheet2!$G$10 -> Yeboah Philomena Ama Okyeso | C13: 74 | D13: =D12 -> ED2-AERO | E13: ENGL 263 | G13: LITERATURE IN ENGLISH I
A14: =_xlfn.CONCAT(E14,",",D14) -> MATH 251,ED2-AERO | B14: Wireko Fredrick Asenso | C14: 74 | D14: =D13 -> ED2-AERO | E14: MATH 251 | G14: DIFFERENTIAL EQUATIONS
A15: =_xlfn.CONCAT(E15,",",D15) -> ME 251,ED2-AERO | B15: Fiagbe Yesuenyeagbe Atsu Kwabla | C15: 74 | D15: =D14 -> ED2-AERO | E15: ME 251 | G15: INTRODUCTION TO FLUID MECHANICS
A16: =_xlfn.CONCAT(E16,",",D16) -> ME 261,ED2-AERO | B16: Ampofo Joshua | C16: 74 | D16: =D15 -> ED2-AERO | E16: ME 261 | G16: =[9]Sheet2!$E$14 -> ENGINEERING MECHANICS II:DYNAMICS
A17: =_xlfn.CONCAT(E17,",",D17) -> ME 295,ED2-AERO | B17: D. K. Oppong | C17: 74 | D17: =D16 -> ED2-AERO | E17: ME 295 | G17: MECHANICAL ENGINEERING LAB. I
A18: =_xlfn.CONCAT(E18,",",D18) -> ECON 151,ED3-AERO | B18: Takyi Paul Owusu | C18: 76 | D18: ED3-AERO | E18: ECON 151 | G18: INTRODUCTION TO ECONOMICS I
A19: =_xlfn.CONCAT(E19,",",D19) -> AERO 393,ED3-AERO | B19: Oppong David Kofi | C19: 76 | D19: =D18 -> ED3-AERO | E19: AERO 393 | G19: AEROSPACE ENGINEERING VACATION TRAINING II
A20: =_xlfn.CONCAT(E20,",",D20) -> AERO 351,ED3-AERO | B20: Bofah Kwasi Kete | C20: 76 | D20: =D19 -> ED3-AERO | E20: AERO 351 | G20: AERODYNAMICS I
A21: =_xlfn.CONCAT(E21,",",D21) -> AERO 391,ED3-AERO | B21: K. K. Bofah | C21: 76 | D21: =D20 -> ED3-AERO | E21: AERO 391 | G21: AEROSPACE INDUSTRY AND ENGINEERING
A22: =_xlfn.CONCAT(E22,",",D22) -> AERO 395,ED3-AERO | B22: Oppong David Kofi | C22: 76 | D22: =D21 -> ED3-AERO | E22: AERO 395 | G22: AEROSPACE ENGINEERING LAB. I
A23: =_xlfn.CONCAT(E23,",",D23) -> MATH 351,ED3-AERO | B23: Borkor Reindorf Nartey | C23: 76 | D23: =D22 -> ED3-AERO | E23: MATH 351 | G23: NUMERICAL ANALYSIS
A24: =_xlfn.CONCAT(E24,",",D24) -> STAT 253,ED3-AERO | B24: C. F. A. Yirenkyi | C24: 76 | D24: =D23 -> ED3-AERO | E24: STAT 253 | G24: PROBABILITY AND STATISTICS
A25: =_xlfn.CONCAT(E25,",",D25) -> ME 363,ED3-AERO | B25: F. W. Adam | C25: 76 | D25: =D24 -> ED3-AERO | E25: ME 363 | G25: AUTOMATIC CONTROL I
A26: =_xlfn.CONCAT(E26,",",D26) -> AERO 473,ED4-AERO | B26: =[9]Sheet4!G8 -> Oppong David Kofi | C26: 61 | D26: ED4-AERO | E26: =[9]Sheet4!B8 -> AERO 473 | G26: =[9]Sheet4!E8 -> AEROSPACE VEHICLE DESIGN
A27: =_xlfn.CONCAT(E27,",",D27) -> AERO 483,ED4-AERO | B27: =[9]Sheet4!G9 -> Oppong David Kofi | C27: 61 | D27: =D26 -> ED4-AERO | E27: =[9]Sheet4!B9 -> AERO 483 | G27: =[9]Sheet4!E9 -> AVIONICS
A28: =_xlfn.CONCAT(E28,",",D28) -> AERO 491,ED4-AERO | B28: =[9]Sheet4!G10 -> Takyi Gabriel | C28: 61 | D28: =D27 -> ED4-AERO | E28: =[9]Sheet4!B10 -> AERO 491 | G28: =[9]Sheet4!E10 -> AVIATION BUSINESS MANAGEMENT
A29: =_xlfn.CONCAT(E29,",",D29) -> AERO 493,ED4-AERO | B29: =[9]Sheet4!G11 -> Oppong David Kofi | C29: 61 | D29: =D28 -> ED4-AERO | E29: =[9]Sheet4!B11 -> AERO 493 | G29: =[9]Sheet4!E11 -> AEROSPACE ENGINEERING VACATION TRAINING III
A30: =_xlfn.CONCAT(E30,",",D30) -> AERO 495,ED4-AERO | B30: =[9]Sheet4!G12 -> Oppong Tawiah Peter | C30: 61 | D30: =D29 -> ED4-AERO | E30: =[9]Sheet4!B12 -> AERO 495 | G30: =[9]Sheet4!E12 -> AIRCRAFT MAINTENANCE ENGINEERING
A31: =_xlfn.CONCAT(E31,",",D31) -> AERO 497,ED4-AERO | B31: =[9]Sheet4!G13 -> Tay Godwin Fabiola Kwaku | C31: 61 | D31: =D30 -> ED4-AERO | E31: =[9]Sheet4!B13 -> AERO 497 | G31: =[9]Sheet4!E13 -> PROJECT I
A32: =_xlfn.CONCAT(E32,",",D32) -> ME 451,ED4-AERO | B32: =[9]Sheet4!G14 -> Opoku Richard | C32: 61 | D32: =D31 -> ED4-AERO | E32: =[9]Sheet4!B14 -> ME 451 | G32: =[9]Sheet4!E14 -> BEHAVIOUR OF REAL FLUIDS
A33: =_xlfn.CONCAT(E33,",",D33) -> ME 465,ED4-AERO | B33: =[9]Sheet4!G15 -> Sekyere Charles Kofi Kafui | C33: 61 | D33: =D32 -> ED4-AERO | E33: =[9]Sheet4!B15 -> ME 465 | G33: =[9]Sheet4!E15 -> AIR CONDITIONING AND REFRIGERATION
A34: =_xlfn.CONCAT(E34,",",D34) -> ME 467,ED4-AERO | B34: =[9]Sheet4!G16 -> Quansah David Ato | C34: 61 | D34: =D33 -> ED4-AERO | E34: =[9]Sheet4!B16 -> ME 467 | G34: =[9]Sheet4!E16 -> RENEWABLE ENERGY CONVERSION
A35: =_xlfn.CONCAT(E35,",",D35) -> ME 473,ED4-AERO | B35: =[9]Sheet4!G17 -> Afriyie Nyarko Frank Kwabena | C35: 61 | D35: =D34 -> ED4-AERO | E35: =[9]Sheet4!B17 -> ME 473 | G35: =[9]Sheet4!E17 -> COMPUTER AIDED DESIGN AND MANUFACTURING
A36: =_xlfn.CONCAT(E36,",",D36) -> ME 499,ED4-AERO | B36: =[9]Sheet4!G18 -> Mensah Lena Dzifa | C36: 61 | D36: =D35 -> ED4-AERO | E36: =[9]Sheet4!B18 -> ME 499 | G36: =[9]Sheet4!E18 -> OPERATIONS RESEARCH
A37: =_xlfn.CONCAT(E37,",",D37) -> ,ED4-AERO | C37: 61 | D37: =D36 -> ED4-AERO | E37: =[9]Sheet4!B19 | G37: =[9]Sheet4!E19 -> 0
A38: =_xlfn.CONCAT(E38,",",D38) -> AE 153,ED1-AE | B38: =[9]Sheet4!G22 -> Bessah Enoch | C38: 126 | D38: ED1-AE | E38: =[9]Sheet4!B22 -> AE 153 | G38: =[9]Sheet4!E22 -> AGRIC. METEOROLOGY AND CLIMATOLOGY
A39: =_xlfn.CONCAT(E39,",",D39) -> EE 151,ED1-AE | B39: =[9]Sheet4!G23 -> Prah II Nicholas Kwesi | C39: 126 | D39: =D38 -> ED1-AE | E39: =[9]Sheet4!B23 -> EE 151 | G39: =[9]Sheet4!E23 -> APPLIED ELECTRICITY
A40: =_xlfn.CONCAT(E40,",",D40) -> ENGL 157,ED1-AE | B40: =[9]Sheet4!G24 -> Yeboah Philomena Ama Okyeso | C40: 126 | D40: =D39 -> ED1-AE | E40: =[9]Sheet4!B24 -> ENGL 157 | G40: =[9]Sheet4!E24 -> COMMUNICATION SKILLS I
A41: =_xlfn.CONCAT(E41,",",D41) -> MATH 151,ED1-AE | B41: =[9]Sheet4!G25 -> Asamoah Joshua Kiddy Kwasi | C41: 126 | D41: =D40 -> ED1-AE | E41: =[9]Sheet4!B25 -> MATH 151 | G41: =[9]Sheet4!E25 -> ALGEBRA
A42: =_xlfn.CONCAT(E42,",",D42) -> ME 159,ED1-AE | B42: =[9]Sheet4!G26 -> Aveyire Joseph | C42: 126 | D42: =D41 -> ED1-AE | E42: =[9]Sheet4!B26 -> ME 159 | G42: =[9]Sheet4!E26 -> TECHNICAL DRAWING
A43: =_xlfn.CONCAT(E43,",",D43) -> ME 195,ED1-AE | B43: =[9]Sheet4!G27 -> Oppong David Kofi | C43: 126 | D43: =D42 -> ED1-AE | E43: =[9]Sheet4!B27 -> ME 195 | G43: =[9]Sheet4!E27 -> ENGINEERING TECHNOLOGY I
A44: =_xlfn.CONCAT(E44,",",D44) -> CE 155,ED1-AE | B44: =[9]Sheet4!G28 -> Buamah Richard Akwasi | C44: 126 | D44: =D43 -> ED1-AE | E44: =[9]Sheet4!B28 -> CE 155 | G44: =[9]Sheet4!E28 -> ENVIRONMENTAL STUDIES
A45: =_xlfn.CONCAT(E45,",",D45) -> CENG 291,ED2-AE | B45: =[9]Sheet5!G8 -> Lavie Jerome Dela | C45: 155 | D45: ED2-AE | E45: =[9]Sheet5!B8 -> CENG 291 | G45: =[9]Sheet5!E8 -> ENGINEERING IN SOCIETY
A46: =_xlfn.CONCAT(E46,",",D46) -> ENGL 263,ED2-AE | B46: =[9]Sheet5!G9 -> Yeboah Philomena Ama Okyeso | C46: 155 | D46: =D45 -> ED2-AE | E46: =[9]Sheet5!B9 -> ENGL 263 | G46: =[9]Sheet5!E9 -> LITERATURE IN ENGLISH I
A47: =_xlfn.CONCAT(E47,",",D47) -> MATH 251,ED2-AE | B47: =[9]Sheet5!G10 -> Wireko Fredrick Asenso | C47: 155 | D47: =D46 -> ED2-AE | E47: =[9]Sheet5!B10 -> MATH 251 | G47: =[9]Sheet5!E10 -> DIFFERENTIAL EQUATIONS
A48: =_xlfn.CONCAT(E48,",",D48) -> ME 251,ED2-AE | B48: =[9]Sheet5!G11 -> Fiagbe Yesuenyeagbe Atsu Kwabla | C48: 155 | D48: =D47 -> ED2-AE | E48: =[9]Sheet5!B11 -> ME 251 | G48: =[9]Sheet5!E11 -> FLUID MECHANICS I
A49: =_xlfn.CONCAT(E49,",",D49) -> ME 255,ED2-AE | B49: =[9]Sheet5!G12 -> Boahen Samuel | C49: 155 | D49: =D48 -> ED2-AE | E49: =[9]Sheet5!B12 -> ME 255 | G49: =[9]Sheet5!E12 -> STRENGTH OF MATERIALS I
A50: =_xlfn.CONCAT(E50,",",D50) -> ME 259,ED2-AE | B50: =[9]Sheet5!G13 -> Asante Eric Amoah | C50: 155 | D50: =D49 -> ED2-AE | E50: =[9]Sheet5!B13 -> ME 259 | G50: =[9]Sheet5!E13 -> APPLICATIONS OF COMPUTER GRAPHICS
A51: =_xlfn.CONCAT(E51,",",D51) -> ME 265,ED2-AE | B51: =[9]Sheet5!G14 -> Forson Francis Kofi | C51: 155 | D51: =D50 -> ED2-AE | E51: =[9]Sheet5!B14 -> ME 265 | G51: =[9]Sheet5!E14 -> THERMODYNAMICS I
A52: =_xlfn.CONCAT(E52,",",D52) -> ME 295,ED2-AE | B52: =[9]Sheet5!G15 -> Adam Faisal Wahib | C52: 155 | D52: =D51 -> ED2-AE | E52: =[9]Sheet5!B15 -> ME 295 | G52: =[9]Sheet5!E15 -> MECHANICAL ENGINEERING LAB. I
A53: =_xlfn.CONCAT(E53,",",D53) -> AE 351,ED3-AE | B53: =[9]Sheet6!G8 -> Kyei-Baffour Nicholas | C53: 105 | D53: ED3-AE | E53: =[9]Sheet6!B8 -> AE 351 | G53: =[9]Sheet6!E8 -> SOIL AND WATER ENGINEERING
A54: =_xlfn.CONCAT(E54,",",D54) -> AE 353,ED3-AE | B54: =[9]Sheet6!G9 -> Akowuah Joseph Oppong | C54: 105 | D54: =D53 -> ED3-AE | E54: =[9]Sheet6!B9 -> AE 353 | G54: =[9]Sheet6!E9 -> AGRICULTURAL MATERIALS HANDLING AND PROCESSING
A55: =_xlfn.CONCAT(E55,",",D55) -> AE 373,ED3-AE | B55: =[9]Sheet6!G10 -> Aveyire Joseph | C55: 105 | D55: =D54 -> ED3-AE | E55: =[9]Sheet6!B10 -> AE 373 | G55: =[9]Sheet6!E10 -> MACHINE DESIGN I
A56: =_xlfn.CONCAT(E56,",",D56) -> AE 381,ED3-AE | B56: =[9]Sheet6!G11 -> Amponsah William | C56: 105 | D56: =D55 -> ED3-AE | E56: =[9]Sheet6!B11 -> AE 381 | G56: =[9]Sheet6!E11 -> COMPUTER APPLICATION FOR AGRICULTURAL ENGINEERS
A57: =_xlfn.CONCAT(E57,",",D57) -> MATH 351,ED3-AE | B57: =[9]Sheet6!G12 -> Borkor Reindorf Nartey | C57: 105 | D57: =D56 -> ED3-AE | E57: =[9]Sheet6!B12 -> MATH 351 | G57: =[9]Sheet6!E12 -> NUMERICAL ANALYSIS
A58: =_xlfn.CONCAT(E58,",",D58) -> ME 355,ED3-AE | B58: =[9]Sheet6!G13 -> Agyei Agyemang Anthony | C58: 105 | D58: =D57 -> ED3-AE | E58: =[9]Sheet6!B13 -> ME 355 | G58: =[9]Sheet6!E13 -> STRENGTH OF MATERIALS II
A59: =_xlfn.CONCAT(E59,",",D59) -> ME 365,ED3-AE | B59: =[9]Sheet6!G14 -> Forson Francis Kofi | C59: 105 | D59: =D58 -> ED3-AE | E59: =[9]Sheet6!B14 -> ME 365 | G59: =[9]Sheet6!E14 -> THERMODYNAMICS II
A60: =_xlfn.CONCAT(E60,",",D60) -> AE 451,ED4-AE | B60: =[9]Sheet7!G8 -> Agodzo Sampson Kwaku | C60: 103 | D60: ED4-AE | E60: =[9]Sheet7!B8 -> AE 451 | G60: =[9]Sheet7!E8 -> IRRIGATION AND DRAINAGE
A61: =_xlfn.CONCAT(E61,",",D61) -> AE 453,ED4-AE | B61: =[9]Sheet7!G9 -> Lavie Jerome Dela | C61: 103 | D61: =D60 -> ED4-AE | E61: =[9]Sheet7!B9 -> AE 453 | G61: =[9]Sheet7!E9 -> ENVIRONMENTAL CONTROL AND LIVESTOCK HOUSING
A62: =_xlfn.CONCAT(E62,",",D62) -> AE 457,ED4-AE | B62: =[9]Sheet7!G10 -> Darko Joseph Ofei | C62: 103 | D62: =D61 -> ED4-AE | E62: =[9]Sheet7!B10 -> AE 457 | G62: =[9]Sheet7!E10 -> CROP PROCESSING
A63: =_xlfn.CONCAT(E63,",",D63) -> AE 459,ED4-AE | B63: =[9]Sheet7!G11 -> Aikins Stephen Hill Mends | C63: 103 | D63: =D62 -> ED4-AE | E63: =[9]Sheet7!B11 -> AE 459 | G63: =[9]Sheet7!E11 -> ADVANCED FARM POWER AND MACHINERY
A64: =_xlfn.CONCAT(E64,",",D64) -> AE 471,ED4-AE | B64: =[9]Sheet7!G12 -> Bart Plange Ato | C64: 103 | D64: =D63 -> ED4-AE | E64: =[9]Sheet7!B12 -> AE 471 | G64: =[9]Sheet7!E12 -> FARM STRUCTURES
A65: =_xlfn.CONCAT(E65,",",D65) -> AE 497,ED4-AE | B65: =[9]Sheet7!G13 -> Darko Clara Bernice | C65: 103 | D65: =D64 -> ED4-AE | E65: =[9]Sheet7!B13 -> AE 497 | G65: =[9]Sheet7!E13 -> PROJECT I
A66: =_xlfn.CONCAT(E66,",",D66) -> ME 491,ED4-AE | B66: =[9]Sheet7!G14 -> Aikins Stephen Hill Mends | C66: 103 | D66: =D65 -> ED4-AE | E66: =[9]Sheet7!B14 -> ME 491 | G66: =[9]Sheet7!E14 -> ENGINEERING ECONOMICS AND MANAGEMENT
A67: =_xlfn.CONCAT(E67,",",D67) -> AE 499,ED4-AE | B67: =[9]Sheet7!G15 -> Asante Eric Amoah | C67: 103 | D67: =D66 -> ED4-AE | E67: =[9]Sheet7!B15 -> AE 499 | G67: =[9]Sheet7!E15 -> VACATION TRAINING
A68: =_xlfn.CONCAT(E68,",",D68) -> AI 150,ED1-AUTO | B68: =[9]Sheet7!G19 -> Nunoo-Mensah Henry | C68: 88 | D68: ED1-AUTO | E68: =[9]Sheet7!B19 -> AI 150 | G68: =[9]Sheet7!E19 -> FUNDAMENTALS OF RESPONSIBLE AI FOR ALL
A69: =_xlfn.CONCAT(E69,",",D69) -> AME 167,ED1-AUTO | B69: =[9]Sheet7!G20 -> Tay Godwin Fabiola Kwaku | C69: 88 | D69: =D68 -> ED1-AUTO | E69: =[9]Sheet7!B20 -> AME 167 | G69: =[9]Sheet7!E20 -> COMPUTER PROGRAMMING FOR ENGINEERS
A70: =_xlfn.CONCAT(E70,",",D70) -> ECON 151,ED1-AUTO | B70: =[9]Sheet7!G21 -> Takyi Paul Owusu | C70: 88 | D70: =D69 -> ED1-AUTO | E70: =[9]Sheet7!B21 -> ECON 151 | G70: =[9]Sheet7!E21 -> INTRODUCTION TO ECONOMICS
A71: =_xlfn.CONCAT(E71,",",D71) -> EE 151,ED1-AUTO | B71: =[9]Sheet7!G22 -> Acheampong Francisca Adoma | C71: 88 | D71: =D70 -> ED1-AUTO | E71: =[9]Sheet7!B22 -> EE 151 | G71: =[9]Sheet7!E22 -> APPLIED ELECTRICITY
A72: =_xlfn.CONCAT(E72,",",D72) -> ENGL 157,ED1-AUTO | B72: =[9]Sheet7!G23 -> Sarfo-Adu Kwasi | C72: 88 | D72: =D71 -> ED1-AUTO | E72: =[9]Sheet7!B23 -> ENGL 157 | G72: =[9]Sheet7!E23 -> COMMUNICATION SKILLS I
A73: =_xlfn.CONCAT(E73,",",D73) -> MATH 151,ED1-AUTO | B73: =[9]Sheet7!G24 -> Azure Isaac | C73: 88 | D73: =D72 -> ED1-AUTO | E73: =[9]Sheet7!B24 -> MATH 151 | G73: =[9]Sheet7!E24 -> ALGEBRA
A74: =_xlfn.CONCAT(E74,",",D74) -> ME 159,ED1-AUTO | B74: =[9]Sheet7!G25 -> Sekyere Charles Kofi Kafui | C74: 88 | D74: =D73 -> ED1-AUTO | E74: =[9]Sheet7!B25 -> ME 159 | G74: =[9]Sheet7!E25 -> TECHNICAL DRAWING
A75: =_xlfn.CONCAT(E75,",",D75) -> ME 195,ED1-AUTO | B75: =[9]Sheet7!G26 -> Tay Godwin Fabiola Kwaku | C75: 88 | D75: =D74 -> ED1-AUTO | E75: =[9]Sheet7!B26 -> ME 195 | G75: =[9]Sheet7!E26 -> ENGINEERING TECHNOLOGY
A76: =_xlfn.CONCAT(E76,",",D76) -> AME 295,ED2-AUTO | B76: =[9]Sheet8!G8 -> Ayetor Godwin Kafui Kwesi | C76: 77 | D76: ED2-AUTO | E76: =[9]Sheet8!B8 -> AME 295 | G76: =[9]Sheet8!E8 -> AUTOMOBILE ENGINEERING LABORATORY I
A77: =_xlfn.CONCAT(E77,",",D77) -> CENG 291,ED2-AUTO | B77: =[9]Sheet8!G9 -> Amoabeng Kofi Owura | C77: 77 | D77: =D76 -> ED2-AUTO | E77: =[9]Sheet8!B9 -> CENG 291 | G77: =[9]Sheet8!E9 -> ENGINEERING IN SOCIETY
A78: =_xlfn.CONCAT(E78,",",D78) -> MATH 251,ED2-AUTO | B78: =[9]Sheet8!G10 -> Eghan Rhydal Esi | C78: 77 | D78: =D77 -> ED2-AUTO | E78: =[9]Sheet8!B10 -> MATH 251 | G78: =[9]Sheet8!E10 -> DIFFERENTIAL EQUATIONS
A79: =_xlfn.CONCAT(E79,",",D79) -> ME 251,ED2-AUTO | B79: =[9]Sheet8!G11 -> Tay Godwin Fabiola Kwaku | C79: 77 | D79: =D78 -> ED2-AUTO | E79: =[9]Sheet8!B11 -> ME 251 | G79: =[9]Sheet8!E11 -> INTRODUCTION TO FLUID MECHANICS
A80: =_xlfn.CONCAT(E80,",",D80) -> ME 255,ED2-AUTO | B80: =[9]Sheet8!G12 -> Dzebre Denis Edem Kwame | C80: 77 | D80: =D79 -> ED2-AUTO | E80: =[9]Sheet8!B12 -> ME 255 | G80: =[9]Sheet8!E12 -> STRENGTH OF MATERIALS I
A81: =_xlfn.CONCAT(E81,",",D81) -> ME 259,ED2-AUTO | B81: =[9]Sheet8!G13 -> Ayetor Godwin Kafui Kwesi | C81: 77 | D81: =D80 -> ED2-AUTO | E81: =[9]Sheet8!B13 -> ME 259 | G81: =[9]Sheet8!E13 -> APPLICATIONS OF COMPUTER GRAPHICS
A82: =_xlfn.CONCAT(E82,",",D82) -> ME 261,ED2-AUTO | B82: =[9]Sheet8!G14 -> Ampofo Joshua | C82: 77 | D82: =D81 -> ED2-AUTO | E82: =[9]Sheet8!B14 -> ME 261 | G82: =[9]Sheet8!E14 -> ENGINEERING MECHANICS II:DYNAMICS
A83: =_xlfn.CONCAT(E83,",",D83) -> ME 281,ED2-AUTO | B83: =[9]Sheet8!G15 -> Boahen Samuel | C83: 77 | D83: =D82 -> ED2-AUTO | E83: =[9]Sheet8!B15 -> ME 281 | G83: =[9]Sheet8!E15 -> ENGINEERING MATERIALS I
A84: =_xlfn.CONCAT(E84,",",D84) -> ,ED2-AUTO | C84: 77 | D84: =D83 -> ED2-AUTO | E84: =[9]Sheet8!B16
A85: =_xlfn.CONCAT(E85,",",D85) -> AME 365,ED3-AUTO | B85: =[9]Sheet9!G8 -> Forson Francis Kofi | C85: 47 | D85: ED3-AUTO | E85: =[9]Sheet9!B8 -> AME 365 | G85: =[9]Sheet9!E8 -> HEAT TRANSFER AND COMBUSTION
A86: =_xlfn.CONCAT(E86,",",D86) -> AME 371,ED3-AUTO | B86: =[9]Sheet9!G9 -> Ayetor Godwin Kafui Kwesi | C86: 47 | D86: =D85 -> ED3-AUTO | E86: =[9]Sheet9!B9 -> AME 371 | G86: =[9]Sheet9!E9 -> LAND VEHICLE DESIGN
A87: =_xlfn.CONCAT(E87,",",D87) -> AME 373,ED3-AUTO | B87: =[9]Sheet9!G10 -> Andoh Prince Yaw | C87: 47 | D87: =D86 -> ED3-AUTO | E87: =[9]Sheet9!B10 -> AME 373 | G87: =[9]Sheet9!E10 -> DESIGN OF AUTO MECHANICAL SYSTEMS
A88: =_xlfn.CONCAT(E88,",",D88) -> AME 379,ED3-AUTO | B88: =[9]Sheet9!G11 -> Ayetor Godwin Kafui Kwesi | C88: 47 | D88: =D87 -> ED3-AUTO | E88: =[9]Sheet9!B11 -> AME 379 | G88: =[9]Sheet9!E11 -> AUTOMOBILE ENGINEERING VACATION TRAINING I
A89: =_xlfn.CONCAT(E89,",",D89) -> AME 381,ED3-AUTO | B89: =[9]Sheet9!G12 -> Ayetor Godwin Kafui Kwesi | C89: 47 | D89: =D88 -> ED3-AUTO | E89: =[9]Sheet9!B12 -> AME 381 | G89: =[9]Sheet9!E12 -> AUTOMOTIVE WORKSHOP PRACTICE I
A90: =_xlfn.CONCAT(E90,",",D90) -> AME 395,ED3-AUTO | B90: =[9]Sheet9!G13 -> Dzebre Denis Edem Kwame | C90: 47 | D90: =D89 -> ED3-AUTO | E90: =[9]Sheet9!B13 -> AME 395 | G90: =[9]Sheet9!E13 -> AUTOMOBILE ENGINEERING LABORATORY III
A91: =_xlfn.CONCAT(E91,",",D91) -> MATH 351,ED3-AUTO | B91: =[9]Sheet9!G14 -> Azure Isaac | C91: 47 | D91: =D90 -> ED3-AUTO | E91: =[9]Sheet9!B14 -> MATH 351 | G91: =[9]Sheet9!E14 -> NUMERICAL ANALYSIS
A92: =_xlfn.CONCAT(E92,",",D92) -> ME 361,ED3-AUTO | B92: =[9]Sheet9!G15 -> Ampofo Joshua | C92: 47 | D92: =D91 -> ED3-AUTO | E92: =[9]Sheet9!B15 -> ME 361 | G92: =[9]Sheet9!E15 -> DYNAMICS OF MACHINERY
A93: =_xlfn.CONCAT(E93,",",D93) -> STAT 253,ED3-AUTO | B93: =[9]Sheet9!G16 -> Okutu John Kwadey | C93: 47 | D93: =D92 -> ED3-AUTO | E93: =[9]Sheet9!B16 -> STAT 253 | G93: =[9]Sheet9!E16 -> PROBABILITY AND STATISTICS
A94: =_xlfn.CONCAT(E94,",",D94) -> AME 455,ED4-AUTO | B94: =[9]Sheet10!G8 -> Sekyere Charles Kofi Kafui | C94: 32 | D94: ED4-AUTO | E94: =[9]Sheet10!B8 -> AME 455 | G94: =[9]Sheet10!E8 -> VEHICLE AIR-CONDITIONING AND REFRIGERATION
A95: =_xlfn.CONCAT(E95,",",D95) -> AME 467,ED4-AUTO | B95: =[9]Sheet10!G9 -> Abu Frimpong Solomon | C95: 32 | D95: =D94 -> ED4-AUTO | E95: =[9]Sheet10!B9 -> AME 467 | G95: =[9]Sheet10!E9 -> AUTOMOTIVE COMPRESSION-IGNITION ENGINES
A96: =_xlfn.CONCAT(E96,",",D96) -> AME 479,ED4-AUTO | B96: =[9]Sheet10!G10 -> Afriyie Nyarko Frank Kwabena | C96: 32 | D96: =D95 -> ED4-AUTO | E96: =[9]Sheet10!B10 -> AME 479 | G96: =[9]Sheet10!E10 -> AUTOMOBILE ENGINEERING VACATION TRAINING II
A97: =_xlfn.CONCAT(E97,",",D97) -> AME 485,ED4-AUTO | B97: =[9]Sheet10!G11 -> Abu Frimpong Solomon | C97: 32 | D97: =D96 -> ED4-AUTO | E97: =[9]Sheet10!B11 -> AME 485 | G97: =[9]Sheet10!E11 -> AUTOMATIC POWER TRAIN
A98: =_xlfn.CONCAT(E98,",",D98) -> AME 495,ED4-AUTO | B98: =[9]Sheet10!G12 -> Ayetor Godwin Kafui Kwesi | C98: 32 | D98: =D97 -> ED4-AUTO | E98: =[9]Sheet10!B12 -> AME 495 | G98: =[9]Sheet10!E12 -> AUTOMOTIVE WORKSHOP PRACTICE II
A99: =_xlfn.CONCAT(E99,",",D99) -> AME 497,ED4-AUTO | B99: =[9]Sheet10!G13 -> Tay Godwin Fabiola Kwaku | C99: 32 | D99: =D98 -> ED4-AUTO | E99: =[9]Sheet10!B13 -> AME 497 | G99: =[9]Sheet10!E13 -> FINAL YEAR PROJECT I
A100: =_xlfn.CONCAT(E100,",",D100) -> ME 453,ED4-AUTO | B100: =[9]Sheet10!G14 -> Fiagbe Yesuenyeagbe Atsu Kwabla | C100: 32 | D100: =D99 -> ED4-AUTO | E100: =[9]Sheet10!B14 -> ME 453 | G100: =[9]Sheet10!E14 -> HYDRAULICS AND PNEUMATICS
...

Sheet ROOMS
A1: College of Engineering
A2: Available Rooms
A3: Rooms | B3: Exam Capacity | E3: Lecturers
A4: LT | B4: 60 | C4: COHORT A1 | D4: BAMFO KWAKYE A | E4: 1
A5: RMA | B5: 48 | E5: 1
A6: RMB | B6: 48 | E6: 1
A7: VSLA | B7: 100 | E7: 2
A8: 206 | B8: 48 | C8: COHORT A2 | E8: 1
A9: 303 | B9: 60 | E9: 1
A10: 304 | B10: 50 | E10: 1
A11: N1 | B11: 50 | C11: COHORT A3 | E11: 1
A12: N2 | B12: 48 | E12: 1 | F12: =SUM(B4:B12) -> 512
A13: PB001 | B13: 90 | C13: COHORT B1 | D13: PETROLEUM BUILDING B | E13: 2
A14: PB020 | B14: 90 | E14: 2
A15: PB014 | B15: 90 | E15: 2
A16: PB012
A17: PB008 | B17: 60 | E17: 2
A18: PB201 | B18: 90 | C18: COHORT B2 | E18: 2
A19: PB214 | B19: 90 | E19: 2
A20: PB212 | B20: 50 | E20: 1
A21: PB208 | B21: 60 | E21: 1 | F21: =SUM(B13:B21) -> 620
A22: VCR | B22: 50 | C22: COHORT C1 | D22: EXAMS OFFICE C | E22: 1
A23: ECR | B23: 50 | E23: 1
A24: A110 | B24: 60 | E24: 1
A25: EA | B25: 60 | C25: COHORT C2 | E25: 1
A26: NAF1 | B26: 90 | E26: 2 | F26: =SUM(B22:B26) -> 310
A27: NEB-SF | B27: 170 | C27: COHORT D1 | D27: NEB D | E27: 3
A28: NEB-TF | B28: 170 | C28: COHORT D2 | E28: 3
A29: NEB-FF1 | B29: 110 | C29: COHORT D3 | E29: 2
A30: NEB-FF2 | B30: 60 | E30: 1 | F30: =SUM(B27:B30) -> 510
E31: 1
A32: Total | B32: =SUM(B4:B30) -> 1952 | E32: =SUM(E4:E30) -> 39

Sheet WATER (2)
A1: College of Engineering
A2: Available Rooms | L2: College of Engineering
B3: INVIGILATORS | E3: TOTAL BOTLES | F3: Bottles x 6S + 1 | G3: Total Pack | H3: TOTAL BOTTLES | I3: TOTAL BOTTLES FOR PERIOD | J3: ROOM USAGE | L3: Available Rooms
A4: Rooms | B4: TA | C4: LT | D4: ATTD | E4: PER SESSION | F4: TT BOTTLES | G4: PACKS PER DAY | H4: OVERALL | L4: Rooms | M4: Name | N4: Contact | O4: Signature | P4: Bottles/Packs Collected
A5: LT | B5: 1 | C5: 1 | D5: 1 | E5: =SUM(B5:D5) -> 3 | F5: =E5*6 -> 18 | G5: =F5/16 -> 1.125 | I5: =E5*J5 -> 90 | J5: 30 | L5: LT | P5: 3btls
A6: RM A | B6: 1 | C6: 1 | D6: 1 | E6: =SUM(C6:D6) -> 2 | F6: =E6*6 -> 12 | G6: =F6/16 -> 0.75 | I6: =E6*J6 -> 60 | J6: 30 | L6: RMA | P6: 3btl
A7: RM B | B7: 1 | C7: 1 | D7: 1 | E7: =SUM(C7:D7) -> 2 | F7: =E7*6 -> 12 | G7: =F7/16 -> 0.75 | I7: =E7*J7 -> 60 | J7: 30 | L7: RMB | P7: 3btls
A8: 206 | B8: 1 | C8: 1 | D8: 1 | E8: =SUM(C8:D8) -> 2 | F8: =E8*6 -> 12 | G8: =F8/16 -> 0.75 | I8: =E8*J8 -> 52 | J8: 26 | L8: 206 | P8: 3btls
A9: 303 | B9: 1 | C9: 1 | D9: 1 | E9: =SUM(C9:D9) -> 2 | F9: =E9*6 -> 12 | G9: =F9/16 -> 0.75 | I9: =E9*J9 -> 60 | J9: 30 | L9: 303 | P9: 3btls
A10: 304 | B10: 1 | C10: 1 | D10: 1 | E10: =SUM(C10:D10) -> 2 | F10: =E10*6 -> 12 | G10: =F10/16 -> 0.75 | I10: =E10*J10 -> 52 | J10: 26 | L10: 304 | P10: 3btls
A11: EA | B11: 1 | C11: 1 | D11: 1 | E11: =SUM(C11:D11) -> 2 | F11: =E11*6 -> 12 | G11: =F11/16 -> 0.75 | I11: =E11*J11 -> 56 | J11: 28 | L11: EA | P11: 3btls
A12: NAF1 | B12: 1 | C12: 2 | D12: 1 | E12: =SUM(C12:D12) -> 3 | F12: =E12*6 -> 18 | G12: =F12/16 -> 1.125 | I12: =E12*J12 -> 90 | J12: 30 | L12: NAF1 | P12: 3btls
A13: A110 | B13: 1 | C13: 1 | D13: 1 | E13: =SUM(C13:D13) -> 2 | F13: =E13*6 -> 12 | G13: =F13/16 -> 0.75 | I13: =E13*J13 -> 56 | J13: 28 | L13: A110 | P13: 3btls
A14: VSLA | B14: 1 | C14: 2 | D14: 1 | E14: =SUM(C14:D14) -> 3 | F14: =E14*6 -> 18 | G14: =F14/16 -> 1.125 | I14: =E14*J14 -> 90 | J14: 30 | L14: VSLA | P14: 3btls
A15: PB001 | B15: 1 | C15: 2 | D15: 1 | E15: =SUM(C15:D15) -> 3 | F15: =E15*6 -> 18 | G15: =F15/16 -> 1.125 | I15: =E15*J15 -> 90 | J15: 30 | L15: PB001 | P15: 3btls
A16: PB020 | B16: 1 | C16: 2 | D16: 1 | E16: =SUM(C16:D16) -> 3 | F16: =E16*6 -> 18 | G16: =F16/16 -> 1.125 | I16: =E16*J16 -> 90 | J16: 30 | L16: PB020 | P16: 3btls
A17: PB014 | B17: 1 | C17: 2 | D17: 1 | E17: =SUM(C17:D17) -> 3 | F17: =E17*6 -> 18 | G17: =F17/16 -> 1.125 | I17: =E17*J17 -> 90 | J17: 30 | L17: PB014 | P17: 3btls
A18: PB008 | B18: 1 | C18: 2 | D18: 1 | E18: =SUM(C18:D18) -> 3 | F18: =E18*6 -> 18 | G18: =F18/16 -> 1.125 | I18: =E18*J18 -> 90 | J18: 30 | L18: PB008 | P18: 3btls
A19: PB201 | B19: 1 | C19: 2 | D19: 1 | E19: =SUM(C19:D19) -> 3 | F19: =E19*6 -> 18 | G19: =F19/16 -> 1.125 | I19: =E19*J19 -> 90 | J19: 30 | L19: PB201 | P19: 3btls
A20: PB214 | B20: 1 | C20: 2 | D20: 1 | E20: =SUM(C20:D20) -> 3 | F20: =E20*6 -> 18 | G20: =F20/16 -> 1.125 | I20: =E20*J20 -> 90 | J20: 30 | L20: PB214 | P20: 3btls
A21: PB212 | B21: 1 | C21: 1 | D21: 1 | E21: =SUM(C21:D21) -> 2 | F21: =E21*6 -> 12 | G21: =F21/16 -> 0.75 | I21: =E21*J21 -> 60 | J21: 30 | L21: PB212 | P21: 3btls
A22: PB208 | B22: 1 | C22: 1 | D22: 1 | E22: =SUM(C22:D22) -> 2 | F22: =E22*6 -> 12 | G22: =F22/16 -> 0.75 | I22: =E22*J22 -> 60 | J22: 30 | L22: PB208 | P22: 3btls
... A29: NEB-TF | B29: 2 | C29: 3 | D29: 2 | E29: =SUM(C29:D29) -> 5 | F29: =E29*6 -> 30 | G29: =F29/16 -> 1.875 | I29: =E29*J29 -> 150 | J29: 30 | L29: NEB-TF | P29: 5btls
A30: Computer Based | E30: 3 | F30: 80 | G30: 4 | H30: 10pks | I30: 80 | J30: 1 | L30: Computer Based | P30: 10pks
A31: Biometric | E31: 18 | F31: 126 | G31: 6 | H31: 8pks | I31: =6*F31 -> 756 | J31: 32 | L31: Biometric | P31: 8pks
A32: NEB OFFICE | E32: 9 | F32: 64 | G32: 2 | H32: 4pks | I32: =6*F32 -> 384 | J32: 32 | L32: NEB OFFICE | P32: 4pks
A33: EXAMS OFFICE | E33: 17 | F33: 112 | G33: 6 | H33: 7pks | I33: =6*F33 -> 672 | J33: 32 | L33: EXAMS OFFICE | P33: 8pks
A34: SCANTRON | E34: 6 | F34: 32 | G34: 6 | H34: 2pks | I34: =6*F34 -> 192 | J34: 32 | L34: SCANTRON | P34: 2pks
A35: BAMFO KWAKYE | E35: 9 | F35: 64 | G35: 4 | H35: 4pks | I35: =6*F35 -> 384 | J35: 32 | L35: BAMFO KWAKYE | P35: 4pks
A36: PB | E36: 9 | F36: 64 | G36: 2 | H36: 4pks | I36: =6*F36 -> 384 | J36: 32 | L36: PB | P36: 4pks
A37: SECURITY | E37: 23 | F37: 161 | G37: =F37/16 -> 10.0625 | H37: 10pks | I37: =6*F37 -> 966 | J37: 32 | L37: SECURITY | P37: 10pks
A38: NURSES | E38: 2 | F38: 8 | G38: =F38/16 -> 0.5 | H38: 8btls | I38: =6*F38 -> 48 | J38: 32 | L38: NURSES | P38: 12tls
E39: 0
A40: Totals Per Session | C40: =SUM(C5:C39) -> 39 | D40: =SUM(D5:D39) -> 29 | E40: =SUM(E5:E39) -> 165 | F40: =SUM(F5:F39) -> 1125 | G40: =SUM(G5:G38) -> 66.4375
A41: Totals Per Day | F41: ~ 74 packs a day (16 bottles per pack) | H41: ~ 370 Overall packs (16 bottles per pack) | L41: Total Collected for the day
L42: Total to be collected for the day
L43: Overall total left
L44: Total bottles for a Day

Sheet COMBINED_ATTD_INV (2)
A2: ROOM NO | B2: INVIGILATORS | C2: ATTENDANTS | D2: TAs | E2: DATE | F2: SESSION
A3: LT | B3: =VLOOKUP(A3,[10]Schedule_Invigilators!$A$2:$B$27,2,FALSE) -> Prince Yaw Andoh | C3: =VLOOKUP(A3,'[10]COMBINED_ATTD_INV (3)'!$A$351:$E$1175,2,FALSE) -> Mohammed Bakang// | D3: Kwabena Owusu-Osei | E3: Monday, 24 Febuary 2025 | F3: Session, 1 (8:15 AM - 9:15 AM)
A4: RM A | B4: =VLOOKUP(A4,[10]Schedule_Invigilators!$A$2:$B$27,2,FALSE) -> Prosper Akaba | C4: =VLOOKUP(A4,'[10]COMBINED_ATTD_INV (3)'!$A$351:$E$1175,2,FALSE) -> Derrick Owusu Mensah// | D4: Elesie Joseph | E4: Monday, 24 Febuary 2025 | F4: Session, 1 (8:15 AM - 9:15 AM)
A5: RM B | B5: =VLOOKUP(A5,[10]Schedule_Invigilators!$A$2:$B$27,2,FALSE) -> Casper Adenutsi | C5: =VLOOKUP(A5,'[10]COMBINED_ATTD_INV (3)'!$A$351:$E$1175,2,FALSE) -> Mercy Nimako// | D5: John Kwesi Baidoo | E5: Monday, 24 Febuary 2025 | F5: Session, 1 (8:15 AM - 9:15 AM)
A6: VSLA | B6: =VLOOKUP(A6,[10]Schedule_Invigilators!$A$2:$B$27,2,FALSE) -> Kenneth Adomako Tutu / Joshua Ampofo | C6: =VLOOKUP(A6,'[10]COMBINED_ATTD_INV (3)'!$A$351:$E$1175,2,FALSE) -> Issaka Ali Sambo/Paul Dery/ | D6: Agyapong Akosua Adubea | E6: Monday, 24 Febuary 2025 | F6: Session, 1 (8:15 AM - 9:15 AM)
A7: 206 | B7: =VLOOKUP(A7,[10]Schedule_Invigilators!$A$2:$B$27,2,FALSE) -> Emmanuel Appiah-Adjei | C7: =VLOOKUP(A7,'[10]COMBINED_ATTD_INV (3)'!$A$351:$E$1175,2,FALSE) -> Edward Kpetege// | D7: Roland Ashie | E7: Monday, 24 Febuary 2025 | F7: Session, 1 (8:15 AM - 9:15 AM)
A8: 303 | B8: =VLOOKUP(A8,[10]Schedule_Invigilators!$A$2:$B$27,2,FALSE) -> Jonathan Atuquaye Quaye / Eliel Keelson | C8: =VLOOKUP(A8,'[10]COMBINED_ATTD_INV (3)'!$A$351:$E$1175,2,FALSE) -> Benjamin Opoku Atuahene// | D8: Malick Ebiasah | E8: Monday, 24 Febuary 2025 | F8: Session, 1 (8:15 AM - 9:15 AM)
A9: 304 | B9: =VLOOKUP(A9,[10]Schedule_Invigilators!$A$2:$B$27,2,FALSE) -> Bernard Konadu Amoah | C9: =VLOOKUP(A9,'[10]COMBINED_ATTD_INV (3)'!$A$351:$E$1175,2,FALSE) -> Eric Soku// | D9: Ernest Kofi Nduakoh | E9: Monday, 24 Febuary 2025 | F9: Session, 1 (8:15 AM - 9:15 AM)
A10: N1 | B10: =VLOOKUP(A10,[10]Schedule_Invigilators!$A$2:$B$27,2,FALSE) -> James Dzisi Gadze | C10: =VLOOKUP(A10,'[10]COMBINED_ATTD_INV (3)'!$A$351:$E$1175,2,FALSE) -> Marian Bemma// | D10: Ofori Rockson Minkah | E10: Monday, 24 Febuary 2025 | F10: Session, 1 (8:15 AM - 9:15 AM)
A11: N2 | B11: =VLOOKUP(A11,[10]Schedule_Invigilators!$A$2:$B$27,2,FALSE) -> Samuel Boahen | C11: =VLOOKUP(A11,'[10]COMBINED_ATTD_INV (3)'!$A$351:$E$1175,2,FALSE) -> Derrick Amoateng// | D11: Joseph Dela Aziafor | E11: Monday, 24 Febuary 2025 | F11: Session, 1 (8:15 AM - 9:15 AM)
A12: PB001 | B12: =VLOOKUP(A12,[10]Schedule_Invigilators!$A$2:$B$27,2,FALSE) -> Martinson Addo Nartey / Benjamin Afotey | C12: =VLOOKUP(A12,'[10]COMBINED_ATTD_INV (3)'!$A$351:$E$1175,2,FALSE) -> John Ofosu// | D12: BELLO RAPHAEL AMETEFE KOMLA | E12: Monday, 24 Febuary 2025 | F12: Session, 1 (8:15 AM - 9:15 AM)
A13: PB020 | B13: =VLOOKUP(A13,[10]Schedule_Invigilators!$A$2:$B$27,2,FALSE) -> Vincent Kofi Abaka Acquaah / Matthew Coffie Wilson | C13: =VLOOKUP(A13,'[10]COMBINED_ATTD_INV (3)'!$A$351:$E$1175,2,FALSE) -> Owusu Stephen Akuoku/Evans Korletey/ | D13: Wiafe Yaw Karikari | E13: Monday, 24 Febuary 2025 | F13: Session, 1 (8:15 AM - 9:15 AM)
A14: PB014 | B14: =VLOOKUP(A14,[10]Schedule_Invigilators!$A$2:$B$27,2,FALSE) -> Prince Odame / Martin Kesse | C14: =VLOOKUP(A14,'[10]COMBINED_ATTD_INV (3)'!$A$351:$E$1175,2,FALSE) -> Kofi Bentum/Linda Berko/ | D14: Agblemiawo Marvin Selasi | E14: Monday, 24 Febuary 2025 | F14: Session, 1 (8:15 AM - 9:15 AM)
A15: PB201 | B15: =VLOOKUP(A15,[10]Schedule_Invigilators!$A$2:$B$27,2,FALSE) -> Sefakor Dogbe / Y. A. Sokama-Neuyam | C15: =VLOOKUP(A15,'[10]COMBINED_ATTD_INV (3)'!$A$351:$E$1175,2,FALSE) -> Joseph Benneth Kankam// | D15: Michael Bansah | E15: Monday, 24 Febuary 2025 | F15: Session, 1 (8:15 AM - 9:15 AM)
A16: PB214 | B16: =VLOOKUP(A16,[10]Schedule_Invigilators!$A$2:$B$27,2,FALSE) -> Godfred Boahen / Nancy Anataba Kyorku Dzikunu-Bansah | C16: =VLOOKUP(A16,'[10]COMBINED_ATTD_INV (3)'!$A$351:$E$1175,2,FALSE) -> Desmond Adu-Yeboah/Fatawu Yakubu/ | D16: Ibrahim Arhin | E16: Monday, 24 Febuary 2025 | F16: Session, 1 (8:15 AM - 9:15 AM)
A17: PB212 | B17: =VLOOKUP(A17,[10]Schedule_Invigilators!$A$2:$B$27,2,FALSE) -> Samuel Osah | C17: =VLOOKUP(A17,'[10]COMBINED_ATTD_INV (3)'!$A$351:$E$1175,2,FALSE) -> Clement Appiah// | D17: YEBOAH HAPPY OWUSU ANTWI | E17: Monday, 24 Febuary 2025 | F17: Session, 1 (8:15 AM - 9:15 AM)
A18: PB208 | B18: =VLOOKUP(A18,[10]Schedule_Invigilators!$A$2:$B$27,2,FALSE) -> Evans Amponsah / Albert Kwame Kwaw | C18: =VLOOKUP(A18,'[10]COMBINED_ATTD_INV (3)'!$A$351:$E$1175,2,FALSE) -> Godfred Appiah// | D18: Owusu Boakye Gideon | E18: Monday, 24 Febuary 2025 | F18: Session, 1 (8:15 AM - 9:15 AM)
A19: VCR | B19: =VLOOKUP(A19,[10]Schedule_Invigilators!$A$2:$B$27,2,FALSE) -> Blestmond Afrifa Brako | C19: =VLOOKUP(A19,'[10]COMBINED_ATTD_INV (3)'!$A$351:$E$1175,2,FALSE) -> Ruth Adwubi Sarfo// | D19: Elita Mawuse Djokotoe Dzontoh | E19: Monday, 24 Febuary 2025 | F19: Session, 1 (8:15 AM - 9:15 AM)
A20: ECR | B20: =VLOOKUP(A20,[10]Schedule_Invigilators!$A$2:$B$27,2,FALSE) -> Andrew Selasi Agbemenu | C20: =VLOOKUP(A20,'[10]COMBINED_ATTD_INV (3)'!$A$351:$E$1175,2,FALSE) -> Sandra Essel// | D20: Berniana John Akwetey | E20: Monday, 24 Febuary 2025 | F20: Session, 1 (8:15 AM - 9:15 AM)
A21: A110 | B21: =VLOOKUP(A21,[10]Schedule_Invigilators!$A$2:$B$27,2,FALSE) -> William Amponsah / Daniel Oduro Boatey Nuamah | C21: =VLOOKUP(A21,'[10]COMBINED_ATTD_INV (3)'!$A$351:$E$1175,2,FALSE) -> Gifty Edem Senyaglo// | D21: Victor Yamoah | E21: Monday, 24 Febuary 2025 | F21: Session, 1 (8:15 AM - 9:15 AM)
... A26: NEB FF1 | B26: =VLOOKUP(A26,[10]Schedule_Invigilators!$A$2:$B$27,2,FALSE) -> Kingsford Sarkodie Obeng Kwakye / Daniel Akwei Addo / David Oppong | C26: =VLOOKUP(A26,'[10]COMBINED_ATTD_INV (3)'!$A$351:$E$1175,2,FALSE) -> Kingsley Kyei Baffour/Bright Andoh-Baidoo/ | D26: Christopher Selasi Dzidolawo | E26: Monday, 24 Febuary 2025 | F26: Session, 1 (8:15 AM - 9:15 AM)
A27: NEB FF2 | B27: =VLOOKUP(A27,[10]Schedule_Invigilators!$A$2:$B$27,2,FALSE) -> Kwame Agyemang Prempeh Agyekum / Eugene Appiah-Effah | C27: =VLOOKUP(A27,'[10]COMBINED_ATTD_INV (3)'!$A$351:$E$1175,2,FALSE) -> Ernest Dapaah// | D27: Prince Kwabena Appiah Boadu | E27: Monday, 24 Febuary 2025
A29: ROOM NO | B29: INVIGILATORS | C29: ATTENDANTS | D29: TAs | E29: DATE | F29: SESSION
A30: LT | B30: =VLOOKUP(A30,[10]Schedule_Invigilators!$A$29:$B$803,2,FALSE) -> Albert Amatey Adjaottor | C30: =VLOOKUP(A30,'[10]COMBINED_ATTD_INV (3)'!$A$379:$E$403,2,FALSE) -> Reuben Asare Bediako// | D30: Mubarak Abdulai Alhassan | E30: Monday, 24 Febuary 2025 | F30: Session, 2 (10:00 AM - 11:00 AM)
A31: RM A | B31: =VLOOKUP(A31,[10]Schedule_Invigilators!$A$29:$B$803,2,FALSE) -> Andrew Cudzo Amenuvor | C31: =VLOOKUP(A31,'[10]COMBINED_ATTD_INV (3)'!$A$379:$E$403,2,FALSE) -> George Ansong// | D31: Kuyini Anisuma Salma | E31: Monday, 24 Febuary 2025 | F31: Session, 2 (10:00 AM - 11:00 AM)
A32: RM B | B32: =VLOOKUP(A32,[10]Schedule_Invigilators!$A$29:$B$803,2,FALSE) -> Evans Amponsah | C32: =VLOOKUP(A32,'[10]COMBINED_ATTD_INV (3)'!$A$379:$E$403,2,FALSE) -> Derrick Owusu Mensah// | D32: Prince Frimpong | E32: Monday, 24 Febuary 2025 | F32: Session, 2 (10:00 AM - 11:00 AM)
A33: VSLA | B33: =VLOOKUP(A33,[10]Schedule_Invigilators!$A$29:$B$803,2,FALSE) -> Charles Adrah / Emmanuel Ampoma Affum | C33: =VLOOKUP(A33,'[10]COMBINED_ATTD_INV (3)'!$A$379:$E$403,2,FALSE) -> Sandra Essel/Paul Dery/ | D33: Obeng Benjamin/Uriel Oppong Buamah | E33: Monday, 24 Febuary 2025 | F33: Session, 2 (10:00 AM - 11:00 AM)
A34: 206 | B34: =VLOOKUP(A34,[10]Schedule_Invigilators!$A$29:$B$803,2,FALSE) -> Augustus Ababio Donkor | C34: =VLOOKUP(A34,'[10]COMBINED_ATTD_INV (3)'!$A$379:$E$403,2,FALSE) -> Edward Kpetege// | D34: Prosper Abewini Atuase | E34: Monday, 24 Febuary 2025 | F34: Session, 2 (10:00 AM - 11:00 AM)
A35: 303 | B35: =VLOOKUP(A35,[10]Schedule_Invigilators!$A$29:$B$803,2,FALSE) -> Nicholas Prah / Kwame Sarkodie | C35: =VLOOKUP(A35,'[10]COMBINED_ATTD_INV (3)'!$A$379:$E$403,2,FALSE) -> Benjamin Opoku Atuahene// | D35: Ebenezer Ekuful | E35: Monday, 24 Febuary 2025 | F35: Session, 2 (10:00 AM - 11:00 AM)
A36: 304 | B36: =VLOOKUP(A36,[10]Schedule_Invigilators!$A$29:$B$803,2,FALSE) -> Asiedu Nana Yaw | C36: =VLOOKUP(A36,'[10]COMBINED_ATTD_INV (3)'!$A$379:$E$403,2,FALSE) -> Eric Soku// | D36: Isaac Danso | E36: Monday, 24 Febuary 2025 | F36: Session, 2 (10:00 AM - 11:00 AM)
A37: N1 | B37: =VLOOKUP(A37,[10]Schedule_Invigilators!$A$29:$B$803,2,FALSE) -> Theresa-Samuelle Maame Atwemaa Adjaidoo | C37: =VLOOKUP(A37,'[10]COMBINED_ATTD_INV (3)'!$A$379:$E$403,2,FALSE) -> Abigail Akos Worlanyo// | D37: Mate-Kole Nyako Gortlieb | E37: Monday, 24 Febuary 2025 | F37: Session, 2 (10:00 AM - 11:00 AM)
A38: PB001 | B38: =VLOOKUP(A38,[10]Schedule_Invigilators!$A$29:$B$803,2,FALSE) -> Benjamin Afotey / Jack Osei Banahene | C38: =VLOOKUP(A38,'[10]COMBINED_ATTD_INV (3)'!$A$379:$E$403,2,FALSE) -> John Ofosu// | D38: Evans Tetteh Owusu | E38: Monday, 24 Febuary 2025 | F38: Session, 2 (10:00 AM - 11:00 AM)
A39: PB020 | B39: =VLOOKUP(A39,[10]Schedule_Invigilators!$A$29:$B$803,2,FALSE) -> Samuel Erzuah / Yesuenyeagbe Fiagbe | C39: =VLOOKUP(A39,'[10]COMBINED_ATTD_INV (3)'!$A$379:$E$403,2,FALSE) -> Owusu Stephen Akuoku/Michael Owusu/ | D39: Gyano Charty Joseph | E39: Monday, 24 Febuary 2025 | F39: Session, 2 (10:00 AM - 11:00 AM)
A40: PB014 | B40: =VLOOKUP(A40,[10]Schedule_Invigilators!$A$29:$B$803,2,FALSE) -> Peter Oppong Tawiah/ Samuel Kwofie | C40: =VLOOKUP(A40,'[10]COMBINED_ATTD_INV (3)'!$A$379:$E$403,2,FALSE) -> Rener Oppong/Fiifi Turkson/ | D40: Williams Ananzoyaa Akandi | E40: Monday, 24 Febuary 2025 | F40: Session, 2 (10:00 AM - 11:00 AM)
A41: PB008 | B41: =VLOOKUP(A41,[10]Schedule_Invigilators!$A$29:$B$803,2,FALSE) -> Ayuba Bene Adam / Emmanuel Offei Akrofi | C41: =VLOOKUP(A41,'[10]COMBINED_ATTD_INV (3)'!$A$379:$E$403,2,FALSE) -> Rebecca Yamoah// | D41: Quaynor Nii Charway Gideon | E41: Monday, 24 Febuary 2025 | F41: Session, 2 (10:00 AM - 11:00 AM)
A42: PB201 | B42: =VLOOKUP(A42,[10]Schedule_Invigilators!$A$29:$B$803,2,FALSE) -> Cosmas Yaw Asante / Bukari Ali | C42: =VLOOKUP(A42,'[10]COMBINED_ATTD_INV (3)'!$A$379:$E$403,2,FALSE) -> Joseph Benneth Kankam// | D42: DOMPREH DERRICK EYRAM | E42: Monday, 24 Febuary 2025 | F42: Session, 2 (10:00 AM - 11:00 AM)
A43: PB214 | B43: =VLOOKUP(A43,[10]Schedule_Invigilators!$A$29:$B$803,2,FALSE) -> Felix Jojo Fianko Ayeh / Martina Francisca Baidoo | C43: =VLOOKUP(A43,'[10]COMBINED_ATTD_INV (3)'!$A$379:$E$403,2,FALSE) -> Evans Korletey/Fatawu Yakubu/ | D43: Elvis Appiah | E43: Monday, 24 Febuary 2025 | F43: Session, 2 (10:00 AM - 11:00 AM)
A44: PB212 | B44: =VLOOKUP(A44,[10]Schedule_Invigilators!$A$29:$B$803,2,FALSE) -> S. H. M. Aikins | C44: =VLOOKUP(A44,'[10]COMBINED_ATTD_INV (3)'!$A$379:$E$403,2,FALSE) -> Clement Appiah// | D44: Benjamin Dagbey | E44: Monday, 24 Febuary 2025 | F44: Session, 2 (10:00 AM - 11:00 AM)
A45: PB208 | B45: =VLOOKUP(A45,[10]Schedule_Invigilators!$A$29:$B$803,2,FALSE) -> Forkuo Eric Kwabena / Bennetta Koomson | C45: =VLOOKUP(A45,'[10]COMBINED_ATTD_INV (3)'!$A$379:$E$403,2,FALSE) -> Theresa Sarpong Peprah// | D45: Anita Dokuwah Nyarko | E45: Monday, 24 Febuary 2025 | F45: Session, 2 (10:00 AM - 11:00 AM)
A46: VCR | B46: =VLOOKUP(A46,[10]Schedule_Invigilators!$A$29:$B$803,2,FALSE) -> Gordon Foli | C46: =VLOOKUP(A46,'[10]COMBINED_ATTD_INV (3)'!$A$379:$E$403,2,FALSE) -> Ruth Adwubi Sarfo// | D46: Osei Amaniampong Henry Manasseh | E46: Monday, 24 Febuary 2025 | F46: Session, 2 (10:00 AM - 11:00 AM)
A47: ECR | B47: =VLOOKUP(A47,[10]Schedule_Invigilators!$A$29:$B$803,2,FALSE) -> Andrew Selasi Agbemenu | C47: =VLOOKUP(A47,'[10]COMBINED_ATTD_INV (3)'!$A$379:$E$403,2,FALSE) -> Clement Dadzie// | D47: Elvis Donkor | E47: Monday, 24 Febuary 2025 | F47: Session, 2 (10:00 AM - 11:00 AM)
A48: A110 | B48: =VLOOKUP(A48,[10]Schedule_Invigilators!$A$29:$B$803,2,FALSE) -> William Amponsah / Francisca Adoma Acheampong | C48: =VLOOKUP(A48,'[10]COMBINED_ATTD_INV (3)'!$A$379:$E$403,2,FALSE) -> Kwame Kwarteng Sarpong// | D48: Abagre Majeed Winimi | E48: Monday, 24 Febuary 2025 | F48: Session, 2 (10:00 AM - 11:00 AM)
... A53: NEB FF1 | B53: =VLOOKUP(A53,[10]Schedule_Invigilators!$A$29:$B$803,2,FALSE) -> Kingsford Sarkodie Obeng Kwakye / Emmanuel Kwesi Arthur / Godfrey Chiri Amedjoe | C53: =VLOOKUP(A53,'[10]COMBINED_ATTD_INV (3)'!$A$379:$E$403,2,FALSE) -> Kingsley Kyei Baffour/Bright Andoh-Baidoo/ | D53: Cofie Benjamin Edinam | E53: Monday, 24 Febuary 2025 | F53: Session, 2 (10:00 AM - 11:00 AM)
A54: NEB FF2 | B54: =VLOOKUP(A54,[10]Schedule_Invigilators!$A$29:$B$803,2,FALSE) -> Francis Boafo Effah / Yaw Adubofour Tuffour | C54: =VLOOKUP(A54,'[10]COMBINED_ATTD_INV (3)'!$A$379:$E$403,2,FALSE) -> Ernest Dapaah// | D54: Agbe Setordzi Gameli | E54: Monday, 24 Febuary 2025
A56: ROOM NO | B56: INVIGILATORS | C56: ATTENDANTS | D56: TAs | E56: DATE | F56: SESSION
A57: LT | B57: =VLOOKUP(A57,[10]Schedule_Invigilators!$A$55:$B$803,2,FALSE) -> Martinson Addo Nartey | C57: =VLOOKUP(A57,'[10]COMBINED_ATTD_INV (3)'!$A$406:$E$431,2,FALSE) -> Theresa Sarpong Peprah// | D57: Philip Kojo Ansah | E57: Monday, 24 Febuary 2025 | F57: Session, 3 (11:45 AM - 12:45 PM)
A58: RM A | B58: =VLOOKUP(A58,[10]Schedule_Invigilators!$A$55:$B$803,2,FALSE) -> Ayuba Bene Adam | C58: =VLOOKUP(A58,'[10]COMBINED_ATTD_INV (3)'!$A$406:$E$431,2,FALSE) -> George Ansong// | D58: Samuel Asiedu | E58: Monday, 24 Febuary 2025 | F58: Session, 3 (11:45 AM - 12:45 PM)
A59: RM B | B59: =VLOOKUP(A59,[10]Schedule_Invigilators!$A$55:$B$803,2,FALSE) -> Faisal Wahib Adam | C59: =VLOOKUP(A59,'[10]COMBINED_ATTD_INV (3)'!$A$406:$E$431,2,FALSE) -> Derrick Owusu Mensah// | D59: OWIREDU-GHORMAN Ewurama Owireduwaa | E59: Monday, 24 Febuary 2025 | F59: Session, 3 (11:45 AM - 12:45 PM)
A60: VSLA | B60: =VLOOKUP(A60,[10]Schedule_Invigilators!$A$55:$B$803,2,FALSE) -> Theresa-Samuelle Maame Atwemaa Adjaidoo / Prince Ebenezer Adjei | C60: =VLOOKUP(A60,'[10]COMBINED_ATTD_INV (3)'!$A$406:$E$431,2,FALSE) -> Victoria Agyenim-Boateng/Michael Owusu/ | D60: Kwame Moses | E60: Monday, 24 Febuary 2025 | F60: Session, 3 (11:45 AM - 12:45 PM)
A61: 206 | B61: =VLOOKUP(A61,[10]Schedule_Invigilators!$A$55:$B$803,2,FALSE) -> Sefakor Dogbe | C61: =VLOOKUP(A61,'[10]COMBINED_ATTD_INV (3)'!$A$406:$E$431,2,FALSE) -> Edward Kpetege// | D61: Kobina Akofi-Holison | E61: Monday, 24 Febuary 2025 | F61: Session, 3 (11:45 AM - 12:45 PM)
A62: 303 | B62: =VLOOKUP(A62,[10]Schedule_Invigilators!$A$55:$B$803,2,FALSE) -> Jack Osei Banahene / Jude Bonsu | C62: =VLOOKUP(A62,'[10]COMBINED_ATTD_INV (3)'!$A$406:$E$431,2,FALSE) -> Linda Berko// | D62: Agyapong Dorcas Nuaniah | E62: Monday, 24 Febuary 2025 | F62: Session, 3 (11:45 AM - 12:45 PM)
A63: 304 | B63: =VLOOKUP(A63,[10]Schedule_Invigilators!$A$55:$B$803,2,FALSE) -> Kofi Owura Amoabeng | C63: =VLOOKUP(A63,'[10]COMBINED_ATTD_INV (3)'!$A$406:$E$431,2,FALSE) -> Eric Soku// | D63: Issah Abdul Ganiwu Gene | E63: Monday, 24 Febuary 2025 | F63: Session, 3 (11:45 AM - 12:45 PM)
A64: N1 | B64: =VLOOKUP(A64,[10]Schedule_Invigilators!$A$55:$B$803,2,FALSE) -> Eric Amoah Asante | C64: =VLOOKUP(A64,'[10]COMBINED_ATTD_INV (3)'!$A$406:$E$431,2,FALSE) -> Salamatu Salifu// | D64: Evelyn Seyram Kakah | E64: Monday, 24 Febuary 2025 | F64: Session, 3 (11:45 AM - 12:45 PM)
A65: N2 | B65: =VLOOKUP(A65,[10]Schedule_Invigilators!$A$55:$B$803,2,FALSE) -> Samuel Osah | C65: =VLOOKUP(A65,'[10]COMBINED_ATTD_INV (3)'!$A$406:$E$431,2,FALSE) -> Derrick Amoateng// | D65: Frank Oduro | E65: Monday, 24 Febuary 2025 | F65: Session, 3 (11:45 AM - 12:45 PM)
A66: PB001 | B66: =VLOOKUP(A66,[10]Schedule_Invigilators!$A$55:$B$803,2,FALSE) -> Isaac Dadzie / John Wise Divine Ayer | C66: =VLOOKUP(A66,'[10]COMBINED_ATTD_INV (3)'!$A$406:$E$431,2,FALSE) -> John Ofosu// | D66: Issifu Fredrick Ali | E66: Monday, 24 Febuary 2025 | F66: Session, 3 (11:45 AM - 12:45 PM)
A67: PB020 | B67: =VLOOKUP(A67,[10]Schedule_Invigilators!$A$55:$B$803,2,FALSE) -> Benjamin Afotey / Francis Kofi Forson | C67: =VLOOKUP(A67,'[10]COMBINED_ATTD_INV (3)'!$A$406:$E$431,2,FALSE) -> Rener Oppong/Samuel Osei-Asibey Bonsu/ | D67: John Yaw Gyasi-Mensah | E67: Monday, 24 Febuary 2025 | F67: Session, 3 (11:45 AM - 12:45 PM)
A68: PB014 | B68: =VLOOKUP(A68,[10]Schedule_Invigilators!$A$55:$B$803,2,FALSE) -> M. Appiah Brempong / Anthony Arko-Adjei | C68: =VLOOKUP(A68,'[10]COMBINED_ATTD_INV (3)'!$A$406:$E$431,2,FALSE) -> Kofi Bentum/Gifty Edem Senyaglo/ | D68: Shallom Ezekiel | E68: Monday, 24 Febuary 2025 | F68: Session, 3 (11:45 AM - 12:45 PM)
A69: PB008 | B69: =VLOOKUP(A69,[10]Schedule_Invigilators!$A$55:$B$803,2,FALSE) -> Nancy Anataba Kyorku Dzikunu-Bansah / Samuel Boahen | C69: =VLOOKUP(A69,'[10]COMBINED_ATTD_INV (3)'!$A$406:$E$431,2,FALSE) -> Rebecca Yamoah// | D69: ADDO THOMAS | E69: Monday, 24 Febuary 2025 | F69: Session, 3 (11:45 AM - 12:45 PM)
A70: PB201 | B70: =VLOOKUP(A70,[10]Schedule_Invigilators!$A$55:$B$803,2,FALSE) -> Eric Kwame Anokye Asare / Daniel Oduro Boatey Nuamah | C70: =VLOOKUP(A70,'[10]COMBINED_ATTD_INV (3)'!$A$406:$E$431,2,FALSE) -> Joseph Benneth Kankam// | D70: Clement Heanampong | E70: Monday, 24 Febuary 2025 | F70: Session, 3 (11:45 AM - 12:45 PM)
A71: PB214 | B71: =VLOOKUP(A71,[10]Schedule_Invigilators!$A$55:$B$803,2,FALSE) -> Albert Kwame Kwaw / Daniel Akwei Addo | C71: =VLOOKUP(A71,'[10]COMBINED_ATTD_INV (3)'!$A$406:$E$431,2,FALSE) -> Bernard Audinada Ampofo/Fatawu Yakubu/ | D71: Prince Dawson Tetteh | E71: Monday, 24 Febuary 2025 | F71: Session, 3 (11:45 AM - 12:45 PM)
A72: PB212 | B72: =VLOOKUP(A72,[10]Schedule_Invigilators!$A$55:$B$803,2,FALSE) -> Jones Owusu Twumasi | C72: =VLOOKUP(A72,'[10]COMBINED_ATTD_INV (3)'!$A$406:$E$431,2,FALSE) -> Clement Appiah// | D72: Emmanuel Yuorkuu | E72: Monday, 24 Febuary 2025 | F72: Session, 3 (11:45 AM - 12:45 PM)
A73: PB208 | B73: =VLOOKUP(A73,[10]Schedule_Invigilators!$A$55:$B$803,2,FALSE) -> Stephen Adjei / Godfred Boahen | C73: =VLOOKUP(A73,'[10]COMBINED_ATTD_INV (3)'!$A$406:$E$431,2,FALSE) -> Godfred Appiah// | D73: Mildred Martetsoo Martey | E73: Monday, 24 Febuary 2025 | F73: Session, 3 (11:45 AM - 12:45 PM)
A74: VCR | B74: =VLOOKUP(A74,[10]Schedule_Invigilators!$A$55:$B$803,2,FALSE) -> Godfrey Chiri Amedjoe | C74: =VLOOKUP(A74,'[10]COMBINED_ATTD_INV (3)'!$A$406:$E$431,2,FALSE) -> Abigail Akos Worlanyo// | D74: Juliet Arthur | E74: Monday, 24 Febuary 2025 | F74: Session, 3 (11:45 AM - 12:45 PM)
A75: ECR | B75: =VLOOKUP(A75,[10]Schedule_Invigilators!$A$55:$B$803,2,FALSE) -> Andrew Selasi Agbemenu | C75: =VLOOKUP(A75,'[10]COMBINED_ATTD_INV (3)'!$A$406:$E$431,2,FALSE) -> Sandra Essel// | D75: Agyemang Duku Rismond | E75: Monday, 24 Febuary 2025 | F75: Session, 3 (11:45 AM - 12:45 PM)
... A82: NEB FF2 | B82: =VLOOKUP(A82,[10]Schedule_Invigilators!$A$55:$B$803,2,FALSE) -> Henry Nunoo-Mensah / Andrew Cudzo Amenuvor | C82: =VLOOKUP(A82,'[10]COMBINED_ATTD_INV (3)'!$A$406:$E$431,2,FALSE) -> Ernest Dapaah// | D82: Bless Elikem Krapah | E82: Monday, 24 Febuary 2025 | F82: Session, 3 (11:45 AM - 12:45 PM)
A84: ROOM NO | B84: INVIGILATORS | C84: ATTENDANTS | D84: TAs | E84: DATE | F84: SESSION
A85: LT | B85: =VLOOKUP(A85,[10]Schedule_Invigilators!$A$82:$B$803,2,FALSE) -> Kwame Agyemang Prempeh Agyekum | C85: =VLOOKUP(A85,'[10]COMBINED_ATTD_INV (3)'!$A$434:$E$458,2,FALSE) -> Reuben Asare Bediako// | D85: Bright Mensah | E85: Monday, 24 Febuary 2025 | F85: Session, 4 (1:30 PM - 2:30 PM)
A86: RM A | B86: =VLOOKUP(A86,[10]Schedule_Invigilators!$A$82:$B$803,2,FALSE) -> Anthony Arko-Adjei | C86: =VLOOKUP(A86,'[10]COMBINED_ATTD_INV (3)'!$A$434:$E$458,2,FALSE) -> George Ansong// | D86: Maruf Usman | E86: Monday, 24 Febuary 2025 | F86: Session, 4 (1:30 PM - 2:30 PM)
A87: RM B | B87: =VLOOKUP(A87,[10]Schedule_Invigilators!$A$82:$B$803,2,FALSE) -> Bennetta Koomson | C87: =VLOOKUP(A87,'[10]COMBINED_ATTD_INV (3)'!$A$434:$E$458,2,FALSE) -> Victoria Agyenim-Boateng// | D87: Phiona Nana Akua Amakah | E87: Monday, 24 Febuary 2025 | F87: Session, 4 (1:30 PM - 2:30 PM)
A88: VSLA | B88: =VLOOKUP(A88,[10]Schedule_Invigilators!$A$82:$B$803,2,FALSE) -> Prince Odame / Emmanuel Ampoma Affum | C88: =VLOOKUP(A88,'[10]COMBINED_ATTD_INV (3)'!$A$434:$E$458,2,FALSE) -> Issaka Ali Sambo/Paul Dery/ | D88: Wanaa Kingsley | E88: Monday, 24 Febuary 2025 | F88: Session, 4 (1:30 PM - 2:30 PM)
A89: 206 | B89: =VLOOKUP(A89,[10]Schedule_Invigilators!$A$82:$B$803,2,FALSE) -> Akwasi Afrifa Acheampong | C89: =VLOOKUP(A89,'[10]COMBINED_ATTD_INV (3)'!$A$434:$E$458,2,FALSE) -> Peter Agetinga// | D89: Joseph Derrick Anane Nti Koduah | E89: Monday, 24 Febuary 2025 | F89: Session, 4 (1:30 PM - 2:30 PM)
A90: 303 | B90: =VLOOKUP(A90,[10]Schedule_Invigilators!$A$82:$B$803,2,FALSE) -> Martin Kesse / Prince Ebenezer Adjei | C90: =VLOOKUP(A90,'[10]COMBINED_ATTD_INV (3)'!$A$434:$E$458,2,FALSE) -> Benjamin Opoku Atuahene// | D90: Gyamfi Morris Akwasi | E90: Monday, 24 Febuary 2025 | F90: Session, 4 (1:30 PM - 2:30 PM)
A91: 304 | B91: =VLOOKUP(A91,[10]Schedule_Invigilators!$A$82:$B$803,2,FALSE) -> James Okae | C91: =VLOOKUP(A91,'[10]COMBINED_ATTD_INV (3)'!$A$434:$E$458,2,FALSE) -> Eric Soku// | D91: Abdul-Basit Nuhu | E91: Monday, 24 Febuary 2025 | F91: Session, 4 (1:30 PM - 2:30 PM)
A92: N1 | B92: =VLOOKUP(A92,[10]Schedule_Invigilators!$A$82:$B$803,2,FALSE) -> Geophrey Kwame Anornu | C92: =VLOOKUP(A92,'[10]COMBINED_ATTD_INV (3)'!$A$434:$E$458,2,FALSE) -> Marian Bemma// | D92: Mercy Boakye | E92: Monday, 24 Febuary 2025 | F92: Session, 4 (1:30 PM - 2:30 PM)
A93: N2 | B93: =VLOOKUP(A93,[10]Schedule_Invigilators!$A$82:$B$803,2,FALSE) -> Blestmond Afrifa Brako | C93: =VLOOKUP(A93,'[10]COMBINED_ATTD_INV (3)'!$A$434:$E$458,2,FALSE) -> Derrick Amoateng// | D93: Bentum Yaw Richmond | E93: Monday, 24 Febuary 2025 | F93: Session, 4 (1:30 PM - 2:30 PM)
A94: PB001 | B94: =VLOOKUP(A94,[10]Schedule_Invigilators!$A$82:$B$803,2,FALSE) -> Samuel Erzuah /Francis Kofi Forson | C94: =VLOOKUP(A94,'[10]COMBINED_ATTD_INV (3)'!$A$434:$E$458,2,FALSE) -> John Ofosu// | D94: Silas Osei-Poku | E94: Monday, 24 Febuary 2025 | F94: Session, 4 (1:30 PM - 2:30 PM)
A95: PB020 | B95: =VLOOKUP(A95,[10]Schedule_Invigilators!$A$82:$B$803,2,FALSE) -> Efiba Vidda Senkyire Kwarteng / Ebenezer Mensah | C95: =VLOOKUP(A95,'[10]COMBINED_ATTD_INV (3)'!$A$434:$E$458,2,FALSE) -> Gifty Edem Senyaglo/Mohammed Bakang/ | D95: Abigail Anku | E95: Monday, 24 Febuary 2025 | F95: Session, 4 (1:30 PM - 2:30 PM)
A96: PB014 | B96: =VLOOKUP(A96,[10]Schedule_Invigilators!$A$82:$B$803,2,FALSE) -> Felix Jojo Fianko Ayeh / Prosper Akaba | C96: =VLOOKUP(A96,'[10]COMBINED_ATTD_INV (3)'!$A$434:$E$458,2,FALSE) -> Michael Owusu/Fiifi Turkson/ | D96: Frank Owusu Boakye | E96: Monday, 24 Febuary 2025 | F96: Session, 4 (1:30 PM - 2:30 PM)
A97: PB008 | B97: =VLOOKUP(A97,[10]Schedule_Invigilators!$A$82:$B$803,2,FALSE) -> Nicholas Prah / James Dzisi Gadze | C97: =VLOOKUP(A97,'[10]COMBINED_ATTD_INV (3)'!$A$434:$E$458,2,FALSE) -> Salamatu Salifu// | D97: Taylor Ebo Benjamin | E97: Monday, 24 Febuary 2025 | F97: Session, 4 (1:30 PM - 2:30 PM)
A98: PB201 | B98: =VLOOKUP(A98,[10]Schedule_Invigilators!$A$82:$B$803,2,FALSE) -> K. O.-B Obour Agyekum / Martina Francisca Baidoo | C98: =VLOOKUP(A98,'[10]COMBINED_ATTD_INV (3)'!$A$434:$E$458,2,FALSE) -> Joseph Benneth Kankam// | D98: Nathaniel Foli | E98: Monday, 24 Febuary 2025 | F98: Session, 4 (1:30 PM - 2:30 PM)
A99: PB214 | B99: =VLOOKUP(A99,[10]Schedule_Invigilators!$A$82:$B$803,2,FALSE) -> M. Appiah Brempong / Alfred Alan Duker | C99: =VLOOKUP(A99,'[10]COMBINED_ATTD_INV (3)'!$A$434:$E$458,2,FALSE) -> Desmond Adu-Yeboah/Benjamin Nana Oduro Konadu/ | D99: Teyi Edem Justice | E99: Monday, 24 Febuary 2025 | F99: Session, 4 (1:30 PM - 2:30 PM)
A100: PB212 | B100: =VLOOKUP(A100,[10]Schedule_Invigilators!$A$82:$B$803,2,FALSE) -> Cosmas Yaw Asante | C100: =VLOOKUP(A100,'[10]COMBINED_ATTD_INV (3)'!$A$434:$E$458,2,FALSE) -> Getrude Opoku// | D100: Bezaleel Nana Akrasi Gyedu-Ware | E100: Monday, 24 Febuary 2025 | F100: Session, 4 (1:30 PM - 2:30 PM)
A101: PB208 | B101: =VLOOKUP(A101,[10]Schedule_Invigilators!$A$82:$B$803,2,FALSE) -> Daniel Akwei Addo / Albert Kwame Kwaw | C101: =VLOOKUP(A101,'[10]COMBINED_ATTD_INV (3)'!$A$434:$E$458,2,FALSE) -> #N/A | D101: Amedume Gideon | E101: Monday, 24 Febuary 2025 | F101: Session, 4 (1:30 PM - 2:30 PM)
A102: VCR | B102: =VLOOKUP(A102,[10]Schedule_Invigilators!$A$82:$B$803,2,FALSE) -> Gordon Foli | C102: =VLOOKUP(A102,'[10]COMBINED_ATTD_INV (3)'!$A$434:$E$458,2,FALSE) -> Ruth Adwubi Sarfo// | D102: Mawuli Dogbatse | E102: Monday, 24 Febuary 2025 | F102: Session, 4 (1:30 PM - 2:30 PM)
A103: ECR | B103: =VLOOKUP(A103,[10]Schedule_Invigilators!$A$82:$B$803,2,FALSE) -> Andrew Selasi Agbemenu | C103: =VLOOKUP(A103,'[10]COMBINED_ATTD_INV (3)'!$A$434:$E$458,2,FALSE) -> Sandra Essel// | D103: Christian Agyekum | E103: Monday, 24 Febuary 2025 | F103: Session, 4 (1:30 PM - 2:30 PM)
... A110: NEB FF2 | B110: =VLOOKUP(A110,[10]Schedule_Invigilators!$A$82:$B$803,2,FALSE) -> C. K. K. Sekyere / Augustus Ababio Donkor | C110: =VLOOKUP(A110,'[10]COMBINED_ATTD_INV (3)'!$A$434:$E$458,2,FALSE) -> Ernest Dapaah// | D110: Poku Atta Andy | E110: Monday, 24 Febuary 2025 | F110: Session, 4 (1:30 PM - 2:30 PM)
A112: ROOM NO | B112: INVIGILATORS | C112: ATTENDANTS | D112: TAs | E112: DATE | F112: SESSION
A113: LT | B113: =VLOOKUP(A113,[10]Schedule_Invigilators!$A$108:$B$803,2,FALSE) -> Y. A. Sokama-Neuyam | C113: =VLOOKUP(A113,'[10]COMBINED_ATTD_INV (3)'!$A$461:$E$485,2,FALSE) -> Reuben Asare Bediako// | D113: Mubarak Abdulai Alhassan | E113: Monday, 24 Febuary 2025 | F113: Session, 5 (3:15 PM - 4:15 PM)
A114: RM A | B114: =VLOOKUP(A114,[10]Schedule_Invigilators!$A$108:$B$803,2,FALSE) -> Jonathan Arthur Quaye-Ballard | C114: =VLOOKUP(A114,'[10]COMBINED_ATTD_INV (3)'!$A$461:$E$485,2,FALSE) -> Desmond Adu-Yeboah// | D114: Kuyini Anisuma Salma | E114: Monday, 24 Febuary 2025 | F114: Session, 5 (3:15 PM - 4:15 PM)
A115: RM B | B115: =VLOOKUP(A115,[10]Schedule_Invigilators!$A$108:$B$803,2,FALSE) -> David Oppong | C115: =VLOOKUP(A115,'[10]COMBINED_ATTD_INV (3)'!$A$461:$E$485,2,FALSE) -> Derrick Owusu Mensah// | D115: Prince Frimpong | E115: Monday, 24 Febuary 2025 | F115: Session, 5 (3:15 PM - 4:15 PM)
A116: VSLA | B116: =VLOOKUP(A116,[10]Schedule_Invigilators!$A$108:$B$803,2,FALSE) -> Samuel Kwofie / Faisal Wahib Adam | C116: =VLOOKUP(A116,'[10]COMBINED_ATTD_INV (3)'!$A$461:$E$485,2,FALSE) -> Issaka Ali Sambo/Paul Dery/ | D116: Obeng Benjamin | E116: Monday, 24 Febuary 2025 | F116: Session, 5 (3:15 PM - 4:15 PM)
A117: 206 | B117: =VLOOKUP(A117,[10]Schedule_Invigilators!$A$108:$B$803,2,FALSE) -> Emmanuel Appiah-Adjei | C117: =VLOOKUP(A117,'[10]COMBINED_ATTD_INV (3)'!$A$461:$E$485,2,FALSE) -> Edward Kpetege// | D117: Prosper Abewini Atuase | E117: Monday, 24 Febuary 2025 | F117: Session, 5 (3:15 PM - 4:15 PM)
A118: 303 | B118: =VLOOKUP(A118,[10]Schedule_Invigilators!$A$108:$B$803,2,FALSE) -> Prince Yaw Andoh / Stephen Adjei | C118: =VLOOKUP(A118,'[10]COMBINED_ATTD_INV (3)'!$A$461:$E$485,2,FALSE) -> Benjamin Opoku Atuahene// | D118: Ebenezer Ekuful | E118: Monday, 24 Febuary 2025 | F118: Session, 5 (3:15 PM - 4:15 PM)
A119: N1 | B119: =VLOOKUP(A119,[10]Schedule_Invigilators!$A$108:$B$803,2,FALSE) -> Godfred Boahen | C119: =VLOOKUP(A119,'[10]COMBINED_ATTD_INV (3)'!$A$461:$E$485,2,FALSE) -> Marian Bemma// | D119: Mate-Kole Nyako Gortlieb | E119: Monday, 24 Febuary 2025 | F119: Session, 5 (3:15 PM - 4:15 PM)
A120: N2 | B120: =VLOOKUP(A120,[10]Schedule_Invigilators!$A$108:$B$803,2,FALSE) -> Kofi Owura Amoabeng | C120: =VLOOKUP(A120,'[10]COMBINED_ATTD_INV (3)'!$A$461:$E$485,2,FALSE) -> Derrick Amoateng// | D120: Doreen Cudjoe | E120: Monday, 24 Febuary 2025 | F120: Session, 5 (3:15 PM - 4:15 PM)
A121: PB001 | B121: =VLOOKUP(A121,[10]Schedule_Invigilators!$A$108:$B$803,2,FALSE) -> Bukari Ali / Albert Amatey Adjaottor | C121: =VLOOKUP(A121,'[10]COMBINED_ATTD_INV (3)'!$A$461:$E$485,2,FALSE) -> John Ofosu// | D121: Evans Tetteh Owusu | E121: Monday, 24 Febuary 2025 | F121: Session, 5 (3:15 PM - 4:15 PM)
A122: PB020 | B122: =VLOOKUP(A122,[10]Schedule_Invigilators!$A$108:$B$803,2,FALSE) -> Evans Amponsah / Gabriel Takyi | C122: =VLOOKUP(A122,'[10]COMBINED_ATTD_INV (3)'!$A$461:$E$485,2,FALSE) -> Owusu Stephen Akuoku/Samuel Osei-Asibey Bonsu/ | D122: Gyano Charty Joseph | E122: Monday, 24 Febuary 2025 | F122: Session, 5 (3:15 PM - 4:15 PM)
A123: PB014 | B123: =VLOOKUP(A123,[10]Schedule_Invigilators!$A$108:$B$803,2,FALSE) -> Benjamin Afotey / John Wise Divine Ayer | C123: =VLOOKUP(A123,'[10]COMBINED_ATTD_INV (3)'!$A$461:$E$485,2,FALSE) -> Kofi Bentum/Fiifi Turkson/ | D123: Williams Ananzoyaa Akandi | E123: Monday, 24 Febuary 2025 | F123: Session, 5 (3:15 PM - 4:15 PM)
A124: PB008 | B124: =VLOOKUP(A124,[10]Schedule_Invigilators!$A$108:$B$803,2,FALSE) -> Daniel Kwegyir / Peter Oppong Tawiah | C124: =VLOOKUP(A124,'[10]COMBINED_ATTD_INV (3)'!$A$461:$E$485,2,FALSE) -> Richmond Awotwe// | D124: Hasky Egyeri Fynn | E124: Monday, 24 Febuary 2025 | F124: Session, 5 (3:15 PM - 4:15 PM)
A125: PB201 | B125: =VLOOKUP(A125,[10]Schedule_Invigilators!$A$108:$B$803,2,FALSE) -> Eric Kwame Anokye Asare / F. K. A. Nyarko | C125: =VLOOKUP(A125,'[10]COMBINED_ATTD_INV (3)'!$A$461:$E$485,2,FALSE) -> Joseph Benneth Kankam// | D125: DOMPREH DERRICK EYRAM | E125: Monday, 24 Febuary 2025 | F125: Session, 5 (3:15 PM - 4:15 PM)
...

Sheet BANK DETAILS INVIGILATORS
A1: SN | B1: ACCOUNT NAME | C1: BANK | D1: ACCOUNT NUMBER | E1: BRANCH
A2: 1 | B2: GASTON EDEM AWASHIE | C2: ECOBANK | D2: 1441000158691 | E2: KNUST
A3: 2 | B3: PETER AMOAKO-YIRENKYI | C3: ZENITH BANK | D3: 4010528168 | E3: KUMASI MAIN
A4: 3 | B4: HENRY MARTIN | C4: GT BANK | D4: 2051043321590 | E4: SPINTEX
A5: 4 | B5: ABEAKU BADU ARTHUR | C5: GT BANK | D5: 3041020071590 | E5: KNUST
A6: 6 | B6: LINUS KWEKU LABIK | C6: GT BANK | D6: 203103267110 | E6: TEMA MAIN
A7: 7 | B7: RHYDAL ESI EGHAN | C7: GCB BANK | D7: 6031010229473 | E7: KNUST
A8: 8 | B8: KWAME ATTA GYAMFI | C8: GT BANK | D8: 20811212115901 | E8: ASHAIMAN BRANCH
A9: 9 | B9: CYRIL DZIEDZORM BOATENG | C9: CBG | D9: 1739700100001 | E9: HO BRANCH
A10: 10 | B10: ROBERT ACQUAH | C10: UBA | D10: 2012823101560 | E10: KNUST
A11: 11 | B11: ADU SAKYI | C11: GCB BANK | D11: 6031010188305 | E11: KNUST
A12: 12 | B12: DORCAS OYUELEY KODIE | C12: STANDARD CHARTED BANK | D12: 101960350600 | E12: KNUST
A13: 13 | B13: WILHEMINA ADOMA PELS | C13: CALBANK | D13: 1400000912699 | E13: KNUST
... A45: 51 | B45: AMOS UWUMBORAGEN BEDAKMAN | C45: CALBANK | D45: 1400004403397 | E45: KNUST
A46: 54 | B46: ISSAKAH OBED | C46: ABSA BANK | D46: 039-3579471 | E46: HO BRANCH
A47: 55 | B47: JOSHUA ATTA ALABI | C47: CALBANK | D47: 1400001033451 | E47: KNUST BRANCH
A48: 57 | B48: EMMANUEL KOFI FRIMPONG | C48: FIDELITY BANK | D48: 2100432434619 | E48: KNUST BRANCH
A49: 58 | B49: HERBERT NTIM | C49: GCB BANK | D49: 6281250011836 | E49: TECH JUNCTION
A50: 59 | B50: MICHEAL KOKONU | C50: FNB | D50: 62002162395 | E50: ACCRA MALL
A51: 60 | B51: KEVIN JOJO ARHIN | C51: CALBANK | D51: 1400005352381 | E51: KNUST
A52: 61 | B52: VICENTIA APPAIAH-AGYEI | C52: CAL BANK | D52: 1400005305798 | E52: SUAME BRANCH
A53: 62 | B53: GABRIEL KLUTSE | C53: CAL BANK | D53: 1400005430684 | E53: KNUST
A54: 63 | B54: ISAAC DOUGHAN | C54: FIDELITY BANK | D54: 2600301678417 | E54: AHODWO
A55: 64 | B55: ELIJAH ATIGAH ALADAGO | C55: GCB BANK | D55: 6031010056939 | E55: KNUST
A56: 65 | B56: JOSEPH GATI | C56: ECOBANK | D56: 1441004876662 | E56: KNUST
A57: 66 | B57: JEPHTAH OGYEFO ACQUAH | C57: FIDELITY BANK | D57: 2100431341410 | E57: KNUST
A58: 67 | B58: DORIGEN ASAMOAH | C58: ZENITH BANK | D58: 9060570065 | E58: AHODWO
... A61: 70 | B61: DERRICK MAWUSI | C61: GT BANK | D61: 3051110621700 | E61: KNUST

Sheet SUPP
A1: KWAME NKRUMAH UNIVERSITY OF SCIENCE AND TECHNOLOGY
A2: COLLEGE OF ENGINEERING
A3: FIRST SEMESTER MID SEMESTER EXAMINATIONS 2024/2025 ACADEMIC YEAR
A4: Invigilation + Meals Reumuneration
A6: SN | B6: Name | C6: Status | D6: Time/hrs | E6: Rate/Hr | F6: Total Inv. Amount | G6: Meals Amount (GHC) | H6: Amt (GHC) | I6: Tax (GHC) | J6: Amt Due (GHC) | K6: Pay Status
A7: 1 | B7: NYARKO, KWABENA BIRITWUM | C7: SM | D7: 81 | E7: 60 | F7: =D7*E7 -> 4860 | G7: 500 | H7: =F7+G7 -> 5360 | I7: =H7*0.1 -> 536 | J7: =H7-I7 -> 4824 | K7: PAYROLL
A8: 2 | B8: Ida Saeed | C8: SM | D8: 54 | E8: 60 | F8: =D8*E8 -> 3240 | G8: 500 | H8: =F8+G8 -> 3740 | I8: =H8*0.1 -> 374 | J8: =H8-I8 -> 3366 | K8: PAYROLL
A9: 3 | B9: OWUSU, JOHNSON | C9: SM | D9: 54 | E9: 60 | F9: =D9*E9 -> 3240 | G9: 500 | H9: =F9+G9 -> 3740 | I9: =H9*0.1 -> 374 | J9: =H9-I9 -> 3366 | K9: PAYROLL
A10: 4 | B10: EMMANUEL ASUMING FRIMPONG | C10: SM/Dean | D10: 64 | E10: 60 | F10: =D10*E10 -> 3840 | G10: 500 | H10: =F10+G10 -> 4340 | I10: =H10*0.1 -> 434 | J10: =H10-I10 -> 3906 | K10: PAYROLL
A11: 5 | B11: KEMAUSOUR FRANCIS | C11: SM/Dean | D11: 64 | E11: 60 | F11: =D11*E11 -> 3840 | G11: 500 | H11: =F11+G11 -> 4340 | I11: =H11*0.1 -> 434 | J11: =H11-I11 -> 3906 | K11: PAYROLL
A12: 6 | B12: ADJEI, KWAKU AMANING | C12: SM/Dean | D12: 64 | E12: 60 | F12: =D12*E12 -> 3840 | G12: 500 | H12: =F12+G12 -> 4340 | I12: =H12*0.1 -> 434 | J12: =H12-I12 -> 3906 | K12: PAYROLL
E13: Total (GHS) | H13: =SUM(H7:H12) -> 25860 | I13: =SUM(I7:I12) -> 2586 | J13: =SUM(J7:J12) -> 23274
B14: `

Sheet Invigilation + Meals(2nd Sem)
A1: KWAME NKRUMAH UNIVERSITY OF SCIENCE AND TECHNOLOGY
A2: COLLEGE OF ENGINEERING
A3: FIRST SEMESTER MID SEMESTER EXAMINATIONS 2024/2025 ACADEMIC YEAR
A4: Invigilation + Meals Reumuneration
A5: SN | B5: Name | C5: Status | D5: Time/hrs | E5: Rate/Hr | F5: Total Inv. Amount | G5: Meals Amount (GHC) | H5: Amt (GHC) | I5: Tax (GHC) | J5: Amt Due (GHC) | K5: Pay Status
A6: 1 | B6: OSEI TUTU DERRICK | C6: NSM/NSS/pro | D6: 10 | E6: 30 | F6: =D6*E6 -> 300 | G6: 150 | H6: =F6+G6 -> 450 | I6: =H6*0.1 -> 45 | J6: =H6*0.9 -> 405 | K6: CASH | M6: 30 | N6: 10
A7: 2 | B7: DOROTHY AGYEMANG AKUA | C7: NSM/NSS/pro | D7: 10 | E7: 30 | F7: =D7*E7 -> 300 | G7: 150 | H7: =F7+G7 -> 450 | I7: =H7*0.1 -> 45 | J7: =H7*0.9 -> 405 | K7: CASH | M7: 30 | N7: 10
A8: 3 | B8: DUFFOUR JUSTICE | C8: NSM/NSS/pro | D8: 10 | E8: 30 | F8: =D8*E8 -> 300 | G8: 150 | H8: =F8+G8 -> 450 | I8: =H8*0.1 -> 45 | J8: =H8*0.9 -> 405 | K8: CASH | M8: 30 | N8: 10
A9: 4 | B9: BRIGHT AMOAKO WIAFE | C9: NSM/NSS/pro | D9: 10 | E9: 30 | F9: =D9*E9 -> 300 | G9: 120 | H9: =F9+G9 -> 420 | I9: =H9*0.1 -> 42 | J9: =H9*0.9 -> 378 | K9: CASH | M9: 30 | N9: 10
A10: 5 | B10: ERICA TUTUWAA BAFFOE JNR. | C10: NSM/NSS/pro | D10: 10 | E10: 30 | F10: =D10*E10 -> 300 | G10: 120 | H10: =F10+G10 -> 420 | I10: =H10*0.1 -> 42 | J10: =H10*0.9 -> 378 | K10: CASH | M10: 30 | N10: 12
A11: 6 | B11: AARON GYAMFI ATOBRAH APRAKU | C11: NSM/NSS/pro | D11: 10 | E11: 30 | F11: =D11*E11 -> 300 | G11: 120 | H11: =F11+G11 -> 420 | I11: =H11*0.1 -> 42 | J11: =H11*0.9 -> 378 | K11: CASH | M11: 30 | N11: 12
A12: 7 | B12: AMPONSAH MICHAEL DARKO | C12: NSM/NSS/pro | D12: 10 | E12: 30 | F12: =D12*E12 -> 300 | G12: 120 | H12: =F12+G12 -> 420 | I12: =H12*0.1 -> 42 | J12: =H12*0.9 -> 378 | K12: CASH | M12: 30 | N12: 15
A13: 8 | B13: GIDEON SAKYI OSEW | C13: NSM/NSS/pro | D13: 10 | E13: 30 | F13: =D13*E13 -> 300 | G13: 120 | H13: =F13+G13 -> 420 | I13: =H13*0.1 -> 42 | J13: =H13*0.9 -> 378 | K13: CASH
A14: 9 | B14: KWABENA AFAAWUAH | C14: NSM/NSS/Acct | D14: 12 | E14: 30 | F14: =D14*E14 -> 360 | G14: 150 | H14: =F14+G14 -> 510 | I14: =H14*0.1 -> 51 | J14: =H14*0.9 -> 459 | K14: CASH
A15: 10 | B15: Cliff Obiri Sepah | C15: NSM/NSS/Acct | D15: 12 | E15: 30 | F15: =D15*E15 -> 360 | G15: 150 | H15: =F15+G15 -> 510 | I15: =H15*0.1 -> 51 | J15: =H15*0.9 -> 459 | K15: CASH
A16: 11 | B16: BAAH-BOATENG SAMUEL | C16: NSM/NSS/Acct | D16: 12 | E16: 30 | F16: =D16*E16 -> 360 | G16: 150 | H16: =F16+G16 -> 510 | I16: =H16*0.1 -> 51 | J16: =H16*0.9 -> 459 | K16: CASH
A17: 12 | B17: NANA AGYEMANG AMOAHENE YEBOAH | C17: NSM/NSS/Audit | D17: 30 | E17: 30 | F17: =D17*E17 -> 900 | G17: 450 | H17: =F17+G17 -> 1350 | I17: =H17*0.1 -> 135 | J17: =H17*0.9 -> 1215 | K17: CASH
A18: 13 | B18: KOFI POKU NNUBENG | C18: NSM/NSS/Audit | D18: 45 | E18: 30 | F18: =D18*E18 -> 1350 | G18: 450 | H18: =F18+G18 -> 1800 | I18: =H18*0.1 -> 180 | J18: =H18*0.9 -> 1620 | K18: CASH
A19: 14 | B19: CHRISTIAN D. BOATENG | C19: NSM/NSS/pro | D19: 15 | E19: =M19 -> 30 | F19: =D19*E19 -> 450 | G19: 150 | H19: =F19+G19 -> 600 | I19: =H19*0.1 -> 60 | J19: =H19*0.9 -> 540 | K19: CASH | M19: 30 | N19: 10
A20: 15 | B20: RICHARD GBENAEH | C20: NSM/NSS/ICT | D20: 35 | E20: =M20 -> 30 | F20: =D20*E20 -> 1050 | G20: 300 | H20: =F20+G20 -> 1350 | I20: =H20*0.1 -> 135 | J20: =H20*0.9 -> 1215 | K20: CASH | M20: 30 | N20: 12
A21: 16 | B21: ACQUAH FAUSTINE DARLINGTON PAPA OFORI | C21: NSM/NSS/ICT | D21: 35 | E21: =M21 -> 30 | F21: =D21*E21 -> 1050 | G21: 300 | H21: =F21+G21 -> 1350 | I21: =H21*0.1 -> 135 | J21: =H21*0.9 -> 1215 | K21: CASH | M21: 30 | N21: 12
A22: 17 | B22: HAWA MOHAMMED AMEEN | C22: NSM/NSS/ICT | D22: 35 | E22: 30 | F22: =D22*E22 -> 1050 | G22: 300 | H22: =F22+G22 -> 1350 | I22: =H22*0.1 -> 135 | J22: =H22*0.9 -> 1215 | K22: CASH | M22: 30
A23: 18 | B23: JONATHAN AGYEMAN-DUAH KARIKARI | C23: SS/procur | D23: 35 | E23: =M23 -> 30 | F23: =D23*E23 -> 1050 | G23: 300 | H23: =F23+G23 -> 1350 | I23: =H23*0.1 -> 135 | J23: =H23*0.9 -> 1215 | K23: CASH | M23: 30 | N23: 12
A24: 19 | B24: IMBEAH JULIET | C24: NSM/NSS-TA-wt | D24: 37 | E24: =M24 -> 30 | F24: =D24*E24 -> 1110 | G24: 215 | H24: =F24+G24 -> 1325 | I24: =H24*0.1 -> 132.5 | J24: =H24*0.9 -> 1192.5 | K24: CASH | M24: 30
A25: 20 | B25: OMANHENE KOFI GYIMAH | C25: NSM/NSS-TA-wt | D25: 35 | E25: 30 | F25: =D25*E25 -> 1050 | G25: 200 | H25: =F25+G25 -> 1250 | I25: =H25*0.1 -> 125 | J25: =H25*0.9 -> 1125 | K25: CASH | M25: 30
A26: 21 | B26: GARVIN KOKONU | C26: NSM/NSS-TA-wt | D26: 35 | E26: 30 | F26: =D26*E26 -> 1050 | G26: 200 | H26: =F26+G26 -> 1250 | I26: =H26*0.1 -> 125 | J26: =H26*0.9 -> 1125 | K26: CASH | M26: 30
A27: 22 | B27: VIVIAN DZAKA | C27: NSM/NSS-nurs | D27: 55 | E27: =M27 -> 30 | F27: =D27*E27 -> 1650 | G27: 450 | H27: =F27+G27 -> 2100 | I27: =H27*0.1 -> 210 | J27: =H27*0.9 -> 1890 | K27: CASH | M27: 30 | N27: 55
A28: 23 | B28: BENEDICTA OSEI | C28: NSM/NSS-nurs | D28: 55 | E28: =M28 -> 30 | F28: =D28*E28 -> 1650 | G28: 450 | H28: =F28+G28 -> 2100 | I28: =H28*0.1 -> 210 | J28: =H28*0.9 -> 1890 | K28: CASH | M28: 30
A29: 24 | B29: Abdul-Mumin Tahiru | C29: NSM/NSS-TA | D29: 18 | E29: 30 | F29: 540 | G29: 270 | H29: 810 | I29: 81 | J29: 729 | K29: CASH | M29: 30 | N29: 55
A30: 25 | B30: Aboh Doreen Kumiwaa | C30: NSM/NSS-TA | D30: 18 | E30: 30 | F30: 540 | G30: 270 | H30: 810 | I30: 81 | J30: 729 | K30: CASH | M30: 30 | N30: 55 | O30: 15
A31: 26 | B31: Akambisa Julius | C31: NSM/NSS-TA | D31: 16 | E31: 30 | F31: 480 | G31: 240 | H31: 720 | I31: 72 | J31: 648 | K31: CASH | M31: 30 | N31: 62
A32: 27 | B32: Adu Isaac Kwabena Afriyie | C32: NSM/NSS-TA | D32: 16 | E32: 30 | F32: 480 | G32: 240 | H32: 720 | I32: 72 | J32: 648 | K32: CASH | M32: 30 | N32: 62
A33: 28 | B33: Alhassan Abdul Ganiyu | C33: NSM/NSS-TA | D33: 19 | E33: 30 | F33: 570 | G33: 285 | H33: 855 | I33: 85.5 | J33: 769.5 | K33: CASH | M33: 30 | N33: 62
A34: 29 | B34: Amissah Nana Ama | C34: NSM/NSS-TA | D34: 20 | E34: 30 | F34: 600 | G34: 300 | H34: 900 | I34: 90 | J34: 810 | K34: CASH | M34: 30 | N34: 62
A35: 30 | B35: Anita Dokuwah Nyarko | C35: NSM/NSS-TA | D35: 20 | E35: 30 | F35: 600 | G35: 300 | H35: 900 | I35: 90 | J35: 810 | K35: CASH | M35: 30 | N35: 10
A36: 31 | B36: Akowuah Nana Amoah | C36: NSM/NSS-TA | D36: 18 | E36: 30 | F36: 540 | G36: 270 | H36: 810 | I36: 81 | J36: 729 | K36: CASH | M36: 30 | N36: 10
A37: 32 | B37: Ankomah Theophilus | C37: NSM/NSS-TA | D37: 17 | E37: 30 | F37: 510 | G37: 255 | H37: 765 | I37: 76.5 | J37: 688.5 | K37: CASH | M37: 30 | N37: 9
A38: 33 | B38: AGYEMANG BADU RICHARD | C38: NSM/NSS-TA | D38: 2 | E38: 30 | F38: 60 | G38: 15 | H38: 75 | I38: 7.5 | J38: =H38*0.9 -> 67.5 | K38: CASH | M38: 30
A39: 34 | B39: PADI CATHERINE NARKIE | C39: NSM/NSS-TA | D39: 2 | E39: 30 | F39: 60 | G39: 15 | H39: 75 | I39: 7.5 | J39: =H39*0.9 -> 67.5 | K39: CASH | M39: 30
A40: 35 | B40: Antwi Dennis Barima | C40: NSM/NSS-TA | D40: 17 | E40: 30 | F40: 510 | G40: 255 | H40: 765 | I40: 76.5 | J40: 688.5 | K40: CASH | M40: 30
A41: 36 | B41: Dzah Raymond | C41: NSM/NSS-TA | D41: 18 | E41: 30 | F41: 540 | G41: 255 | H41: 810 | I41: 81 | J41: 729 | K41: CASH | M41: 30 | N41: 15
A42: 37 | B42: Dadzie Emmanuel | C42: NSM/NSS-TA | D42: 17 | E42: 30 | F42: 510 | G42: 255 | H42: 765 | I42: 76.5 | J42: 688.5 | K42: CASH | M42: 30 | N42: 11
A43: 38 | B43: Egyir Bernard | C43: NSM/NSS-TA | D43: 17 | E43: 30 | F43: 510 | G43: 255 | H43: 765 | I43: 76.5 | J43: 688.5 | K43: CASH | M43: 30 | N43: 21
A44: 39 | B44: Ekuful Ebenezer | C44: NSM/NSS-TA | D44: 21 | E44: 30 | F44: 630 | G44: 315 | H44: 945 | I44: 94.5 | J44: 850.5 | K44: CASH | M44: 30
A45: 40 | B45: Felix Owiredu Owusu | C45: NSM/NSS-TA | D45: 22 | E45: 30 | F45: 660 | G45: 330 | H45: 990 | I45: 99 | J45: 891 | K45: CASH | M45: 30 | N45: 14
A46: 41 | B46: George Nii Martey Colley | C46: NSM/NSS-TA | D46: 18 | E46: 30 | F46: 540 | G46: 270 | H46: 810 | I46: 81 | J46: 729 | K46: CASH | M46: 30 | N46: 10
A47: 42 | B47: Immanuel Yeboah Anomah | C47: NSM/NSS-TA | D47: 18 | E47: 30 | F47: 540 | G47: 270 | H47: 810 | I47: 81 | J47: 729 | K47: CASH | M47: 30 | N47: 11
A48: 43 | B48: Isaac Adu | C48: NSM/NSS-TA | D48: 18 | E48: 30 | F48: 540 | G48: 270 | H48: 810 | I48: 81 | J48: 729 | K48: CASH | M48: 30 | N48: 10
A49: 44 | B49: Isaac Clottey | C49: NSM/NSS-TA | D49: 19 | E49: 30 | F49: 570 | G49: 285 | H49: 855 | I49: 85.5 | J49: 769.5 | K49: CASH | M49: 30 | N49: 8
A50: 45 | B50: Jeremiah Dodzi Cofie | C50: NSM/NSS-TA | D50: 21 | E50: 30 | F50: 630 | G50: 315 | H50: 945 | I50: 94.5 | J50: 850.5 | K50: CASH | M50: 30 | N50: 6
A51: 46 | B51: Jibril Aligabass | C51: NSM/NSS-TA | D51: 16 | E51: 30 | F51: 480 | G51: 240 | H51: 720 | I51: 72 | J51: 648 | K51: CASH | M51: 30 | N51: 8
A52: 47 | B52: Owusu Binfoh Romeo | C52: NSM/NSS-TA | D52: 16 | E52: 30 | F52: 480 | G52: 240 | H52: 720 | I52: 72 | J52: 648 | K52: CASH | M52: 30 | N52: 8
A53: 48 | B53: Priscilla Adwoa Fordjour | C53: NSM/NSS-TA | D53: 18 | E53: 30 | F53: 540 | G53: 270 | H53: 810 | I53: 81 | J53: 729 | K53: CASH | M53: 30 | N53: 8
A54: 49 | B54: Solomon Appiah-Gyamfi | C54: NSM/NSS-TA | D54: 17 | E54: 30 | F54: 510 | G54: 255 | H54: 765 | I54: 76.5 | J54: 688.5 | K54: CASH | M54: 30 | N54: 8
A55: 50 | B55: Stephen Onomah | C55: NSM/NSS-TA | D55: 17 | E55: 30 | F55: 510 | G55: 255 | H55: 765 | I55: 76.5 | J55: 688.5 | K55: CASH | M55: 30 | N55: 8
A56: 51 | B56: Theophilus Nyarko | C56: NSM/NSS-TA | D56: 18 | E56: 30 | F56: 540 | G56: 270 | H56: 810 | I56: 81 | J56: 729 | K56: CASH | M56: 30 | N56: 7
... A64: 59 | B64: ABAGRE MAJEED WINIMI | C64: NSM/NSS-TA | D64: 10 | E64: 30 | F64: 300 | G64: 150 | H64: 450 | I64: 45 | J64: 405 | K64: CASH | M64: 30 | N64: 6
A65: 60 | B65: ABDUL-BASIT NUHU | C65: NSM/NSS-TA | D65: 9 | E65: 30 | F65: 270 | G65: 135 | H65: 405 | I65: 40.5 | J65: 364.5 | K65: CASH | M65: 30
A66: 61 | B66: ABIGAIL ANKU | C66: NSM/NSS-TA | D66: 5 | E66: 30 | F66: 150 | G66: 75 | H66: 225 | I66: 22.5 | J66: 202.5 | K66: CASH | M66: 30 | N66: 35
A67: 62 | B67: ADDO THOMAS | C67: NSM/NSS-TA | D67: 9 | E67: 30 | F67: 270 | G67: 135 | H67: 405 | I67: 40.5 | J67: 364.5 | K67: CASH | M67: 30 | N67: 35
A68: 63 | B68: AGBE SETORDZI GAMELI | C68: NSM/NSS-TA | D68: 6 | E68: 30 | F68: 180 | G68: 90 | H68: 270 | I68: 27 | J68: 243 | K68: CASH | M68: 30 | N68: 25
A69: 64 | B69: AGBLEMIAWO MARVIN SELASI | C69: NSM/NSS-TA | D69: 9 | E69: 30 | F69: 270 | G69: 135 | H69: 405 | I69: 40.5 | J69: 364.5 | K69: CASH | M69: 30 | N69: 25
A70: 65 | B70: AGYAPONG AKOSUA ADUBEA | C70: NSM/NSS-TA | D70: 5 | E70: 30 | F70: 150 | G70: 75 | H70: 225 | I70: 22.5 | J70: 202.5 | K70: CASH | M70: 30 | N70: 25
A71: 66 | B71: AGYAPONG DORCAS NUANIAH | C71: NSM/NSS-TA | D71: 2 | E71: 30 | F71: 60 | G71: 30 | H71: 90 | I71: 9 | J71: 81 | K71: CASH | M71: 30 | N71: 25
A72: 67 | B72: AGYEMANG DUKU RISMOND | C72: NSM/NSS-TA | D72: 2 | E72: 30 | F72: 60 | G72: 30 | H72: 90 | I72: 9 | J72: 81 | K72: CASH | M72: 30 | N72: 25
A73: 68 | B73: AKUA BOADIWAA | C73: NSM/NSS-TA | D73: 1 | E73: 30 | F73: 30 | G73: 15 | H73: 45 | I73: 4.5 | J73: 40.5 | K73: CASH | M73: 30 | N73: 25
A74: 69 | B74: ALHASSAN ABDUL GANIYU | C74: NSM/NSS-TA | D74: 5 | E74: 30 | F74: 150 | G74: 75 | H74: 225 | I74: 22.5 | J74: 202.5 | K74: CASH | M74: 30 | N74: 25
A75: 70 | B75: ALHASSAN MUBARIK | C75: NSM/NSS-TA | D75: 6 | E75: 30 | F75: 180 | G75: 90 | H75: 270 | I75: 27 | J75: 243 | K75: CASH | M75: 30 | N75: 25
A76: 71 | B76: ALI MUHAISIN | C76: NSM/NSS-TA | D76: 8 | E76: 30 | F76: 240 | G76: 120 | H76: 360 | I76: 36 | J76: 324 | K76: CASH | M76: 30 | N76: 25
A77: 72 | B77: ANITA DOKUWAH NYARKO | C77: NSM/NSS-TA | D77: 6 | E77: 30 | F77: 180 | G77: 90 | H77: 270 | I77: 27 | J77: 243 | K77: CASH | M77: 30 | N77: 25
... A106: 101 | B106: FAISAL IHUNNANG NURIDEEN | C106: NSM/NSS-TA | D106: 6 | E106: 30 | F106: 180 | G106: 90 | H106: 270 | I106: 27 | J106: 243 | K106: CASH | M106: 30 | N106: 25
A107: 102 | B107: FRANK ODURO | C107: NSM/NSS-TA | D107: 3 | E107: 30 | F107: 90 | G107: 45 | H107: 135 | I107: 13.5 | J107: 121.5 | K107: CASH | M107: 30
A108: 103 | B108: FRANK OWUSU BOAKYE | C108: NSM/NSS-TA | D108: 7 | E108: 30 | F108: 210 | G108: 105 | H108: 315 | I108: 31.5 | J108: 283.5 | K108: CASH | M108: 30 | N108: 25
A109: 104 | B109: FREDINALD B. HAYFORD | C109: NSM/NSS-TA | D109: 6 | E109: 30 | F109: 180 | G109: 90 | H109: 270 | I109: 27 | J109: 243 | K109: CASH | M109: 30 | N109: 25
A110: 105 | B110: GYAMFI MORRIS AKWASI | C110: NSM/NSS-TA | D110: 8 | E110: 30 | F110: 240 | G110: 120 | H110: 360 | I110: 36 | J110: 324 | K110: CASH | M110: 30 | N110: 14
A111: 106 | B111: GYANO CHARTY JOSEPH | C111: NSM/NSS-TA | D111: 7 | E111: 30 | F111: 210 | G111: 105 | H111: 315 | I111: 31.5 | J111: 283.5 | K111: CASH | M111: 30
A112: 107 | B112: HASKY EGYERI FYNN | C112: NSM/NSS-TA | D112: 7 | E112: 30 | F112: 210 | G112: 105 | H112: 315 | I112: 31.5 | J112: 283.5 | K112: CASH | M112: 30 | N112: 30
A113: 108 | B113: IBRAHIM ARHIN | C113: NSM/NSS-TA | D113: 6 | E113: 30 | F113: 180 | G113: 90 | H113: 270 | I113: 27 | J113: 243 | K113: CASH | M113: 30 | N113: 16
A114: 109 | B114: ISAAC DANSO | C114: NSM/NSS-TA | D114: 9 | E114: 30 | F114: 270 | G114: 135 | H114: 405 | I114: 40.5 | J114: 364.5 | K114: CASH | M114: 30 | N114: 18
A115: 110 | B115: ISAIAH AMPONSAH | C115: NSM/NSS-TA | D115: 6 | E115: 30 | F115: 180 | G115: 90 | H115: 270 | I115: 27 | J115: 243 | K115: CASH | M115: 30 | N115: 14
A116: 111 | B116: ISSAH ABDUL GANIWU GENE | C116: NSM/NSS-TA | D116: 10 | E116: 30 | F116: 300 | G116: 150 | H116: 450 | I116: 45 | J116: 405 | K116: CASH | M116: 30
A117: 112 | B117: ISSIFU FREDRICK ALI | C117: NSM/NSS-TA | D117: 7 | E117: 30 | F117: 210 | G117: 105 | H117: 315 | I117: 31.5 | J117: 283.5 | K117: CASH | M117: 30 | N117: 18
A118: 113 | B118: JOHN KWESI BAIDOO | C118: NSM/NSS-TA | D118: 7 | E118: 30 | F118: 210 | G118: 105 | H118: 315 | I118: 31.5 | J118: 283.5 | K118: CASH | M118: 30 | N118: 16
A119: 114 | B119: JOHN YAW GYASI-MENSAH | C119: NSM/NSS-TA | D119: 7 | E119: 30 | F119: 210 | G119: 105 | H119: 315 | I119: 31.5 | J119: 283.5 | K119: CASH | M119: 30
A120: 115 | B120: JOSEPH DELA AZIAFOR | C120: NSM/NSS-TA | D120: 12 | E120: 30 | F120: 360 | G120: 180 | H120: 540 | I120: 54 | J120: 486 | K120: CASH | M120: 30
A121: 116 | B121: JOSEPH DERRICK ANANE NTI KODUAH | C121: NSM/NSS-TA | D121: 9 | E121: 30 | F121: 270 | G121: 135 | H121: 405 | I121: 40.5 | J121: 364.5 | K121: CASH | M121: 30 | N121: 10
A122: 117 | B122: JULIET ARTHUR | C122: NSM/NSS-TA | D122: 6 | E122: 30 | F122: 180 | G122: 90 | H122: 270 | I122: 27 | J122: 243 | K122: CASH | M122: 30 | N122: 10
A123: 118 | B123: KATE NYARKO BOADI | C123: NSM/NSS-TA | D123: 11 | E123: 30 | F123: 330 | G123: 165 | H123: 495 | I123: 49.5 | J123: 445.5 | K123: CASH | M123: 30
A124: 119 | B124: KOBINA AKOFI-HOLISON | C124: NSM/NSS-TA | D124: 6 | E124: 30 | F124: 180 | G124: 90 | H124: 270 | I124: 27 | J124: 243 | K124: CASH | M124: 30
A125: 120 | B125: KUYINI ANISUMA SALMA | C125: NSM/NSS-TA | D125: 7 | E125: 30 | F125: 210 | G125: 105 | H125: 315 | I125: 31.5 | J125: 283.5 | K125: CASH | M125: 30
A126: 121 | B126: KWABENA OWUSU-OSEI | C126: NSM/NSS-TA | D126: 8 | E126: 30 | F126: 240 | G126: 120 | H126: 360 | I126: 36 | J126: 324 | K126: CASH | M126: 30 | N126: 14
A127: 122 | B127: KWAME MOSES | C127: NSM/NSS-TA | D127: 6 | E127: 30 | F127: 180 | G127: 90 | H127: 270 | I127: 27 | J127: 243 | K127: CASH | M127: 30 | N127: 14
A128: 123 | B128: MACKLEODE BEN-BOULO | C128: NSM/NSS-TA | D128: 7 | E128: 30 | F128: 210 | G128: 105 | H128: 315 | I128: 31.5 | J128: 283.5 | K128: CASH | M128: 30 | N128: 2
A129: 124 | B129: MALICK ABIASAH | C129: NSM/NSS-TA | D129: 10 | E129: 30 | F129: 300 | G129: 130 | H129: 430 | I129: =H129*0.1 -> 43 | J129: =H129*0.9 -> 387 | K129: CASH | M129: 30
A130: 125 | B130: MARUF USMAN | C130: NSM/NSS-TA | D130: 8 | E130: 30 | F130: 240 | G130: 120 | H130: 360 | I130: 36 | J130: 324 | K130: CASH | M130: 30
A131: 126 | B131: MATE-KOLE NYAKO GORTLIEB | C131: NSM/NSS-TA | D131: 10 | E131: 30 | F131: 300 | G131: 150 | H131: 450 | I131: 45 | J131: 405 | K131: CASH | M131: 30
A132: 127 | B132: MAWULI DOGBATSE | C132: NSM/NSS-TA | D132: 10 | E132: 30 | F132: 300 | G132: 150 | H132: 450 | I132: 45 | J132: 405 | K132: CASH | M132: 30
A133: 128 | B133: MERCY BOAKYE | C133: NSM/NSS-TA | D133: 10 | E133: 30 | F133: 300 | G133: 150 | H133: 450 | I133: 45 | J133: 405 | K133: CASH | M133: 30
A134: 129 | B134: MICHAEL BANSAH | C134: NSM/NSS-TA | D134: 12 | E134: 30 | F134: 360 | G134: 180 | H134: 540 | I134: 54 | J134: 486 | K134: CASH | M134: 30
A135: 130 | B135: MILDRED MARTETSOO MARTEY | C135: NSM/NSS-TA | D135: 1 | E135: 30 | F135: 30 | G135: 15 | H135: 45 | I135: 4.5 | J135: 40.5 | K135: CASH | M135: 30
...
